Workbook

Sheet МТР
A1: № КС | B1: Шифр сметы | C1: 1 - Труд 2 - ЭММ 3 - МАТ | D1: Column5 | E1: Обоснование | F1: Наименование | G1: Ед. изм. | H1: Расход | I1: Базовая цена | J1: Стоимость | K1: =1-SUMIFS(K2:K1590,O2:O1590,"") -> 0.88237884 | L1: #1 | M1: #2 | N1: #3 | O1: Средняя цена, EGP, без НДС | P1: Наименование 1 | Q1: ЕдИзм1 | R1: Цена1 на площадке, EGP без НДС | S1: ДатаЦены1 | T1: Поставщик1 | U1: Обоснование1 | V1: Наименование 2 | W1: ЕдИзм2 | X1: Цена2 на площадке, EGP без НДС | Y1: ДатаЦены2 | Z1: Поставщик2 | AA1: Обоснование2 | AB1: Наименование 3 | AC1: ЕдИзм3 | AD1: Цена3 на площадке, EGP без НДС | AE1: ДатаЦены3 | AF1: Поставщик3 | AG1: Обоснование3 | AH1: ID1 | AI1: ID2 | AJ1: ID3
A2: 2 | B2: ЛСР-03-08-201ТМ | C2: 3 | E2: ТЦ_23.7.01.02_31_3123315768_20.05.2022_02/ КА п.1/ ООО "Белэнергомаш-БЗЭМ" №006-00073 | F2: Трубопроводы низкого давления из нержавеющей стали 4 класса безопасности Ду > 80мм_ DN 900 | G2: т | H2: 44.174 | I2: 799960.85 | J2: =H2*I2 -> 35337471 | K2: =J2/SUM($J$2:$J$1590) -> 0.27672821 | L2: =IFERROR(INDEX([1]мтр!G:G,MATCH($F2,[1]мтр!$C:$C,0)),"") -> 4861 | M2: =IFERROR(INDEX([1]мтр!H:H,MATCH($F2,[1]мтр!$C:$C,0)),"") -> 0 | N2: =IFERROR(INDEX([1]мтр!I:I,MATCH($F2,[1]мтр!$C:$C,0)),"") -> 0 | O2: =IFERROR(AVERAGE(R2,X2,AD2),"") -> 2050605.2 | P2: =IFERROR(INDEX([2]Лист1!$E:$E,AH2),"") -> Трубопроводы низкого давления из нержавеющей стали зданий UJA, UKD. Объём: 40 315 616 руб. / 6 074,16 кг = 6637 RUB/кг. Транспорт 5800 USD (Договор ЕОС-закупки №629007, №7720/220816 от 07.09.2022, АСЭ_Рускон) /40DV контейнер 25 т, класс груза - 2, загрузка 85%. | Q2: =IFERROR(INDEX([2]Лист1!$I:$I,AH2),"") -> т | R2: =IFERROR(INDEX([2]Лист1!$V:$V,AH2),"") -> 2050605.2 | S2: =IFERROR(INDEX([2]Лист1!$L:$L,AH2),"") -> 44753 | T2: =IFERROR(INDEX([2]Лист1!$J:$J,AH2),"") -> Белэнергомаш-БЗЭМ | U2: =IFERROR(INDEX([2]Лист1!$K:$K,AH2),"") -> Поставка трубопроводов по лоту 19677-248 Куд3;4. НМЦ от 11.07.2022, рассчитанная на основании п.1 раздела 3 главы 3 (приложения №8 к ЕОСЗ). | V2: =IFERROR(INDEX([2]Лист1!$E:$E,AI2),"") | W2: =IFERROR(INDEX([2]Лист1!$I:$I,AI2),"") | X2: =IFERROR(INDEX([2]Лист1!$V:$V,AI2),"") | Y2: =IFERROR(INDEX([2]Лист1!$L:$L,AI2),"") | Z2: =IFERROR(INDEX([2]Лист1!$J:$J,AI2),"") | AA2: =IFERROR(INDEX([2]Лист1!$K:$K,AI2),"") | AB2: =IFERROR(INDEX([2]Лист1!$E:$E,AJ2),"") | AC2: =IFERROR(INDEX([2]Лист1!$I:$I,AJ2),"") | AD2: =IFERROR(INDEX([2]Лист1!$V:$V,AJ2),"") | AE2: =IFERROR(INDEX([2]Лист1!$L:$L,AJ2),"") | AF2: =IFERROR(INDEX([2]Лист1!$J:$J,AJ2),"") | AG2: =IFERROR(INDEX([2]Лист1!$K:$K,AJ2),"") | AH2: =MATCH(L2,[2]Лист1!$A:$A,0) -> 4798 | AI2: =MATCH(M2,[2]Лист1!$A:$A,0) -> #N/A | AJ2: =MATCH(N2,[2]Лист1!$A:$A,0) -> #N/A
A3: 1 | B3: ЛСР-03-05-602Э | C3: 3 | E3: ТЦ_20.2.07.00_31.03.2022_01/КА табл.1, п.2/WIBE Group в России/ED.B.P000.&.1104&&&&&&&&.031.TD.0001 | F3: Конструкции кабельные разных размеров, включая стойки, полки, лотки, короба | G3: кг | H3: 27000 | I3: 398.56 | J3: =H3*I3 -> 10761120 | K3: =J3/SUM($J$2:$J$1590) -> 0.084270475 | L3: =IFERROR(INDEX([1]мтр!G:G,MATCH($F3,[1]мтр!$C:$C,0)),"") -> 3411 | M3: =IFERROR(INDEX([1]мтр!H:H,MATCH($F3,[1]мтр!$C:$C,0)),"") -> 0 | N3: =IFERROR(INDEX([1]мтр!I:I,MATCH($F3,[1]мтр!$C:$C,0)),"") -> 0 | O3: =IFERROR(AVERAGE(R3,X3,AD3),"") -> 448.64572 | P3: =IFERROR(INDEX([2]Лист1!$E:$E,AH3),"") -> Конструкции кабельные разных размеров (стойки, полки, лотки, короб и т.д.) из горячеоцинкованной стали на основе спецификаций материалов проекта ЛАЭС-2.Транспорт экспертно 5% | Q3: =IFERROR(INDEX([2]Лист1!$I:$I,AH3),"") -> кг | R3: =IFERROR(INDEX([2]Лист1!$V:$V,AH3),"") -> 448.64572 | S3: =IFERROR(INDEX([2]Лист1!$L:$L,AH3),"") -> 44344 | T3: =IFERROR(INDEX([2]Лист1!$J:$J,AH3),"") -> Schneider Electric | U3: =IFERROR(INDEX([2]Лист1!$K:$K,AH3),"") -> Письмо от 28.05.2021 | V3: =IFERROR(INDEX([2]Лист1!$E:$E,AI3),"") | W3: =IFERROR(INDEX([2]Лист1!$I:$I,AI3),"") | X3: =IFERROR(INDEX([2]Лист1!$V:$V,AI3),"") | Y3: =IFERROR(INDEX([2]Лист1!$L:$L,AI3),"") | Z3: =IFERROR(INDEX([2]Лист1!$J:$J,AI3),"") | AA3: =IFERROR(INDEX([2]Лист1!$K:$K,AI3),"") | AB3: =IFERROR(INDEX([2]Лист1!$E:$E,AJ3),"") | AC3: =IFERROR(INDEX([2]Лист1!$I:$I,AJ3),"") | AD3: =IFERROR(INDEX([2]Лист1!$V:$V,AJ3),"") | AE3: =IFERROR(INDEX([2]Лист1!$L:$L,AJ3),"") | AF3: =IFERROR(INDEX([2]Лист1!$J:$J,AJ3),"") | AG3: =IFERROR(INDEX([2]Лист1!$K:$K,AJ3),"") | AH3: =MATCH(L3,[2]Лист1!$A:$A,0) -> 2824 | AI3: =MATCH(M3,[2]Лист1!$A:$A,0) -> #N/A | AJ3: =MATCH(N3,[2]Лист1!$A:$A,0) -> #N/A
A4: 1 | B4: ЛСР-03-05-206ТМ | C4: 3 | E4: ТЦ_23.7.01.02_31_3123315768_20.05.2022_02/ КА п.78/ ООО "Белэнергомаш-БЗЭМ" №006-00073 | F4: Трубопроводы низкого давления из нержавеющей стали 4 класса безопасности Ду > 80мм_ DN 900 | G4: т | H4: 4.554 | I4: 799960.85 | J4: =H4*I4 -> 3643021.7 | K4: =J4/SUM($J$2:$J$1590) -> 0.028528552 | L4: =IFERROR(INDEX([1]мтр!G:G,MATCH($F4,[1]мтр!$C:$C,0)),"") -> 4861 | M4: =IFERROR(INDEX([1]мтр!H:H,MATCH($F4,[1]мтр!$C:$C,0)),"") -> 0 | N4: =IFERROR(INDEX([1]мтр!I:I,MATCH($F4,[1]мтр!$C:$C,0)),"") -> 0 | O4: =IFERROR(AVERAGE(R4,X4,AD4),"") -> 2050605.2 | P4: =IFERROR(INDEX([2]Лист1!$E:$E,AH4),"") -> Трубопроводы низкого давления из нержавеющей стали зданий UJA, UKD. Объём: 40 315 616 руб. / 6 074,16 кг = 6637 RUB/кг. Транспорт 5800 USD (Договор ЕОС-закупки №629007, №7720/220816 от 07.09.2022, АСЭ_Рускон) /40DV контейнер 25 т, класс груза - 2, загрузка 85%. | Q4: =IFERROR(INDEX([2]Лист1!$I:$I,AH4),"") -> т | R4: =IFERROR(INDEX([2]Лист1!$V:$V,AH4),"") -> 2050605.2 | S4: =IFERROR(INDEX([2]Лист1!$L:$L,AH4),"") -> 44753 | T4: =IFERROR(INDEX([2]Лист1!$J:$J,AH4),"") -> Белэнергомаш-БЗЭМ | U4: =IFERROR(INDEX([2]Лист1!$K:$K,AH4),"") -> Поставка трубопроводов по лоту 19677-248 Куд3;4. НМЦ от 11.07.2022, рассчитанная на основании п.1 раздела 3 главы 3 (приложения №8 к ЕОСЗ). | V4: =IFERROR(INDEX([2]Лист1!$E:$E,AI4),"") | W4: =IFERROR(INDEX([2]Лист1!$I:$I,AI4),"") | X4: =IFERROR(INDEX([2]Лист1!$V:$V,AI4),"") | Y4: =IFERROR(INDEX([2]Лист1!$L:$L,AI4),"") | Z4: =IFERROR(INDEX([2]Лист1!$J:$J,AI4),"") | AA4: =IFERROR(INDEX([2]Лист1!$K:$K,AI4),"") | AB4: =IFERROR(INDEX([2]Лист1!$E:$E,AJ4),"") | AC4: =IFERROR(INDEX([2]Лист1!$I:$I,AJ4),"") | AD4: =IFERROR(INDEX([2]Лист1!$V:$V,AJ4),"") | AE4: =IFERROR(INDEX([2]Лист1!$L:$L,AJ4),"") | AF4: =IFERROR(INDEX([2]Лист1!$J:$J,AJ4),"") | AG4: =IFERROR(INDEX([2]Лист1!$K:$K,AJ4),"") | AH4: =MATCH(L4,[2]Лист1!$A:$A,0) -> 4798 | AI4: =MATCH(M4,[2]Лист1!$A:$A,0) -> #N/A | AJ4: =MATCH(N4,[2]Лист1!$A:$A,0) -> #N/A
A5: 1 | B5: ЛСР-03-05-203ТМ | C5: 3 | E5: ТЦ_18.1.06.00_50_5503095632_05.07.2022_02/ КА п.70/ ЗАО "Сибгазстройдеталь" №897 | F5: Запорная арматура По типу 1156-125-М DN 125; pmax=1.10 MPag; tmax=40 °С / °C; Раб. среда:Вода химически обессоленная; Способ управления: Ручной привод; Тип присоединения: Под приварку, Кл4Н, угл.ст. | G5: шт. | H5: 16 | I5: 226407.66 | J5: =H5*I5 -> 3622522.6 | K5: =J5/SUM($J$2:$J$1590) -> 0.028368023 | L5: 7311 | M5: =IFERROR(INDEX([1]мтр!H:H,MATCH($F5,[1]мтр!$C:$C,0)),"") | N5: =IFERROR(INDEX([1]мтр!I:I,MATCH($F5,[1]мтр!$C:$C,0)),"") | O5: =IFERROR(AVERAGE(R5,X5,AD5),"") -> 0 | P5: =IFERROR(INDEX([2]Лист1!$E:$E,AH5),"") -> 0 | Q5: =IFERROR(INDEX([2]Лист1!$I:$I,AH5),"") -> 0 | R5: =IFERROR(INDEX([2]Лист1!$V:$V,AH5),"") -> 0 | S5: =IFERROR(INDEX([2]Лист1!$L:$L,AH5),"") -> 0 | T5: =IFERROR(INDEX([2]Лист1!$J:$J,AH5),"") -> 0 | U5: =IFERROR(INDEX([2]Лист1!$K:$K,AH5),"") -> 0 | V5: =IFERROR(INDEX([2]Лист1!$E:$E,AI5),"") | W5: =IFERROR(INDEX([2]Лист1!$I:$I,AI5),"") | X5: =IFERROR(INDEX([2]Лист1!$V:$V,AI5),"") | Y5: =IFERROR(INDEX([2]Лист1!$L:$L,AI5),"") | Z5: =IFERROR(INDEX([2]Лист1!$J:$J,AI5),"") | AA5: =IFERROR(INDEX([2]Лист1!$K:$K,AI5),"") | AB5: =IFERROR(INDEX([2]Лист1!$E:$E,AJ5),"") | AC5: =IFERROR(INDEX([2]Лист1!$I:$I,AJ5),"") | AD5: =IFERROR(INDEX([2]Лист1!$V:$V,AJ5),"") | AE5: =IFERROR(INDEX([2]Лист1!$L:$L,AJ5),"") | AF5: =IFERROR(INDEX([2]Лист1!$J:$J,AJ5),"") | AG5: =IFERROR(INDEX([2]Лист1!$K:$K,AJ5),"") | AH5: =MATCH(L5,[2]Лист1!$A:$A,0) -> 6377 | AI5: =MATCH(M5,[2]Лист1!$A:$A,0) -> #N/A | AJ5: =MATCH(N5,[2]Лист1!$A:$A,0) -> #N/A
A6: 1 | B6: ЛСР-03-05-501ОВ | C6: 3 | E6: ТЦ_12.2.04.12_24_7709046921_28.03.2022_02 / КА п.1 / АО "Фирма Энергозащита" №00000000373 от 8.03.2022г. | F6: Маты прошивные из базальтового штапельного волокна МБПЭ 4-50 КТ-11, толщ=50 mm | G6: м3 | H6: 225 | I6: 10887.18 | J6: =H6*I6 -> 2449615.5 | K6: =J6/SUM($J$2:$J$1590) -> 0.019182972 | L6: =IFERROR(INDEX([1]мтр!G:G,MATCH($F6,[1]мтр!$C:$C,0)),"") -> 7501 | M6: =IFERROR(INDEX([1]мтр!H:H,MATCH($F6,[1]мтр!$C:$C,0)),"") -> 0 | N6: =IFERROR(INDEX([1]мтр!I:I,MATCH($F6,[1]мтр!$C:$C,0)),"") -> 0 | O6: =IFERROR(AVERAGE(R6,X6,AD6),"") -> 30253.766 | P6: =IFERROR(INDEX([2]Лист1!$E:$E,AH6),"") -> Маты базальтовые прошивные энергетические в обкладке из кремнеземистой ткани КТ-11 со всех сторон МБПЭ-4-50 2000.1000.50 | Q6: =IFERROR(INDEX([2]Лист1!$I:$I,AH6),"") -> м3 | R6: =IFERROR(INDEX([2]Лист1!$V:$V,AH6),"") -> 30253.766 | S6: =IFERROR(INDEX([2]Лист1!$L:$L,AH6),"") -> 44994 | T6: =IFERROR(INDEX([2]Лист1!$J:$J,AH6),"") -> АО "Фирма Энергозащита" | U6: =IFERROR(INDEX([2]Лист1!$K:$K,AH6),"") -> КП №000-000387 от 09.03.2023 | V6: =IFERROR(INDEX([2]Лист1!$E:$E,AI6),"") | W6: =IFERROR(INDEX([2]Лист1!$I:$I,AI6),"") | X6: =IFERROR(INDEX([2]Лист1!$V:$V,AI6),"") | Y6: =IFERROR(INDEX([2]Лист1!$L:$L,AI6),"") | Z6: =IFERROR(INDEX([2]Лист1!$J:$J,AI6),"") | AA6: =IFERROR(INDEX([2]Лист1!$K:$K,AI6),"") | AB6: =IFERROR(INDEX([2]Лист1!$E:$E,AJ6),"") | AC6: =IFERROR(INDEX([2]Лист1!$I:$I,AJ6),"") | AD6: =IFERROR(INDEX([2]Лист1!$V:$V,AJ6),"") | AE6: =IFERROR(INDEX([2]Лист1!$L:$L,AJ6),"") | AF6: =IFERROR(INDEX([2]Лист1!$J:$J,AJ6),"") | AG6: =IFERROR(INDEX([2]Лист1!$K:$K,AJ6),"") | AH6: =MATCH(L6,[2]Лист1!$A:$A,0) -> 6567 | AI6: =MATCH(M6,[2]Лист1!$A:$A,0) -> #N/A | AJ6: =MATCH(N6,[2]Лист1!$A:$A,0) -> #N/A
A7: 1 | B7: ЛСР-03-05-501ОВ | C7: 3 | E7: ТЦ_12.2.04.12_24_7709046921_28.03.2022_02 / КА п.1 / АО "Фирма Энергозащита" №00000000373 от 8.03.2022г. | F7: Маты прошивные из базальтового штапельного волокна МБПЭ 4-50 КТ-11, толщ=50 mm | G7: м3 | H7: 225 | I7: 10887.18 | J7: =H7*I7 -> 2449615.5 | K7: =J7/SUM($J$2:$J$1590) -> 0.019182972 | L7: =IFERROR(INDEX([1]мтр!G:G,MATCH($F7,[1]мтр!$C:$C,0)),"") -> 7501 | M7: =IFERROR(INDEX([1]мтр!H:H,MATCH($F7,[1]мтр!$C:$C,0)),"") -> 0 | N7: =IFERROR(INDEX([1]мтр!I:I,MATCH($F7,[1]мтр!$C:$C,0)),"") -> 0 | O7: =IFERROR(AVERAGE(R7,X7,AD7),"") -> 30253.766 | P7: =IFERROR(INDEX([2]Лист1!$E:$E,AH7),"") -> Маты базальтовые прошивные энергетические в обкладке из кремнеземистой ткани КТ-11 со всех сторон МБПЭ-4-50 2000.1000.50 | Q7: =IFERROR(INDEX([2]Лист1!$I:$I,AH7),"") -> м3 | R7: =IFERROR(INDEX([2]Лист1!$V:$V,AH7),"") -> 30253.766 | S7: =IFERROR(INDEX([2]Лист1!$L:$L,AH7),"") -> 44994 | T7: =IFERROR(INDEX([2]Лист1!$J:$J,AH7),"") -> АО "Фирма Энергозащита" | U7: =IFERROR(INDEX([2]Лист1!$K:$K,AH7),"") -> КП №000-000387 от 09.03.2023 | V7: =IFERROR(INDEX([2]Лист1!$E:$E,AI7),"") | W7: =IFERROR(INDEX([2]Лист1!$I:$I,AI7),"") | X7: =IFERROR(INDEX([2]Лист1!$V:$V,AI7),"") | Y7: =IFERROR(INDEX([2]Лист1!$L:$L,AI7),"") | Z7: =IFERROR(INDEX([2]Лист1!$J:$J,AI7),"") | AA7: =IFERROR(INDEX([2]Лист1!$K:$K,AI7),"") | AB7: =IFERROR(INDEX([2]Лист1!$E:$E,AJ7),"") | AC7: =IFERROR(INDEX([2]Лист1!$I:$I,AJ7),"") | AD7: =IFERROR(INDEX([2]Лист1!$V:$V,AJ7),"") | AE7: =IFERROR(INDEX([2]Лист1!$L:$L,AJ7),"") | AF7: =IFERROR(INDEX([2]Лист1!$J:$J,AJ7),"") | AG7: =IFERROR(INDEX([2]Лист1!$K:$K,AJ7),"") | AH7: =MATCH(L7,[2]Лист1!$A:$A,0) -> 6567 | AI7: =MATCH(M7,[2]Лист1!$A:$A,0) -> #N/A | AJ7: =MATCH(N7,[2]Лист1!$A:$A,0) -> #N/A
A8: 1 | B8: ЛСР-03-05-202ТМ | C8: 3 | E8: ТЦ_23.7.01.02_31_3123315768_20.05.2022_02 / КА п.2 / Энергомаш ООО "Белэнергомаш-БЗЭМ" № 006-00073 | F8: Трубопроводы низкого давления, 4Н класса безопасности, материал - нж, Дн 159х6, 133х6, 89х5_Трубопроводы из н/ж. стали низкого давления: трубопроводы Ду > 80мм | G8: т | H8: 2.94 | I8: 799960.85 | J8: =H8*I8 -> 2351884.9 | K8: =J8/SUM($J$2:$J$1590) -> 0.018417642 | L8: =IFERROR(INDEX([1]мтр!G:G,MATCH($F8,[1]мтр!$C:$C,0)),"") -> 4861 | M8: =IFERROR(INDEX([1]мтр!H:H,MATCH($F8,[1]мтр!$C:$C,0)),"") -> 0 | N8: =IFERROR(INDEX([1]мтр!I:I,MATCH($F8,[1]мтр!$C:$C,0)),"") -> 0 | O8: =IFERROR(AVERAGE(R8,X8,AD8),"") -> 2050605.2 | P8: =IFERROR(INDEX([2]Лист1!$E:$E,AH8),"") -> Трубопроводы низкого давления из нержавеющей стали зданий UJA, UKD. Объём: 40 315 616 руб. / 6 074,16 кг = 6637 RUB/кг. Транспорт 5800 USD (Договор ЕОС-закупки №629007, №7720/220816 от 07.09.2022, АСЭ_Рускон) /40DV контейнер 25 т, класс груза - 2, загрузка 85%. | Q8: =IFERROR(INDEX([2]Лист1!$I:$I,AH8),"") -> т | R8: =IFERROR(INDEX([2]Лист1!$V:$V,AH8),"") -> 2050605.2 | S8: =IFERROR(INDEX([2]Лист1!$L:$L,AH8),"") -> 44753 | T8: =IFERROR(INDEX([2]Лист1!$J:$J,AH8),"") -> Белэнергомаш-БЗЭМ | U8: =IFERROR(INDEX([2]Лист1!$K:$K,AH8),"") -> Поставка трубопроводов по лоту 19677-248 Куд3;4. НМЦ от 11.07.2022, рассчитанная на основании п.1 раздела 3 главы 3 (приложения №8 к ЕОСЗ). | V8: =IFERROR(INDEX([2]Лист1!$E:$E,AI8),"") | W8: =IFERROR(INDEX([2]Лист1!$I:$I,AI8),"") | X8: =IFERROR(INDEX([2]Лист1!$V:$V,AI8),"") | Y8: =IFERROR(INDEX([2]Лист1!$L:$L,AI8),"") | Z8: =IFERROR(INDEX([2]Лист1!$J:$J,AI8),"") | AA8: =IFERROR(INDEX([2]Лист1!$K:$K,AI8),"") | AB8: =IFERROR(INDEX([2]Лист1!$E:$E,AJ8),"") | AC8: =IFERROR(INDEX([2]Лист1!$I:$I,AJ8),"") | AD8: =IFERROR(INDEX([2]Лист1!$V:$V,AJ8),"") | AE8: =IFERROR(INDEX([2]Лист1!$L:$L,AJ8),"") | AF8: =IFERROR(INDEX([2]Лист1!$J:$J,AJ8),"") | AG8: =IFERROR(INDEX([2]Лист1!$K:$K,AJ8),"") | AH8: =MATCH(L8,[2]Лист1!$A:$A,0) -> 4798 | AI8: =MATCH(M8,[2]Лист1!$A:$A,0) -> #N/A | AJ8: =MATCH(N8,[2]Лист1!$A:$A,0) -> #N/A
A9: 1 | B9: ЛСР-03-05-701АК | C9: 3 | E9: ТЦ_20.2.03.02_50_7710050305_31.05.2022_02 | F9: Опорная конструкция T MQK-600. Hilti 4; III; QNC | G9: шт. | H9: 1592 | I9: 1422.48 | J9: =H9*I9 -> 2264588.2 | K9: =J9/SUM($J$2:$J$1590) -> 0.01773402 | L9: =IFERROR(INDEX([1]мтр!G:G,MATCH($F9,[1]мтр!$C:$C,0)),"") -> 7609 | M9: =IFERROR(INDEX([1]мтр!H:H,MATCH($F9,[1]мтр!$C:$C,0)),"") -> 0 | N9: =IFERROR(INDEX([1]мтр!I:I,MATCH($F9,[1]мтр!$C:$C,0)),"") -> 0 | O9: =IFERROR(AVERAGE(R9,X9,AD9),"") -> 2697.7432 | P9: =IFERROR(INDEX([2]Лист1!$E:$E,AH9),"") -> Опорная конструкция T MQK-600 в составе:- консольная опора MQK-72/600 #369616, 1 шт;- анкер для тяжелых нагрузок HSL4-G M8 d12x92 5/-/- #2237458, 2 шт. Транспорт экспертно 5% | Q9: =IFERROR(INDEX([2]Лист1!$I:$I,AH9),"") -> шт. | R9: =IFERROR(INDEX([2]Лист1!$V:$V,AH9),"") -> 2697.7432 | S9: =IFERROR(INDEX([2]Лист1!$L:$L,AH9),"") -> 45013 | T9: =IFERROR(INDEX([2]Лист1!$J:$J,AH9),"") -> Hilti Italy | U9: =IFERROR(INDEX([2]Лист1!$K:$K,AH9),"") -> https://www.hilti.it/c/CLS_INSTALLATION_SYS_7134/CLS_SPRINKLER_7134/CLS_SPRINKLER_COMPONENTS_7134/r4345https://www.hilti.it/?CHA_GLOBAL_ANC_SIZE=M8&CHD_ANCHOR_LENGTH=102%20mm&combo_content=51979bb59b0ce01b4fe329858c7e0028&salespackquantity=40%20pezzi&itemCode=371793 | V9: =IFERROR(INDEX([2]Лист1!$E:$E,AI9),"") | W9: =IFERROR(INDEX([2]Лист1!$I:$I,AI9),"") | X9: =IFERROR(INDEX([2]Лист1!$V:$V,AI9),"") | Y9: =IFERROR(INDEX([2]Лист1!$L:$L,AI9),"") | Z9: =IFERROR(INDEX([2]Лист1!$J:$J,AI9),"") | AA9: =IFERROR(INDEX([2]Лист1!$K:$K,AI9),"") | AB9: =IFERROR(INDEX([2]Лист1!$E:$E,AJ9),"") | AC9: =IFERROR(INDEX([2]Лист1!$I:$I,AJ9),"") | AD9: =IFERROR(INDEX([2]Лист1!$V:$V,AJ9),"") | AE9: =IFERROR(INDEX([2]Лист1!$L:$L,AJ9),"") | AF9: =IFERROR(INDEX([2]Лист1!$J:$J,AJ9),"") | AG9: =IFERROR(INDEX([2]Лист1!$K:$K,AJ9),"") | AH9: =MATCH(L9,[2]Лист1!$A:$A,0) -> 6675 | AI9: =MATCH(M9,[2]Лист1!$A:$A,0) -> #N/A | AJ9: =MATCH(N9,[2]Лист1!$A:$A,0) -> #N/A
A10: 1 | B10: ЛСР-03-05-101C | C10: 3 | E10: 08.4.03.03-0009 | F10: Сталь арматурная рифленая свариваемая, класс A500С, диаметр 25 мм_А500C (d20- d32) | G10: т | H10: 394 | I10: 5488.69 | J10: =H10*I10 -> 2162543.9 | K10: =J10/SUM($J$2:$J$1590) -> 0.01693491 | L10: =IFERROR(INDEX([1]мтр!G:G,MATCH($F10,[1]мтр!$C:$C,0)),"") -> 7509 | M10: =IFERROR(INDEX([1]мтр!H:H,MATCH($F10,[1]мтр!$C:$C,0)),"") -> 0 | N10: =IFERROR(INDEX([1]мтр!I:I,MATCH($F10,[1]мтр!$C:$C,0)),"") -> 0 | O10: =IFERROR(AVERAGE(R10,X10,AD10),"") -> 16541.58 | P10: =IFERROR(INDEX([2]Лист1!$E:$E,AH10),"") -> Арматура стальная периодического профиля, класс B500DWR, диаметр 6 - 40 мм | Q10: =IFERROR(INDEX([2]Лист1!$I:$I,AH10),"") -> т | R10: =IFERROR(INDEX([2]Лист1!$V:$V,AH10),"") -> 16541.58 | S10: =IFERROR(INDEX([2]Лист1!$L:$L,AH10),"") -> 44984 | T10: =IFERROR(INDEX([2]Лист1!$J:$J,AH10),"") -> N/A | U10: =IFERROR(INDEX([2]Лист1!$K:$K,AH10),"") -> Справочник сметных цен на строильные материалы, изделия и конструкции для строительства АЭС Эль-Дабаа, Арабская республика Египет. III квартал 2022 года, ГК Росатом №05-0077 | V10: =IFERROR(INDEX([2]Лист1!$E:$E,AI10),"") | W10: =IFERROR(INDEX([2]Лист1!$I:$I,AI10),"") | X10: =IFERROR(INDEX([2]Лист1!$V:$V,AI10),"") | Y10: =IFERROR(INDEX([2]Лист1!$L:$L,AI10),"") | Z10: =IFERROR(INDEX([2]Лист1!$J:$J,AI10),"") | AA10: =IFERROR(INDEX([2]Лист1!$K:$K,AI10),"") | AB10: =IFERROR(INDEX([2]Лист1!$E:$E,AJ10),"") | AC10: =IFERROR(INDEX([2]Лист1!$I:$I,AJ10),"") | AD10: =IFERROR(INDEX([2]Лист1!$V:$V,AJ10),"") | AE10: =IFERROR(INDEX([2]Лист1!$L:$L,AJ10),"") | AF10: =IFERROR(INDEX([2]Лист1!$J:$J,AJ10),"") | AG10: =IFERROR(INDEX([2]Лист1!$K:$K,AJ10),"") | AH10: =MATCH(L10,[2]Лист1!$A:$A,0) -> 6575 | AI10: =MATCH(M10,[2]Лист1!$A:$A,0) -> #N/A | AJ10: =MATCH(N10,[2]Лист1!$A:$A,0) -> #N/A
A11: 1 | B11: ЛСР-03-05-101C | C11: 3 | E11: 04.1.02.02-0014 | F11: Смеси бетонные тяжелого бетона (БСТ) для гидротехнических сооружений на сульфатостойких цементах, класс В45 (М600)_B45 W8 | G11: м3 | H11: 1588.28 | I11: 1339.78 | J11: =H11*I11 -> 2127945.8 | K11: =J11/SUM($J$2:$J$1590) -> 0.016663972 | L11: =IFERROR(INDEX([1]мтр!G:G,MATCH($F11,[1]мтр!$C:$C,0)),"") -> 5710 | M11: =IFERROR(INDEX([1]мтр!H:H,MATCH($F11,[1]мтр!$C:$C,0)),"") -> 0 | N11: =IFERROR(INDEX([1]мтр!I:I,MATCH($F11,[1]мтр!$C:$C,0)),"") -> 0 | O11: =IFERROR(AVERAGE(R11,X11,AD11),"") -> 2207.07 | P11: =IFERROR(INDEX([2]Лист1!$E:$E,AH11),"") -> Бетон тяжелый на сульфатостойком портландцементе, класс В45 П5 W8 SRC XS3, XA3 | Q11: =IFERROR(INDEX([2]Лист1!$I:$I,AH11),"") -> м3 | R11: =IFERROR(INDEX([2]Лист1!$V:$V,AH11),"") -> 2207.07 | S11: =IFERROR(INDEX([2]Лист1!$L:$L,AH11),"") -> 44872 | T11: =IFERROR(INDEX([2]Лист1!$J:$J,AH11),"") -> N/A | U11: =IFERROR(INDEX([2]Лист1!$K:$K,AH11),"") -> Справочник сметных цен на строильные материалы, изделия и конструкции для строительства АЭС Эль-Дабаа, Арабская республика Египет. II квартал 2022 года, ГК Росатом №05-0070 | V11: =IFERROR(INDEX([2]Лист1!$E:$E,AI11),"") | W11: =IFERROR(INDEX([2]Лист1!$I:$I,AI11),"") | X11: =IFERROR(INDEX([2]Лист1!$V:$V,AI11),"") | Y11: =IFERROR(INDEX([2]Лист1!$L:$L,AI11),"") | Z11: =IFERROR(INDEX([2]Лист1!$J:$J,AI11),"") | AA11: =IFERROR(INDEX([2]Лист1!$K:$K,AI11),"") | AB11: =IFERROR(INDEX([2]Лист1!$E:$E,AJ11),"") | AC11: =IFERROR(INDEX([2]Лист1!$I:$I,AJ11),"") | AD11: =IFERROR(INDEX([2]Лист1!$V:$V,AJ11),"") | AE11: =IFERROR(INDEX([2]Лист1!$L:$L,AJ11),"") | AF11: =IFERROR(INDEX([2]Лист1!$J:$J,AJ11),"") | AG11: =IFERROR(INDEX([2]Лист1!$K:$K,AJ11),"") | AH11: =MATCH(L11,[2]Лист1!$A:$A,0) -> 463 | AI11: =MATCH(M11,[2]Лист1!$A:$A,0) -> #N/A | AJ11: =MATCH(N11,[2]Лист1!$A:$A,0) -> #N/A
A12: 1 | B12: ЛСР-03-05-206ТМ | C12: 3 | E12: ТЦ_23.7.01.02_31_3123315768_20.05.2022_02/ КА п.78/ ООО "Белэнергомаш-БЗЭМ" №006-00073 | F12: Трубопроводы низкого давления из нержавеющей стали, 4 класса безопасности, Ду>80мм_ DN 150 мм, DN 125 мм | G12: т | H12: 2.651 | I12: 799960.85 | J12: =H12*I12 -> 2120696.2 | K12: =J12/SUM($J$2:$J$1590) -> 0.016607201 | L12: =IFERROR(INDEX([1]мтр!G:G,MATCH($F12,[1]мтр!$C:$C,0)),"") -> 4861 | M12: =IFERROR(INDEX([1]мтр!H:H,MATCH($F12,[1]мтр!$C:$C,0)),"") -> 0 | N12: =IFERROR(INDEX([1]мтр!I:I,MATCH($F12,[1]мтр!$C:$C,0)),"") -> 0 | O12: =IFERROR(AVERAGE(R12,X12,AD12),"") -> 2050605.2 | P12: =IFERROR(INDEX([2]Лист1!$E:$E,AH12),"") -> Трубопроводы низкого давления из нержавеющей стали зданий UJA, UKD. Объём: 40 315 616 руб. / 6 074,16 кг = 6637 RUB/кг. Транспорт 5800 USD (Договор ЕОС-закупки №629007, №7720/220816 от 07.09.2022, АСЭ_Рускон) /40DV контейнер 25 т, класс груза - 2, загрузка 85%. | Q12: =IFERROR(INDEX([2]Лист1!$I:$I,AH12),"") -> т | R12: =IFERROR(INDEX([2]Лист1!$V:$V,AH12),"") -> 2050605.2 | S12: =IFERROR(INDEX([2]Лист1!$L:$L,AH12),"") -> 44753 | T12: =IFERROR(INDEX([2]Лист1!$J:$J,AH12),"") -> Белэнергомаш-БЗЭМ | U12: =IFERROR(INDEX([2]Лист1!$K:$K,AH12),"") -> Поставка трубопроводов по лоту 19677-248 Куд3;4. НМЦ от 11.07.2022, рассчитанная на основании п.1 раздела 3 главы 3 (приложения №8 к ЕОСЗ). | V12: =IFERROR(INDEX([2]Лист1!$E:$E,AI12),"") | W12: =IFERROR(INDEX([2]Лист1!$I:$I,AI12),"") | X12: =IFERROR(INDEX([2]Лист1!$V:$V,AI12),"") | Y12: =IFERROR(INDEX([2]Лист1!$L:$L,AI12),"") | Z12: =IFERROR(INDEX([2]Лист1!$J:$J,AI12),"") | AA12: =IFERROR(INDEX([2]Лист1!$K:$K,AI12),"") | AB12: =IFERROR(INDEX([2]Лист1!$E:$E,AJ12),"") | AC12: =IFERROR(INDEX([2]Лист1!$I:$I,AJ12),"") | AD12: =IFERROR(INDEX([2]Лист1!$V:$V,AJ12),"") | AE12: =IFERROR(INDEX([2]Лист1!$L:$L,AJ12),"") | AF12: =IFERROR(INDEX([2]Лист1!$J:$J,AJ12),"") | AG12: =IFERROR(INDEX([2]Лист1!$K:$K,AJ12),"") | AH12: =MATCH(L12,[2]Лист1!$A:$A,0) -> 4798 | AI12: =MATCH(M12,[2]Лист1!$A:$A,0) -> #N/A | AJ12: =MATCH(N12,[2]Лист1!$A:$A,0) -> #N/A
A13: 1 | B13: ЛСР-03-05-101C | C13: 3 | E13: 04.1.02.05-0011 | F13: Смеси бетонные тяжелого бетона (БСТ), класс В30 (М400)_В30 W8 | G13: м3 | H13: 2430.925 | I13: 811.26 | J13: =H13*I13 -> 1972112.2 | K13: =J13/SUM($J$2:$J$1590) -> 0.015443637 | L13: =IFERROR(INDEX([1]мтр!G:G,MATCH($F13,[1]мтр!$C:$C,0)),"") -> 5177 | M13: =IFERROR(INDEX([1]мтр!H:H,MATCH($F13,[1]мтр!$C:$C,0)),"") -> 5178 | N13: =IFERROR(INDEX([1]мтр!I:I,MATCH($F13,[1]мтр!$C:$C,0)),"") -> 0 | O13: =IFERROR(AVERAGE(R13,X13,AD13),"") -> 1831.03 | P13: =IFERROR(INDEX([2]Лист1!$E:$E,AH13),"") -> Бетон тяжелый, класс C35 CEM I | Q13: =IFERROR(INDEX([2]Лист1!$I:$I,AH13),"") -> м3 | R13: =IFERROR(INDEX([2]Лист1!$V:$V,AH13),"") -> 1813.6704 | S13: =IFERROR(INDEX([2]Лист1!$L:$L,AH13),"") -> 44735 | T13: =IFERROR(INDEX([2]Лист1!$J:$J,AH13),"") -> Nuclear Concrete Mixes | U13: =IFERROR(INDEX([2]Лист1!$K:$K,AH13),"") -> ТКП 04-N-161 от 23.06.2022 | V13: =IFERROR(INDEX([2]Лист1!$E:$E,AI13),"") -> Бетон тяжелый, класс C35 CEM I | W13: =IFERROR(INDEX([2]Лист1!$I:$I,AI13),"") -> м3 | X13: =IFERROR(INDEX([2]Лист1!$V:$V,AI13),"") -> 1848.3896 | Y13: =IFERROR(INDEX([2]Лист1!$L:$L,AI13),"") -> 44738 | Z13: =IFERROR(INDEX([2]Лист1!$J:$J,AI13),"") -> 3S READY MIX | AA13: =IFERROR(INDEX([2]Лист1!$K:$K,AI13),"") -> ТКП от 26.06.2022 | AB13: =IFERROR(INDEX([2]Лист1!$E:$E,AJ13),"") | AC13: =IFERROR(INDEX([2]Лист1!$I:$I,AJ13),"") | AD13: =IFERROR(INDEX([2]Лист1!$V:$V,AJ13),"") | AE13: =IFERROR(INDEX([2]Лист1!$L:$L,AJ13),"") | AF13: =IFERROR(INDEX([2]Лист1!$J:$J,AJ13),"") | AG13: =IFERROR(INDEX([2]Лист1!$K:$K,AJ13),"") | AH13: =MATCH(L13,[2]Лист1!$A:$A,0) -> 4854 | AI13: =MATCH(M13,[2]Лист1!$A:$A,0) -> 4855 | AJ13: =MATCH(N13,[2]Лист1!$A:$A,0) -> #N/A
A14: 1 | B14: ЛСР-03-05-602Э | C14: 3 | E14: 21.1.06.10-0142 | F14: Кабель силовой с медными жилами ПвПнг(A)-FRHF 5х95-1000_Кабель силовой 5х95мм2-1кВ | G14: 1000 м | H14: 2.856 | I14: 688756.52 | J14: =H14*I14 -> 1967088.6 | K14: =J14/SUM($J$2:$J$1590) -> 0.015404297 | L14: =IFERROR(INDEX([1]мтр!G:G,MATCH($F14,[1]мтр!$C:$C,0)),"") -> 5263 | M14: =IFERROR(INDEX([1]мтр!H:H,MATCH($F14,[1]мтр!$C:$C,0)),"") -> 0 | N14: =IFERROR(INDEX([1]мтр!I:I,MATCH($F14,[1]мтр!$C:$C,0)),"") -> 0 | O14: =IFERROR(AVERAGE(R14,X14,AD14),"") -> 1051715.2 | P14: =IFERROR(INDEX([2]Лист1!$E:$E,AH14),"") -> Импорт из РФ_ПвПнг(А)-HF 5х95мс(N,PE)-1 кВ ТУ 16.К71-341-2004 (ГОСТ 31996-2012), в контейнере 4 барабанов №18, на барабане= 0,55 км кабеля. Транспорт контейнер:1) автомобильный Москва - Новорос.: 1540 км х 70руб/км;2) таможенное оформление РФ: 34 830 руб;3) портовая обработка и фрахт до Александрии: 273 800 руб;4) портовая обработка и таможенное оформление в Александрии: 1250 EGP;5) автомобильный Александрия - площадка: 6200 EGPИст. 1-3: согл НМЦ РосСЭМ от 17.01.2022, 4-5: инф Филиал от 20.01.2022. | Q14: =IFERROR(INDEX([2]Лист1!$I:$I,AH14),"") -> 1000 м | R14: =IFERROR(INDEX([2]Лист1!$V:$V,AH14),"") -> 1051715.2 | S14: =IFERROR(INDEX([2]Лист1!$L:$L,AH14),"") -> 44571 | T14: =IFERROR(INDEX([2]Лист1!$J:$J,AH14),"") -> Электрокабель | U14: =IFERROR(INDEX([2]Лист1!$K:$K,AH14),"") -> Прайс-лист Электрокабель от 10.01.2022 | V14: =IFERROR(INDEX([2]Лист1!$E:$E,AI14),"") | W14: =IFERROR(INDEX([2]Лист1!$I:$I,AI14),"") | X14: =IFERROR(INDEX([2]Лист1!$V:$V,AI14),"") | Y14: =IFERROR(INDEX([2]Лист1!$L:$L,AI14),"") | Z14: =IFERROR(INDEX([2]Лист1!$J:$J,AI14),"") | AA14: =IFERROR(INDEX([2]Лист1!$K:$K,AI14),"") | AB14: =IFERROR(INDEX([2]Лист1!$E:$E,AJ14),"") | AC14: =IFERROR(INDEX([2]Лист1!$I:$I,AJ14),"") | AD14: =IFERROR(INDEX([2]Лист1!$V:$V,AJ14),"") | AE14: =IFERROR(INDEX([2]Лист1!$L:$L,AJ14),"") | AF14: =IFERROR(INDEX([2]Лист1!$J:$J,AJ14),"") | AG14: =IFERROR(INDEX([2]Лист1!$K:$K,AJ14),"") | AH14: =MATCH(L14,[2]Лист1!$A:$A,0) -> 2364 | AI14: =MATCH(M14,[2]Лист1!$A:$A,0) -> #N/A | AJ14: =MATCH(N14,[2]Лист1!$A:$A,0) -> #N/A
A15: 1 | B15: ЛСР-03-05-203ТМ | C15: 3 | E15: ТЦ_18.2.08.00_50_5503095632_05.07.2022_02 / КА п.24/ ЗАО "Сибгазстройдеталь" №897 | F15: Фильтр механический По типу ФС 100 С 16-0.4У DN 100; pmax=0.12 MPag; tmax=109 °С; Раб. среда: Вода питательная ПРК; Q=217 м?/ч; H-высота = 235 мм; L-длина = 350 мм; W-ширина = 169 мм, Кл 4Н_ФС100/16П-200-Ф1-Д1-УХЛ 1; ФС- фильтр сливной 100-номинальный диаметр, DN 16-давление 16 кг/см2 или (1,6Мпа) | G15: шт. | H15: 5 | I15: 363366.32 | J15: =H15*I15 -> 1816831.6 | K15: =J15/SUM($J$2:$J$1590) -> 0.014227633 | L15: =IFERROR(INDEX([1]мтр!G:G,MATCH($F15,[1]мтр!$C:$C,0)),"") | M15: =IFERROR(INDEX([1]мтр!H:H,MATCH($F15,[1]мтр!$C:$C,0)),"") | N15: =IFERROR(INDEX([1]мтр!I:I,MATCH($F15,[1]мтр!$C:$C,0)),"") | O15: =IFERROR(AVERAGE(R15,X15,AD15),"") | P15: =IFERROR(INDEX([2]Лист1!$E:$E,AH15),"") | Q15: =IFERROR(INDEX([2]Лист1!$I:$I,AH15),"") | R15: =IFERROR(INDEX([2]Лист1!$V:$V,AH15),"") | S15: =IFERROR(INDEX([2]Лист1!$L:$L,AH15),"") | T15: =IFERROR(INDEX([2]Лист1!$J:$J,AH15),"") | U15: =IFERROR(INDEX([2]Лист1!$K:$K,AH15),"") | V15: =IFERROR(INDEX([2]Лист1!$E:$E,AI15),"") | W15: =IFERROR(INDEX([2]Лист1!$I:$I,AI15),"") | X15: =IFERROR(INDEX([2]Лист1!$V:$V,AI15),"") | Y15: =IFERROR(INDEX([2]Лист1!$L:$L,AI15),"") | Z15: =IFERROR(INDEX([2]Лист1!$J:$J,AI15),"") | AA15: =IFERROR(INDEX([2]Лист1!$K:$K,AI15),"") | AB15: =IFERROR(INDEX([2]Лист1!$E:$E,AJ15),"") | AC15: =IFERROR(INDEX([2]Лист1!$I:$I,AJ15),"") | AD15: =IFERROR(INDEX([2]Лист1!$V:$V,AJ15),"") | AE15: =IFERROR(INDEX([2]Лист1!$L:$L,AJ15),"") | AF15: =IFERROR(INDEX([2]Лист1!$J:$J,AJ15),"") | AG15: =IFERROR(INDEX([2]Лист1!$K:$K,AJ15),"") | AH15: =MATCH(L15,[2]Лист1!$A:$A,0) -> #N/A | AI15: =MATCH(M15,[2]Лист1!$A:$A,0) -> #N/A | AJ15: =MATCH(N15,[2]Лист1!$A:$A,0) -> #N/A
A16: 1 | B16: ЛСР-03-05-102С | C16: 3 | E16: 14.5.04.06-0006 | F16: Мастика кровельная двухкомпонентная полиуретановая | G16: т | H16: 101.2284 | I16: 16460.67 | J16: =H16*I16 -> 1666287.3 | K16: =J16/SUM($J$2:$J$1590) -> 0.013048718 | L16: 5813 | M16: =IFERROR(INDEX([1]мтр!H:H,MATCH($F16,[1]мтр!$C:$C,0)),"") | N16: =IFERROR(INDEX([1]мтр!I:I,MATCH($F16,[1]мтр!$C:$C,0)),"") | O16: =IFERROR(AVERAGE(R16,X16,AD16),"") -> 27434.4 | P16: =IFERROR(INDEX([2]Лист1!$E:$E,AH16),"") -> Мастика МББП-65 (ЛИЛО-1) ГОСТ 32870-2014 /Мастика бутилкаучуковая холодная | Q16: =IFERROR(INDEX([2]Лист1!$I:$I,AH16),"") -> т | R16: =IFERROR(INDEX([2]Лист1!$V:$V,AH16),"") -> 27434.4 | S16: =IFERROR(INDEX([2]Лист1!$L:$L,AH16),"") -> 44900 | T16: =IFERROR(INDEX([2]Лист1!$J:$J,AH16),"") -> ООО "УРАЛЬСКИЙ БИТУМНЫЙ ЗАВОД", | U16: =IFERROR(INDEX([2]Лист1!$K:$K,AH16),"") -> ООО "УРАЛЬСКИЙ БИТУМНЫЙ ЗАВОД", | V16: =IFERROR(INDEX([2]Лист1!$E:$E,AI16),"") | W16: =IFERROR(INDEX([2]Лист1!$I:$I,AI16),"") | X16: =IFERROR(INDEX([2]Лист1!$V:$V,AI16),"") | Y16: =IFERROR(INDEX([2]Лист1!$L:$L,AI16),"") | Z16: =IFERROR(INDEX([2]Лист1!$J:$J,AI16),"") | AA16: =IFERROR(INDEX([2]Лист1!$K:$K,AI16),"") | AB16: =IFERROR(INDEX([2]Лист1!$E:$E,AJ16),"") | AC16: =IFERROR(INDEX([2]Лист1!$I:$I,AJ16),"") | AD16: =IFERROR(INDEX([2]Лист1!$V:$V,AJ16),"") | AE16: =IFERROR(INDEX([2]Лист1!$L:$L,AJ16),"") | AF16: =IFERROR(INDEX([2]Лист1!$J:$J,AJ16),"") | AG16: =IFERROR(INDEX([2]Лист1!$K:$K,AJ16),"") | AH16: =MATCH(L16,[2]Лист1!$A:$A,0) -> 4962 | AI16: =MATCH(M16,[2]Лист1!$A:$A,0) -> #N/A | AJ16: =MATCH(N16,[2]Лист1!$A:$A,0) -> #N/A
A17: 1 | B17: ЛСР-03-05-206ТМ | C17: 3 | E17: 14.5.09.10-0001 | F17: Толуол каменноугольный и сланцевый, марка А | G17: т | H17: 385 | I17: 3922 | J17: =H17*I17 -> 1509970 | K17: =J17/SUM($J$2:$J$1590) -> 0.011824595 | L17: =IFERROR(INDEX([1]мтр!G:G,MATCH($F17,[1]мтр!$C:$C,0)),"") -> 7163 | M17: =IFERROR(INDEX([1]мтр!H:H,MATCH($F17,[1]мтр!$C:$C,0)),"") -> 0 | N17: =IFERROR(INDEX([1]мтр!I:I,MATCH($F17,[1]мтр!$C:$C,0)),"") -> 0 | O17: =IFERROR(AVERAGE(R17,X17,AD17),"") -> 110509.64 | P17: =IFERROR(INDEX([2]Лист1!$E:$E,AH17),"") -> Толуол нефтяной ГОСТ 14710-78 | Q17: =IFERROR(INDEX([2]Лист1!$I:$I,AH17),"") -> т | R17: =IFERROR(INDEX([2]Лист1!$V:$V,AH17),"") -> 110509.64 | S17: =IFERROR(INDEX([2]Лист1!$L:$L,AH17),"") -> 44937 | T17: =IFERROR(INDEX([2]Лист1!$J:$J,AH17),"") -> ООО "УФАХИМКОМПЛЕКТ" | U17: =IFERROR(INDEX([2]Лист1!$K:$K,AH17),"") -> ЕОС Закупки (665497) №4163/2022/10.1-ДОГ от 11.01.2023 | V17: =IFERROR(INDEX([2]Лист1!$E:$E,AI17),"") | W17: =IFERROR(INDEX([2]Лист1!$I:$I,AI17),"") | X17: =IFERROR(INDEX([2]Лист1!$V:$V,AI17),"") | Y17: =IFERROR(INDEX([2]Лист1!$L:$L,AI17),"") | Z17: =IFERROR(INDEX([2]Лист1!$J:$J,AI17),"") | AA17: =IFERROR(INDEX([2]Лист1!$K:$K,AI17),"") | AB17: =IFERROR(INDEX([2]Лист1!$E:$E,AJ17),"") | AC17: =IFERROR(INDEX([2]Лист1!$I:$I,AJ17),"") | AD17: =IFERROR(INDEX([2]Лист1!$V:$V,AJ17),"") | AE17: =IFERROR(INDEX([2]Лист1!$L:$L,AJ17),"") | AF17: =IFERROR(INDEX([2]Лист1!$J:$J,AJ17),"") | AG17: =IFERROR(INDEX([2]Лист1!$K:$K,AJ17),"") | AH17: =MATCH(L17,[2]Лист1!$A:$A,0) -> 6229 | AI17: =MATCH(M17,[2]Лист1!$A:$A,0) -> #N/A | AJ17: =MATCH(N17,[2]Лист1!$A:$A,0) -> #N/A
A18: 1 | B18: ЛСР-03-05-203ТМ | C18: 3 | E18: ТЦ_18.1.06.00_50_5503095632_05.07.2022_02 /КА п.51/ ЗАО "Сибгазстройдеталь" №897 | F18: Запорная арматура По типу 2с-27-2Н DN 200; pmax=0.40 MPag; tmax=155 °С / °C; Раб. среда:Пар собственных нужд; Способ управления: Ручной привод; Тип присоединения: Под приварку, Кл.4Н, угл.ст | G18: шт. | H18: 10 | I18: 147436.32 | J18: =H18*I18 -> 1474363.2 | K18: =J18/SUM($J$2:$J$1590) -> 0.011545758 | L18: =IFERROR(INDEX([1]мтр!G:G,MATCH($F18,[1]мтр!$C:$C,0)),"") | M18: =IFERROR(INDEX([1]мтр!H:H,MATCH($F18,[1]мтр!$C:$C,0)),"") | N18: =IFERROR(INDEX([1]мтр!I:I,MATCH($F18,[1]мтр!$C:$C,0)),"") | O18: =IFERROR(AVERAGE(R18,X18,AD18),"") | P18: =IFERROR(INDEX([2]Лист1!$E:$E,AH18),"") | Q18: =IFERROR(INDEX([2]Лист1!$I:$I,AH18),"") | R18: =IFERROR(INDEX([2]Лист1!$V:$V,AH18),"") | S18: =IFERROR(INDEX([2]Лист1!$L:$L,AH18),"") | T18: =IFERROR(INDEX([2]Лист1!$J:$J,AH18),"") | U18: =IFERROR(INDEX([2]Лист1!$K:$K,AH18),"") | V18: =IFERROR(INDEX([2]Лист1!$E:$E,AI18),"") | W18: =IFERROR(INDEX([2]Лист1!$I:$I,AI18),"") | X18: =IFERROR(INDEX([2]Лист1!$V:$V,AI18),"") | Y18: =IFERROR(INDEX([2]Лист1!$L:$L,AI18),"") | Z18: =IFERROR(INDEX([2]Лист1!$J:$J,AI18),"") | AA18: =IFERROR(INDEX([2]Лист1!$K:$K,AI18),"") | AB18: =IFERROR(INDEX([2]Лист1!$E:$E,AJ18),"") | AC18: =IFERROR(INDEX([2]Лист1!$I:$I,AJ18),"") | AD18: =IFERROR(INDEX([2]Лист1!$V:$V,AJ18),"") | AE18: =IFERROR(INDEX([2]Лист1!$L:$L,AJ18),"") | AF18: =IFERROR(INDEX([2]Лист1!$J:$J,AJ18),"") | AG18: =IFERROR(INDEX([2]Лист1!$K:$K,AJ18),"") | AH18: =MATCH(L18,[2]Лист1!$A:$A,0) -> #N/A | AI18: =MATCH(M18,[2]Лист1!$A:$A,0) -> #N/A | AJ18: =MATCH(N18,[2]Лист1!$A:$A,0) -> #N/A
A19: 1 | B19: ЛСР-03-05-206ТМ | C19: 3 | E19: ТЦ_23.7.01.02_31_3123315768_20.05.2022_02/ КА п.76/ ООО "Белэнергомаш-БЗЭМ" №006-00073 | F19: Трубопроводы низкого давления из углеродистой стали, 4 класса безопасности, Ду > 80мм_ DN350 мм, DN300 мм, DN200, DN100 | G19: т | H19: 6.957 | I19: 211499.32 | J19: =H19*I19 -> 1471400.8 | K19: =J19/SUM($J$2:$J$1590) -> 0.011522559 | L19: =IFERROR(INDEX([1]мтр!G:G,MATCH($F19,[1]мтр!$C:$C,0)),"") -> 4859 | M19: =IFERROR(INDEX([1]мтр!H:H,MATCH($F19,[1]мтр!$C:$C,0)),"") -> 0 | N19: =IFERROR(INDEX([1]мтр!I:I,MATCH($F19,[1]мтр!$C:$C,0)),"") -> 0 | O19: =IFERROR(AVERAGE(R19,X19,AD19),"") -> 479788.26 | P19: =IFERROR(INDEX([2]Лист1!$E:$E,AH19),"") -> Трубопроводы низкого давления из углеродистой стали зданий UJA, UKD. Объём: 4526466 руб. / 2939,52 кг = 1540 RUB/кг. Транспорт 5800 USD (Договор ЕОС-закупки №629007, №7720/220816 от 07.09.2022, АСЭ_Рускон) /40DV контейнер 25 т, класс груза - 2, загрузка 85%. | Q19: =IFERROR(INDEX([2]Лист1!$I:$I,AH19),"") -> т | R19: =IFERROR(INDEX([2]Лист1!$V:$V,AH19),"") -> 479788.26 | S19: =IFERROR(INDEX([2]Лист1!$L:$L,AH19),"") -> 44753 | T19: =IFERROR(INDEX([2]Лист1!$J:$J,AH19),"") -> Белэнергомаш-БЗЭМ | U19: =IFERROR(INDEX([2]Лист1!$K:$K,AH19),"") -> Поставка трубопроводов по лоту 19677-248 Куд3;4. НМЦ от 11.07.2022, рассчитанная на основании п.1 раздела 3 главы 3 (приложения №8 к ЕОСЗ). | V19: =IFERROR(INDEX([2]Лист1!$E:$E,AI19),"") | W19: =IFERROR(INDEX([2]Лист1!$I:$I,AI19),"") | X19: =IFERROR(INDEX([2]Лист1!$V:$V,AI19),"") | Y19: =IFERROR(INDEX([2]Лист1!$L:$L,AI19),"") | Z19: =IFERROR(INDEX([2]Лист1!$J:$J,AI19),"") | AA19: =IFERROR(INDEX([2]Лист1!$K:$K,AI19),"") | AB19: =IFERROR(INDEX([2]Лист1!$E:$E,AJ19),"") | AC19: =IFERROR(INDEX([2]Лист1!$I:$I,AJ19),"") | AD19: =IFERROR(INDEX([2]Лист1!$V:$V,AJ19),"") | AE19: =IFERROR(INDEX([2]Лист1!$L:$L,AJ19),"") | AF19: =IFERROR(INDEX([2]Лист1!$J:$J,AJ19),"") | AG19: =IFERROR(INDEX([2]Лист1!$K:$K,AJ19),"") | AH19: =MATCH(L19,[2]Лист1!$A:$A,0) -> 4796 | AI19: =MATCH(M19,[2]Лист1!$A:$A,0) -> #N/A | AJ19: =MATCH(N19,[2]Лист1!$A:$A,0) -> #N/A
A20: 1 | B20: ЛСР-03-05-103С | C20: 3 | E20: 07.2.07.13-0161 | F20: Площадки просадочные, мостики, кронштейны, маршевые лестницы, пожарные щиты переходных площадок, ограждений | G20: т | H20: 117.866 | I20: 11879.76 | J20: =H20*I20 -> 1400219.8 | K20: =J20/SUM($J$2:$J$1590) -> 0.01096514 | L20: =IFERROR(INDEX([1]мтр!G:G,MATCH($F20,[1]мтр!$C:$C,0)),"") -> 7590 | M20: =IFERROR(INDEX([1]мтр!H:H,MATCH($F20,[1]мтр!$C:$C,0)),"") -> 7591 | N20: =IFERROR(INDEX([1]мтр!I:I,MATCH($F20,[1]мтр!$C:$C,0)),"") -> 0 | O20: =IFERROR(AVERAGE(R20,X20,AD20),"") -> 49555.459 | P20: =IFERROR(INDEX([2]Лист1!$E:$E,AH20),"") -> Усредненная цена готовых металлоконструкций (на примере здания ЦЕХА СМБ Арматурное хозяйство), с доставкой, без установки. Эскалация в фев.2023 по CAPMAS "round steel", окт.2019=11450 EGP/т, фев.2023=28370,5 EGP/т | Q20: =IFERROR(INDEX([2]Лист1!$I:$I,AH20),"") -> т | R20: =IFERROR(INDEX([2]Лист1!$V:$V,AH20),"") -> 44599.913 | S20: =IFERROR(INDEX([2]Лист1!$L:$L,AH20),"") -> 43758 | T20: =IFERROR(INDEX([2]Лист1!$J:$J,AH20),"") -> Arcons Egypt | U20: =IFERROR(INDEX([2]Лист1!$K:$K,AH20),"") -> ТКП Arcons Egypt 20.10.2019 Эскалация в фев.2023 по CAPMAS "round steel", окт.2019=11450 EGP/т, фев.2023=28370,5 EGP/т | V20: =IFERROR(INDEX([2]Лист1!$E:$E,AI20),"") -> Усредненная цена готовых металлоконструкций (на примере здания ЦЕХА СМБ Арматурное хозяйство), с доставкой, без установки. Эскалация в фев.2023 по CAPMAS "round steel", окт.2019=11450 EGP/т, фев.2023=28370,5 EGP/т | W20: =IFERROR(INDEX([2]Лист1!$I:$I,AI20),"") -> т | X20: =IFERROR(INDEX([2]Лист1!$V:$V,AI20),"") -> 54511.004 | Y20: =IFERROR(INDEX([2]Лист1!$L:$L,AI20),"") -> 43762 | Z20: =IFERROR(INDEX([2]Лист1!$J:$J,AI20),"") -> Steelcom | AA20: =IFERROR(INDEX([2]Лист1!$K:$K,AI20),"") -> ТКП Steelcom 24.10.2019Эскалация в фев.2023 по CAPMAS "round steel", окт.2019=11450 EGP/т, фев.2023=28370,5 EGP/т | AB20: =IFERROR(INDEX([2]Лист1!$E:$E,AJ20),"") | AC20: =IFERROR(INDEX([2]Лист1!$I:$I,AJ20),"") | AD20: =IFERROR(INDEX([2]Лист1!$V:$V,AJ20),"") | AE20: =IFERROR(INDEX([2]Лист1!$L:$L,AJ20),"") | AF20: =IFERROR(INDEX([2]Лист1!$J:$J,AJ20),"") | AG20: =IFERROR(INDEX([2]Лист1!$K:$K,AJ20),"") | AH20: =MATCH(L20,[2]Лист1!$A:$A,0) -> 6656 | AI20: =MATCH(M20,[2]Лист1!$A:$A,0) -> 6657 | AJ20: =MATCH(N20,[2]Лист1!$A:$A,0) -> #N/A
A21: 1 | B21: ЛСР-03-05-206ТМ | C21: 3 | E21: ТЦ_23.7.01.02_31_3123315768_20.05.2022_02/КА п.76/ООО "Белэнергомаш-БЗЭМ" №006-00073 | F21: Трубопроводы низкого давления из углеродистой стали, 4 класса безопасности, Ду > 80мм_DN250,DN200, DN150, DN125, DN100, DN80 | G21: т | H21: 6.602 | I21: 211499.32 | J21: =H21*I21 -> 1396318.5 | K21: =J21/SUM($J$2:$J$1590) -> 0.010934589 | L21: =IFERROR(INDEX([1]мтр!G:G,MATCH($F21,[1]мтр!$C:$C,0)),"") -> 4859 | M21: =IFERROR(INDEX([1]мтр!H:H,MATCH($F21,[1]мтр!$C:$C,0)),"") -> 0 | N21: =IFERROR(INDEX([1]мтр!I:I,MATCH($F21,[1]мтр!$C:$C,0)),"") -> 0 | O21: =IFERROR(AVERAGE(R21,X21,AD21),"") -> 479788.26 | P21: =IFERROR(INDEX([2]Лист1!$E:$E,AH21),"") -> Трубопроводы низкого давления из углеродистой стали зданий UJA, UKD. Объём: 4526466 руб. / 2939,52 кг = 1540 RUB/кг. Транспорт 5800 USD (Договор ЕОС-закупки №629007, №7720/220816 от 07.09.2022, АСЭ_Рускон) /40DV контейнер 25 т, класс груза - 2, загрузка 85%. | Q21: =IFERROR(INDEX([2]Лист1!$I:$I,AH21),"") -> т | R21: =IFERROR(INDEX([2]Лист1!$V:$V,AH21),"") -> 479788.26 | S21: =IFERROR(INDEX([2]Лист1!$L:$L,AH21),"") -> 44753 | T21: =IFERROR(INDEX([2]Лист1!$J:$J,AH21),"") -> Белэнергомаш-БЗЭМ | U21: =IFERROR(INDEX([2]Лист1!$K:$K,AH21),"") -> Поставка трубопроводов по лоту 19677-248 Куд3;4. НМЦ от 11.07.2022, рассчитанная на основании п.1 раздела 3 главы 3 (приложения №8 к ЕОСЗ). | V21: =IFERROR(INDEX([2]Лист1!$E:$E,AI21),"") | W21: =IFERROR(INDEX([2]Лист1!$I:$I,AI21),"") | X21: =IFERROR(INDEX([2]Лист1!$V:$V,AI21),"") | Y21: =IFERROR(INDEX([2]Лист1!$L:$L,AI21),"") | Z21: =IFERROR(INDEX([2]Лист1!$J:$J,AI21),"") | AA21: =IFERROR(INDEX([2]Лист1!$K:$K,AI21),"") | AB21: =IFERROR(INDEX([2]Лист1!$E:$E,AJ21),"") | AC21: =IFERROR(INDEX([2]Лист1!$I:$I,AJ21),"") | AD21: =IFERROR(INDEX([2]Лист1!$V:$V,AJ21),"") | AE21: =IFERROR(INDEX([2]Лист1!$L:$L,AJ21),"") | AF21: =IFERROR(INDEX([2]Лист1!$J:$J,AJ21),"") | AG21: =IFERROR(INDEX([2]Лист1!$K:$K,AJ21),"") | AH21: =MATCH(L21,[2]Лист1!$A:$A,0) -> 4796 | AI21: =MATCH(M21,[2]Лист1!$A:$A,0) -> #N/A | AJ21: =MATCH(N21,[2]Лист1!$A:$A,0) -> #N/A
A22: 1 | B22: ЛСР-03-05-701АК | C22: 3 | E22: ТЦ_20.5.02.02_77_7702341124_01.06.2022_02 | F22: Коробка коммутации электропривода TB/ED-SS-30/32-2*EC2. Weidmuller 32 клемм 4H/N; III; QNC; | G22: шт. | H22: 76 | I22: 17239.58 | J22: =H22*I22 -> 1310208.1 | K22: =J22/SUM($J$2:$J$1590) -> 0.010260257 | L22: =IFERROR(INDEX([1]мтр!G:G,MATCH($F22,[1]мтр!$C:$C,0)),"") -> 5050 | M22: =IFERROR(INDEX([1]мтр!H:H,MATCH($F22,[1]мтр!$C:$C,0)),"") -> 0 | N22: =IFERROR(INDEX([1]мтр!I:I,MATCH($F22,[1]мтр!$C:$C,0)),"") -> 0 | O22: =IFERROR(AVERAGE(R22,X22,AD22),"") -> 37798.356 | P22: =IFERROR(INDEX([2]Лист1!$E:$E,AH22),"") -> Коробка Klippon TB/ED-SS-30/32-2*EC2. Транспорт экcпертно 5% | Q22: =IFERROR(INDEX([2]Лист1!$I:$I,AH22),"") -> шт. | R22: =IFERROR(INDEX([2]Лист1!$V:$V,AH22),"") -> 37798.356 | S22: =IFERROR(INDEX([2]Лист1!$L:$L,AH22),"") -> 44441 | T22: =IFERROR(INDEX([2]Лист1!$J:$J,AH22),"") -> Weidmuller | U22: =IFERROR(INDEX([2]Лист1!$K:$K,AH22),"") -> Письмо от А. Стрельцова, рук. "Атомное направление" | V22: =IFERROR(INDEX([2]Лист1!$E:$E,AI22),"") | W22: =IFERROR(INDEX([2]Лист1!$I:$I,AI22),"") | X22: =IFERROR(INDEX([2]Лист1!$V:$V,AI22),"") | Y22: =IFERROR(INDEX([2]Лист1!$L:$L,AI22),"") | Z22: =IFERROR(INDEX([2]Лист1!$J:$J,AI22),"") | AA22: =IFERROR(INDEX([2]Лист1!$K:$K,AI22),"") | AB22: =IFERROR(INDEX([2]Лист1!$E:$E,AJ22),"") | AC22: =IFERROR(INDEX([2]Лист1!$I:$I,AJ22),"") | AD22: =IFERROR(INDEX([2]Лист1!$V:$V,AJ22),"") | AE22: =IFERROR(INDEX([2]Лист1!$L:$L,AJ22),"") | AF22: =IFERROR(INDEX([2]Лист1!$J:$J,AJ22),"") | AG22: =IFERROR(INDEX([2]Лист1!$K:$K,AJ22),"") | AH22: =MATCH(L22,[2]Лист1!$A:$A,0) -> 2841 | AI22: =MATCH(M22,[2]Лист1!$A:$A,0) -> #N/A | AJ22: =MATCH(N22,[2]Лист1!$A:$A,0) -> #N/A
A23: 2 | B23: ЛСР-03-08-102С | C23: 3 | E23: 07.4.01.04-0002 | F23: Каркасы башен водонапорных решетчатых, прожекторные и молниезащиты, каркасы вентиляционных дымовых труб, опоры канатных дорог, высота до 200 м, масса 1 м от 50 до 100 кг_наружная обечайка | G23: т | H23: 91.9625 | I23: 13514.45 | J23: =H23*I23 -> 1242822.6 | K23: =J23/SUM($J$2:$J$1590) -> 0.0097325605 | L23: =IFERROR(INDEX([1]мтр!G:G,MATCH($F23,[1]мтр!$C:$C,0)),"") -> 7590 | M23: =IFERROR(INDEX([1]мтр!H:H,MATCH($F23,[1]мтр!$C:$C,0)),"") -> 7591 | N23: =IFERROR(INDEX([1]мтр!I:I,MATCH($F23,[1]мтр!$C:$C,0)),"") -> 0 | O23: =IFERROR(AVERAGE(R23,X23,AD23),"") -> 49555.459 | P23: =IFERROR(INDEX([2]Лист1!$E:$E,AH23),"") -> Усредненная цена готовых металлоконструкций (на примере здания ЦЕХА СМБ Арматурное хозяйство), с доставкой, без установки. Эскалация в фев.2023 по CAPMAS "round steel", окт.2019=11450 EGP/т, фев.2023=28370,5 EGP/т | Q23: =IFERROR(INDEX([2]Лист1!$I:$I,AH23),"") -> т | R23: =IFERROR(INDEX([2]Лист1!$V:$V,AH23),"") -> 44599.913 | S23: =IFERROR(INDEX([2]Лист1!$L:$L,AH23),"") -> 43758 | T23: =IFERROR(INDEX([2]Лист1!$J:$J,AH23),"") -> Arcons Egypt | U23: =IFERROR(INDEX([2]Лист1!$K:$K,AH23),"") -> ТКП Arcons Egypt 20.10.2019 Эскалация в фев.2023 по CAPMAS "round steel", окт.2019=11450 EGP/т, фев.2023=28370,5 EGP/т | V23: =IFERROR(INDEX([2]Лист1!$E:$E,AI23),"") -> Усредненная цена готовых металлоконструкций (на примере здания ЦЕХА СМБ Арматурное хозяйство), с доставкой, без установки. Эскалация в фев.2023 по CAPMAS "round steel", окт.2019=11450 EGP/т, фев.2023=28370,5 EGP/т | W23: =IFERROR(INDEX([2]Лист1!$I:$I,AI23),"") -> т | X23: =IFERROR(INDEX([2]Лист1!$V:$V,AI23),"") -> 54511.004 | Y23: =IFERROR(INDEX([2]Лист1!$L:$L,AI23),"") -> 43762 | Z23: =IFERROR(INDEX([2]Лист1!$J:$J,AI23),"") -> Steelcom | AA23: =IFERROR(INDEX([2]Лист1!$K:$K,AI23),"") -> ТКП Steelcom 24.10.2019Эскалация в фев.2023 по CAPMAS "round steel", окт.2019=11450 EGP/т, фев.2023=28370,5 EGP/т | AB23: =IFERROR(INDEX([2]Лист1!$E:$E,AJ23),"") | AC23: =IFERROR(INDEX([2]Лист1!$I:$I,AJ23),"") | AD23: =IFERROR(INDEX([2]Лист1!$V:$V,AJ23),"") | AE23: =IFERROR(INDEX([2]Лист1!$L:$L,AJ23),"") | AF23: =IFERROR(INDEX([2]Лист1!$J:$J,AJ23),"") | AG23: =IFERROR(INDEX([2]Лист1!$K:$K,AJ23),"") | AH23: =MATCH(L23,[2]Лист1!$A:$A,0) -> 6656 | AI23: =MATCH(M23,[2]Лист1!$A:$A,0) -> 6657 | AJ23: =MATCH(N23,[2]Лист1!$A:$A,0) -> #N/A
A24: 1 | B24: ЛСР-03-05-701АК | C24: 3 | E24: ТЦ_01.7.15.01_50_7710050305_31.05.2022_02 | F24: Анкер-шпилька HSA-R M12х145 Нж | G24: шт. | H24: 8736 | I24: 141.09 | J24: =H24*I24 -> 1232562.2 | K24: =J24/SUM($J$2:$J$1590) -> 0.0096522115 | L24: 7302 | M24: =IFERROR(INDEX([1]мтр!H:H,MATCH($F24,[1]мтр!$C:$C,0)),"") -> 0 | N24: =IFERROR(INDEX([1]мтр!I:I,MATCH($F24,[1]мтр!$C:$C,0)),"") -> 0 | O24: =IFERROR(AVERAGE(R24,X24,AD24),"") -> 316.58888 | P24: =IFERROR(INDEX([2]Лист1!$E:$E,AH24),"") -> Анкер-шпилька HSA-R M12x145 65/50/15. Транспорт экспертно 5% | Q24: =IFERROR(INDEX([2]Лист1!$I:$I,AH24),"") -> шт. | R24: =IFERROR(INDEX([2]Лист1!$V:$V,AH24),"") -> 316.58888 | S24: =IFERROR(INDEX([2]Лист1!$L:$L,AH24),"") -> 45087 | T24: =IFERROR(INDEX([2]Лист1!$J:$J,AH24),"") -> HILTI | U24: =IFERROR(INDEX([2]Лист1!$K:$K,AH24),"") -> https://www.hilti.it/c/CLS_FASTENER_7135/CLS_MECHANICAL_ANCHORS_7135/r5234?CHA_GLOBAL_ANC_SIZE=M12&CHD_ANCHOR_LENGTH=145%20mm&combo_content=750bc77ac94e3b3855a251dfb32ed670&salespackquantity=25%20pezzi&itemCode=2004210 | V24: =IFERROR(INDEX([2]Лист1!$E:$E,AI24),"") | W24: =IFERROR(INDEX([2]Лист1!$I:$I,AI24),"") | X24: =IFERROR(INDEX([2]Лист1!$V:$V,AI24),"") | Y24: =IFERROR(INDEX([2]Лист1!$L:$L,AI24),"") | Z24: =IFERROR(INDEX([2]Лист1!$J:$J,AI24),"") | AA24: =IFERROR(INDEX([2]Лист1!$K:$K,AI24),"") | AB24: =IFERROR(INDEX([2]Лист1!$E:$E,AJ24),"") | AC24: =IFERROR(INDEX([2]Лист1!$I:$I,AJ24),"") | AD24: =IFERROR(INDEX([2]Лист1!$V:$V,AJ24),"") | AE24: =IFERROR(INDEX([2]Лист1!$L:$L,AJ24),"") | AF24: =IFERROR(INDEX([2]Лист1!$J:$J,AJ24),"") | AG24: =IFERROR(INDEX([2]Лист1!$K:$K,AJ24),"") | AH24: =MATCH(L24,[2]Лист1!$A:$A,0) -> 6368 | AI24: =MATCH(M24,[2]Лист1!$A:$A,0) -> #N/A | AJ24: =MATCH(N24,[2]Лист1!$A:$A,0) -> #N/A
A25: 1 | B25: ЛСР-03-05-203ТМ | C25: 3 | E25: ТЦ_18.2.08.00_50_5503095632_05.07.2022_02 / КА п.25/ ЗАО "Сибгазстройдеталь" №897 | F25: Фильтр механический По типу ФС 125 С 16-0.4У DN 125; pmax=1.10 MPag; tmax=40 °С; Раб. среда: Вода химически обессоленная; Q=307.8 м?/ч; H-высота = 280 мм; L-длина = 400 мм; W-ширина = 199 мм; Кл 4Н_ФС125/16П-200-Ф1-Д1-УХЛ 1 ФС- фильтр сливной 125-номинальный диаметр, DN 16-давление 16 кг/см2 или (1,6Мпа) | G25: шт. | H25: 3 | I25: 392457.51 | J25: =H25*I25 -> 1177372.5 | K25: =J25/SUM($J$2:$J$1590) -> 0.0092200201 | L25: =IFERROR(INDEX([1]мтр!G:G,MATCH($F25,[1]мтр!$C:$C,0)),"") | M25: =IFERROR(INDEX([1]мтр!H:H,MATCH($F25,[1]мтр!$C:$C,0)),"") | N25: =IFERROR(INDEX([1]мтр!I:I,MATCH($F25,[1]мтр!$C:$C,0)),"") | O25: =IFERROR(AVERAGE(R25,X25,AD25),"") | P25: =IFERROR(INDEX([2]Лист1!$E:$E,AH25),"") | Q25: =IFERROR(INDEX([2]Лист1!$I:$I,AH25),"") | R25: =IFERROR(INDEX([2]Лист1!$V:$V,AH25),"") | S25: =IFERROR(INDEX([2]Лист1!$L:$L,AH25),"") | T25: =IFERROR(INDEX([2]Лист1!$J:$J,AH25),"") | U25: =IFERROR(INDEX([2]Лист1!$K:$K,AH25),"") | V25: =IFERROR(INDEX([2]Лист1!$E:$E,AI25),"") | W25: =IFERROR(INDEX([2]Лист1!$I:$I,AI25),"") | X25: =IFERROR(INDEX([2]Лист1!$V:$V,AI25),"") | Y25: =IFERROR(INDEX([2]Лист1!$L:$L,AI25),"") | Z25: =IFERROR(INDEX([2]Лист1!$J:$J,AI25),"") | AA25: =IFERROR(INDEX([2]Лист1!$K:$K,AI25),"") | AB25: =IFERROR(INDEX([2]Лист1!$E:$E,AJ25),"") | AC25: =IFERROR(INDEX([2]Лист1!$I:$I,AJ25),"") | AD25: =IFERROR(INDEX([2]Лист1!$V:$V,AJ25),"") | AE25: =IFERROR(INDEX([2]Лист1!$L:$L,AJ25),"") | AF25: =IFERROR(INDEX([2]Лист1!$J:$J,AJ25),"") | AG25: =IFERROR(INDEX([2]Лист1!$K:$K,AJ25),"") | AH25: =MATCH(L25,[2]Лист1!$A:$A,0) -> #N/A | AI25: =MATCH(M25,[2]Лист1!$A:$A,0) -> #N/A | AJ25: =MATCH(N25,[2]Лист1!$A:$A,0) -> #N/A
A26: 1 | B26: ЛСР-03-05-602Э | C26: 3 | E26: 21.1.08.03-0035 | F26: Кабель контрольный КВВГнг-FRLS 19х1,5 | G26: 1000 м | H26: 15.3 | I26: 69118.72 | J26: =H26*I26 -> 1057516.4 | K26: =J26/SUM($J$2:$J$1590) -> 0.0082814253 | L26: 7308 | M26: =IFERROR(INDEX([1]мтр!H:H,MATCH($F26,[1]мтр!$C:$C,0)),"") -> 0 | N26: =IFERROR(INDEX([1]мтр!I:I,MATCH($F26,[1]мтр!$C:$C,0)),"") -> 0 | O26: =IFERROR(AVERAGE(R26,X26,AD26),"") -> 198712.94 | P26: =IFERROR(INDEX([2]Лист1!$E:$E,AH26),"") -> Импорт из РФ_КВВГнг(А)-FRLS 19х1,5 660В ТУ 16.К19-11-2000 (ГОСТ 26411-85), Транспорт экспертно 5% | Q26: =IFERROR(INDEX([2]Лист1!$I:$I,AH26),"") -> 1000 м | R26: =IFERROR(INDEX([2]Лист1!$V:$V,AH26),"") -> 198712.94 | S26: =IFERROR(INDEX([2]Лист1!$L:$L,AH26),"") -> 45047 | T26: =IFERROR(INDEX([2]Лист1!$J:$J,AH26),"") -> Группа компаний "Электрокабель" | U26: =IFERROR(INDEX([2]Лист1!$K:$K,AH26),"") -> Прайс лист от 01.05.2023 группы компаний "Электрокабель" https://elektrokable.ru/Prais_kabel/Prais-list_kabel.xls | V26: =IFERROR(INDEX([2]Лист1!$E:$E,AI26),"") | W26: =IFERROR(INDEX([2]Лист1!$I:$I,AI26),"") | X26: =IFERROR(INDEX([2]Лист1!$V:$V,AI26),"") | Y26: =IFERROR(INDEX([2]Лист1!$L:$L,AI26),"") | Z26: =IFERROR(INDEX([2]Лист1!$J:$J,AI26),"") | AA26: =IFERROR(INDEX([2]Лист1!$K:$K,AI26),"") | AB26: =IFERROR(INDEX([2]Лист1!$E:$E,AJ26),"") | AC26: =IFERROR(INDEX([2]Лист1!$I:$I,AJ26),"") | AD26: =IFERROR(INDEX([2]Лист1!$V:$V,AJ26),"") | AE26: =IFERROR(INDEX([2]Лист1!$L:$L,AJ26),"") | AF26: =IFERROR(INDEX([2]Лист1!$J:$J,AJ26),"") | AG26: =IFERROR(INDEX([2]Лист1!$K:$K,AJ26),"") | AH26: =MATCH(L26,[2]Лист1!$A:$A,0) -> 6374 | AI26: =MATCH(M26,[2]Лист1!$A:$A,0) -> #N/A | AJ26: =MATCH(N26,[2]Лист1!$A:$A,0) -> #N/A
A27: 1 | B27: ЛСР-03-05-202ТМ | C27: 3 | E27: ТЦ_18.1.06.04_76_7610060282_05.05.22_02 / КА п.11 / ООО "Актан" № 955 | F27: Клапан запорный ручной (по типу А.КШ.Р.015.25.02.01), DN 15; Pmax= 0.6 Mpag; tmax= 35°C; Раб. среда: Обессоленная вода; Способ управления: Ручной привод; Тип присоединения: Фланцевый, Класс безопасности 4Н; материал - нж; с комплектом ответных фланцев под приварку с прокладками и крепежом_Кран шаровой А.КШ.Р.015.25.02.01 | G27: шт. | H27: 54 | I27: 19376.11 | J27: =H27*I27 -> 1046309.9 | K27: =J27/SUM($J$2:$J$1590) -> 0.0081936672 | L27: =IFERROR(INDEX([1]мтр!G:G,MATCH($F27,[1]мтр!$C:$C,0)),"") | M27: =IFERROR(INDEX([1]мтр!H:H,MATCH($F27,[1]мтр!$C:$C,0)),"") | N27: =IFERROR(INDEX([1]мтр!I:I,MATCH($F27,[1]мтр!$C:$C,0)),"") | O27: =IFERROR(AVERAGE(R27,X27,AD27),"") | P27: =IFERROR(INDEX([2]Лист1!$E:$E,AH27),"") | Q27: =IFERROR(INDEX([2]Лист1!$I:$I,AH27),"") | R27: =IFERROR(INDEX([2]Лист1!$V:$V,AH27),"") | S27: =IFERROR(INDEX([2]Лист1!$L:$L,AH27),"") | T27: =IFERROR(INDEX([2]Лист1!$J:$J,AH27),"") | U27: =IFERROR(INDEX([2]Лист1!$K:$K,AH27),"") | V27: =IFERROR(INDEX([2]Лист1!$E:$E,AI27),"") | W27: =IFERROR(INDEX([2]Лист1!$I:$I,AI27),"") | X27: =IFERROR(INDEX([2]Лист1!$V:$V,AI27),"") | Y27: =IFERROR(INDEX([2]Лист1!$L:$L,AI27),"") | Z27: =IFERROR(INDEX([2]Лист1!$J:$J,AI27),"") | AA27: =IFERROR(INDEX([2]Лист1!$K:$K,AI27),"") | AB27: =IFERROR(INDEX([2]Лист1!$E:$E,AJ27),"") | AC27: =IFERROR(INDEX([2]Лист1!$I:$I,AJ27),"") | AD27: =IFERROR(INDEX([2]Лист1!$V:$V,AJ27),"") | AE27: =IFERROR(INDEX([2]Лист1!$L:$L,AJ27),"") | AF27: =IFERROR(INDEX([2]Лист1!$J:$J,AJ27),"") | AG27: =IFERROR(INDEX([2]Лист1!$K:$K,AJ27),"") | AH27: =MATCH(L27,[2]Лист1!$A:$A,0) -> #N/A | AI27: =MATCH(M27,[2]Лист1!$A:$A,0) -> #N/A | AJ27: =MATCH(N27,[2]Лист1!$A:$A,0) -> #N/A
A28: 1 | B28: ЛСР-03-05-601СВ | C28: 3 | E28: ТЦ_20.2.07.00_31.03.2022_01/КА п.2/WIBE Group в России | F28: Кабельный лоток неперфорированный горячеоцинкованный, прямой, 100х100, длиной 2000 мм, с разделительной перегородкой и крышкой, включая монтажные элементы | G28: кг | H28: 2473.62 | I28: 398.56 | J28: =H28*I28 -> 985885.99 | K28: =J28/SUM($J$2:$J$1590) -> 0.0077204864 | L28: =IFERROR(INDEX([1]мтр!G:G,MATCH($F28,[1]мтр!$C:$C,0)),"") -> 5721 | M28: =IFERROR(INDEX([1]мтр!H:H,MATCH($F28,[1]мтр!$C:$C,0)),"") -> 0 | N28: =IFERROR(INDEX([1]мтр!I:I,MATCH($F28,[1]мтр!$C:$C,0)),"") -> 0 | O28: =IFERROR(AVERAGE(R28,X28,AD28),"") -> 359.93461 | P28: =IFERROR(INDEX([2]Лист1!$E:$E,AH28),"") -> Лоток листовой неперфорированный 100х100 L3000 сталь 0.7мм DKC 35101HDZ Транспорт экспертно 5% | Q28: =IFERROR(INDEX([2]Лист1!$I:$I,AH28),"") -> кг | R28: =IFERROR(INDEX([2]Лист1!$V:$V,AH28),"") -> 359.93461 | S28: =IFERROR(INDEX([2]Лист1!$L:$L,AH28),"") -> 44889 | T28: =IFERROR(INDEX([2]Лист1!$J:$J,AH28),"") -> N/A | U28: =IFERROR(INDEX([2]Лист1!$K:$K,AH28),"") -> https://rs24.ru/product/138276 (весовое значение: https://www.dkc.ru/ru/catalog/192/35101/) | V28: =IFERROR(INDEX([2]Лист1!$E:$E,AI28),"") | W28: =IFERROR(INDEX([2]Лист1!$I:$I,AI28),"") | X28: =IFERROR(INDEX([2]Лист1!$V:$V,AI28),"") | Y28: =IFERROR(INDEX([2]Лист1!$L:$L,AI28),"") | Z28: =IFERROR(INDEX([2]Лист1!$J:$J,AI28),"") | AA28: =IFERROR(INDEX([2]Лист1!$K:$K,AI28),"") | AB28: =IFERROR(INDEX([2]Лист1!$E:$E,AJ28),"") | AC28: =IFERROR(INDEX([2]Лист1!$I:$I,AJ28),"") | AD28: =IFERROR(INDEX([2]Лист1!$V:$V,AJ28),"") | AE28: =IFERROR(INDEX([2]Лист1!$L:$L,AJ28),"") | AF28: =IFERROR(INDEX([2]Лист1!$J:$J,AJ28),"") | AG28: =IFERROR(INDEX([2]Лист1!$K:$K,AJ28),"") | AH28: =MATCH(L28,[2]Лист1!$A:$A,0) -> 4943 | AI28: =MATCH(M28,[2]Лист1!$A:$A,0) -> #N/A | AJ28: =MATCH(N28,[2]Лист1!$A:$A,0) -> #N/A
A29: 1 | B29: ЛСР-03-05-101C | C29: 3 | E29: 12.1.02.10-0131 | F29: ТПО-мембрана гидроизоляционная, марка Sikaplan "WT 1200-20C" ("Sarnafil TG68-20") | G29: м2 | H29: 1797.12 | I29: 548.11 | J29: =H29*I29 -> 985019.44 | K29: =J29/SUM($J$2:$J$1590) -> 0.0077137005 | L29: =IFERROR(INDEX([1]мтр!G:G,MATCH($F29,[1]мтр!$C:$C,0)),"") -> 4683 | M29: =IFERROR(INDEX([1]мтр!H:H,MATCH($F29,[1]мтр!$C:$C,0)),"") -> 0 | N29: =IFERROR(INDEX([1]мтр!I:I,MATCH($F29,[1]мтр!$C:$C,0)),"") -> 0 | O29: =IFERROR(AVERAGE(R29,X29,AD29),"") -> 600 | P29: =IFERROR(INDEX([2]Лист1!$E:$E,AH29),"") -> ТПО-мембрана гидроизоляционная, марка Sikaplan WT 1200-20C | Q29: =IFERROR(INDEX([2]Лист1!$I:$I,AH29),"") -> м2 | R29: =IFERROR(INDEX([2]Лист1!$V:$V,AH29),"") -> 600 | S29: =IFERROR(INDEX([2]Лист1!$L:$L,AH29),"") -> 44608 | T29: =IFERROR(INDEX([2]Лист1!$J:$J,AH29),"") -> Sika Egypt For Construction Chemicals | U29: =IFERROR(INDEX([2]Лист1!$K:$K,AH29),"") -> Предложение SikaEgypt от 16.02.2022 | V29: =IFERROR(INDEX([2]Лист1!$E:$E,AI29),"") | W29: =IFERROR(INDEX([2]Лист1!$I:$I,AI29),"") | X29: =IFERROR(INDEX([2]Лист1!$V:$V,AI29),"") | Y29: =IFERROR(INDEX([2]Лист1!$L:$L,AI29),"") | Z29: =IFERROR(INDEX([2]Лист1!$J:$J,AI29),"") | AA29: =IFERROR(INDEX([2]Лист1!$K:$K,AI29),"") | AB29: =IFERROR(INDEX([2]Лист1!$E:$E,AJ29),"") | AC29: =IFERROR(INDEX([2]Лист1!$I:$I,AJ29),"") | AD29: =IFERROR(INDEX([2]Лист1!$V:$V,AJ29),"") | AE29: =IFERROR(INDEX([2]Лист1!$L:$L,AJ29),"") | AF29: =IFERROR(INDEX([2]Лист1!$J:$J,AJ29),"") | AG29: =IFERROR(INDEX([2]Лист1!$K:$K,AJ29),"") | AH29: =MATCH(L29,[2]Лист1!$A:$A,0) -> 3792 | AI29: =MATCH(M29,[2]Лист1!$A:$A,0) -> #N/A | AJ29: =MATCH(N29,[2]Лист1!$A:$A,0) -> #N/A
A30: 1 | B30: ЛСР-03-05-101C | C30: 3 | E30: 01.7.07.27-0013 | F30: Шпонка ТПО гидроизоляционная, наружного заложения для деформационных швов, марка "Sika Waterbar WT DF 400/30 MP" | G30: м | H30: 692.16 | I30: 1391.09 | J30: =H30*I30 -> 962856.85 | K30: =J30/SUM($J$2:$J$1590) -> 0.007540145 | L30: 3359 | M30: =IFERROR(INDEX([1]мтр!H:H,MATCH($F30,[1]мтр!$C:$C,0)),"") -> 0 | N30: =IFERROR(INDEX([1]мтр!I:I,MATCH($F30,[1]мтр!$C:$C,0)),"") -> 0 | O30: =IFERROR(AVERAGE(R30,X30,AD30),"") -> 684 | P30: =IFERROR(INDEX([2]Лист1!$E:$E,AH30),"") -> Шпонка Sika Waterbar WT AF 310/30. Транспорт от 50 тыс.EGP - бесплатно. | Q30: =IFERROR(INDEX([2]Лист1!$I:$I,AH30),"") -> м | R30: =IFERROR(INDEX([2]Лист1!$V:$V,AH30),"") -> 684 | S30: =IFERROR(INDEX([2]Лист1!$L:$L,AH30),"") -> 44320 | T30: =IFERROR(INDEX([2]Лист1!$J:$J,AH30),"") -> Sika Egypt For Construction Chemicals | U30: =IFERROR(INDEX([2]Лист1!$K:$K,AH30),"") -> Предложение SikaEgypt от 04.05.2021 | V30: =IFERROR(INDEX([2]Лист1!$E:$E,AI30),"") | W30: =IFERROR(INDEX([2]Лист1!$I:$I,AI30),"") | X30: =IFERROR(INDEX([2]Лист1!$V:$V,AI30),"") | Y30: =IFERROR(INDEX([2]Лист1!$L:$L,AI30),"") | Z30: =IFERROR(INDEX([2]Лист1!$J:$J,AI30),"") | AA30: =IFERROR(INDEX([2]Лист1!$K:$K,AI30),"") | AB30: =IFERROR(INDEX([2]Лист1!$E:$E,AJ30),"") | AC30: =IFERROR(INDEX([2]Лист1!$I:$I,AJ30),"") | AD30: =IFERROR(INDEX([2]Лист1!$V:$V,AJ30),"") | AE30: =IFERROR(INDEX([2]Лист1!$L:$L,AJ30),"") | AF30: =IFERROR(INDEX([2]Лист1!$J:$J,AJ30),"") | AG30: =IFERROR(INDEX([2]Лист1!$K:$K,AJ30),"") | AH30: =MATCH(L30,[2]Лист1!$A:$A,0) -> 4508 | AI30: =MATCH(M30,[2]Лист1!$A:$A,0) -> #N/A | AJ30: =MATCH(N30,[2]Лист1!$A:$A,0) -> #N/A
A31: 1 | B31: ЛСР-03-05-202ТМ | C31: 3 | E31: ТЦ_18.1.03.02_76_7610060282_05.05.22_02 / КА п.9 / ООО "Актан" № 955 | F31: Затвор дисковый поворотный (по типу А.КШ.Р.150.25.02.01), DN 150; Pmax=0.6MPag; Tmax=35 °С; Раб. среда: Обессоленная вода; Способ управления: Ручной привод; Тип присоединения: Фланцевый; Класс безопасности 4Н; материал - нж; с комплектом ответных фланцев под приварку с прокладками и крепежом_Кран шаровой А.КШ.Р.150.25.02.01 | G31: шт. | H31: 4 | I31: 229485.17 | J31: =H31*I31 -> 917940.68 | K31: =J31/SUM($J$2:$J$1590) -> 0.0071884058 | L31: =IFERROR(INDEX([1]мтр!G:G,MATCH($F31,[1]мтр!$C:$C,0)),"") | M31: =IFERROR(INDEX([1]мтр!H:H,MATCH($F31,[1]мтр!$C:$C,0)),"") | N31: =IFERROR(INDEX([1]мтр!I:I,MATCH($F31,[1]мтр!$C:$C,0)),"") | O31: =IFERROR(AVERAGE(R31,X31,AD31),"") | P31: =IFERROR(INDEX([2]Лист1!$E:$E,AH31),"") | Q31: =IFERROR(INDEX([2]Лист1!$I:$I,AH31),"") | R31: =IFERROR(INDEX([2]Лист1!$V:$V,AH31),"") | S31: =IFERROR(INDEX([2]Лист1!$L:$L,AH31),"") | T31: =IFERROR(INDEX([2]Лист1!$J:$J,AH31),"") | U31: =IFERROR(INDEX([2]Лист1!$K:$K,AH31),"") | V31: =IFERROR(INDEX([2]Лист1!$E:$E,AI31),"") | W31: =IFERROR(INDEX([2]Лист1!$I:$I,AI31),"") | X31: =IFERROR(INDEX([2]Лист1!$V:$V,AI31),"") | Y31: =IFERROR(INDEX([2]Лист1!$L:$L,AI31),"") | Z31: =IFERROR(INDEX([2]Лист1!$J:$J,AI31),"") | AA31: =IFERROR(INDEX([2]Лист1!$K:$K,AI31),"") | AB31: =IFERROR(INDEX([2]Лист1!$E:$E,AJ31),"") | AC31: =IFERROR(INDEX([2]Лист1!$I:$I,AJ31),"") | AD31: =IFERROR(INDEX([2]Лист1!$V:$V,AJ31),"") | AE31: =IFERROR(INDEX([2]Лист1!$L:$L,AJ31),"") | AF31: =IFERROR(INDEX([2]Лист1!$J:$J,AJ31),"") | AG31: =IFERROR(INDEX([2]Лист1!$K:$K,AJ31),"") | AH31: =MATCH(L31,[2]Лист1!$A:$A,0) -> #N/A | AI31: =MATCH(M31,[2]Лист1!$A:$A,0) -> #N/A | AJ31: =MATCH(N31,[2]Лист1!$A:$A,0) -> #N/A
A32: 1 | B32: ЛСР-03-05-203ТМ | C32: 3 | E32: ТЦ_18.1.06.00_50_5503095632_05.07.2022_02 /КА п.50/ ЗАО "Сибгазстройдеталь" №897 | F32: Запорная арматура По типу 2с-25-1Н DN 150; pmax=0.40 MPag; tmax=155 °С / °C; Раб. среда:Пар собственных нужд; Способ управления: Ручной привод; Тип присоединения: Под приварку Кл.4Н, угл.ст. | G32: шт. | H32: 6 | I32: 151166.68 | J32: =H32*I32 -> 907000.08 | K32: =J32/SUM($J$2:$J$1590) -> 0.0071027298 | L32: 7314 | M32: =IFERROR(INDEX([1]мтр!H:H,MATCH($F32,[1]мтр!$C:$C,0)),"") | N32: =IFERROR(INDEX([1]мтр!I:I,MATCH($F32,[1]мтр!$C:$C,0)),"") | O32: =IFERROR(AVERAGE(R32,X32,AD32),"") -> 0 | P32: =IFERROR(INDEX([2]Лист1!$E:$E,AH32),"") -> 0 | Q32: =IFERROR(INDEX([2]Лист1!$I:$I,AH32),"") -> 0 | R32: =IFERROR(INDEX([2]Лист1!$V:$V,AH32),"") -> 0 | S32: =IFERROR(INDEX([2]Лист1!$L:$L,AH32),"") -> 0 | T32: =IFERROR(INDEX([2]Лист1!$J:$J,AH32),"") -> 0 | U32: =IFERROR(INDEX([2]Лист1!$K:$K,AH32),"") -> 0 | V32: =IFERROR(INDEX([2]Лист1!$E:$E,AI32),"") | W32: =IFERROR(INDEX([2]Лист1!$I:$I,AI32),"") | X32: =IFERROR(INDEX([2]Лист1!$V:$V,AI32),"") | Y32: =IFERROR(INDEX([2]Лист1!$L:$L,AI32),"") | Z32: =IFERROR(INDEX([2]Лист1!$J:$J,AI32),"") | AA32: =IFERROR(INDEX([2]Лист1!$K:$K,AI32),"") | AB32: =IFERROR(INDEX([2]Лист1!$E:$E,AJ32),"") | AC32: =IFERROR(INDEX([2]Лист1!$I:$I,AJ32),"") | AD32: =IFERROR(INDEX([2]Лист1!$V:$V,AJ32),"") | AE32: =IFERROR(INDEX([2]Лист1!$L:$L,AJ32),"") | AF32: =IFERROR(INDEX([2]Лист1!$J:$J,AJ32),"") | AG32: =IFERROR(INDEX([2]Лист1!$K:$K,AJ32),"") | AH32: =MATCH(L32,[2]Лист1!$A:$A,0) -> 6380 | AI32: =MATCH(M32,[2]Лист1!$A:$A,0) -> #N/A | AJ32: =MATCH(N32,[2]Лист1!$A:$A,0) -> #N/A
A33: 1 | B33: ЛСР-03-05-206ТМ | C33: 3 | E33: ТЦ_23.7.01.02_31_3123315768_20.05.2022_02/ КА п.76/ ООО "Белэнергомаш-БЗЭМ" №006-00073 | F33: Трубопроводы низкого давления из углеродистой стали, 4 класса безопасности, Ду > 80мм_DN250, DN200, DN150. | G33: т | H33: 3.645 | I33: 211499.32 | J33: =H33*I33 -> 770915.02 | K33: =J33/SUM($J$2:$J$1590) -> 0.0060370459 | L33: =IFERROR(INDEX([1]мтр!G:G,MATCH($F33,[1]мтр!$C:$C,0)),"") -> 4859 | M33: =IFERROR(INDEX([1]мтр!H:H,MATCH($F33,[1]мтр!$C:$C,0)),"") -> 0 | N33: =IFERROR(INDEX([1]мтр!I:I,MATCH($F33,[1]мтр!$C:$C,0)),"") -> 0 | O33: =IFERROR(AVERAGE(R33,X33,AD33),"") -> 479788.26 | P33: =IFERROR(INDEX([2]Лист1!$E:$E,AH33),"") -> Трубопроводы низкого давления из углеродистой стали зданий UJA, UKD. Объём: 4526466 руб. / 2939,52 кг = 1540 RUB/кг. Транспорт 5800 USD (Договор ЕОС-закупки №629007, №7720/220816 от 07.09.2022, АСЭ_Рускон) /40DV контейнер 25 т, класс груза - 2, загрузка 85%. | Q33: =IFERROR(INDEX([2]Лист1!$I:$I,AH33),"") -> т | R33: =IFERROR(INDEX([2]Лист1!$V:$V,AH33),"") -> 479788.26 | S33: =IFERROR(INDEX([2]Лист1!$L:$L,AH33),"") -> 44753 | T33: =IFERROR(INDEX([2]Лист1!$J:$J,AH33),"") -> Белэнергомаш-БЗЭМ | U33: =IFERROR(INDEX([2]Лист1!$K:$K,AH33),"") -> Поставка трубопроводов по лоту 19677-248 Куд3;4. НМЦ от 11.07.2022, рассчитанная на основании п.1 раздела 3 главы 3 (приложения №8 к ЕОСЗ). | V33: =IFERROR(INDEX([2]Лист1!$E:$E,AI33),"") | W33: =IFERROR(INDEX([2]Лист1!$I:$I,AI33),"") | X33: =IFERROR(INDEX([2]Лист1!$V:$V,AI33),"") | Y33: =IFERROR(INDEX([2]Лист1!$L:$L,AI33),"") | Z33: =IFERROR(INDEX([2]Лист1!$J:$J,AI33),"") | AA33: =IFERROR(INDEX([2]Лист1!$K:$K,AI33),"") | AB33: =IFERROR(INDEX([2]Лист1!$E:$E,AJ33),"") | AC33: =IFERROR(INDEX([2]Лист1!$I:$I,AJ33),"") | AD33: =IFERROR(INDEX([2]Лист1!$V:$V,AJ33),"") | AE33: =IFERROR(INDEX([2]Лист1!$L:$L,AJ33),"") | AF33: =IFERROR(INDEX([2]Лист1!$J:$J,AJ33),"") | AG33: =IFERROR(INDEX([2]Лист1!$K:$K,AJ33),"") | AH33: =MATCH(L33,[2]Лист1!$A:$A,0) -> 4796 | AI33: =MATCH(M33,[2]Лист1!$A:$A,0) -> #N/A | AJ33: =MATCH(N33,[2]Лист1!$A:$A,0) -> #N/A
A34: 1 | B34: ЛСР-03-05-101C | C34: 3 | E34: 08.4.03.03-0009 | F34: Сталь арматурная рифленая свариваемая, класс A500С, диаметр 25 мм_А500C (d20-32) | G34: т | H34: 140 | I34: 5488.69 | J34: =H34*I34 -> 768416.6 | K34: =J34/SUM($J$2:$J$1590) -> 0.0060174807 | L34: =IFERROR(INDEX([1]мтр!G:G,MATCH($F34,[1]мтр!$C:$C,0)),"") -> 7509 | M34: =IFERROR(INDEX([1]мтр!H:H,MATCH($F34,[1]мтр!$C:$C,0)),"") -> 0 | N34: =IFERROR(INDEX([1]мтр!I:I,MATCH($F34,[1]мтр!$C:$C,0)),"") -> 0 | O34: =IFERROR(AVERAGE(R34,X34,AD34),"") -> 16541.58 | P34: =IFERROR(INDEX([2]Лист1!$E:$E,AH34),"") -> Арматура стальная периодического профиля, класс B500DWR, диаметр 6 - 40 мм | Q34: =IFERROR(INDEX([2]Лист1!$I:$I,AH34),"") -> т | R34: =IFERROR(INDEX([2]Лист1!$V:$V,AH34),"") -> 16541.58 | S34: =IFERROR(INDEX([2]Лист1!$L:$L,AH34),"") -> 44984 | T34: =IFERROR(INDEX([2]Лист1!$J:$J,AH34),"") -> N/A | U34: =IFERROR(INDEX([2]Лист1!$K:$K,AH34),"") -> Справочник сметных цен на строильные материалы, изделия и конструкции для строительства АЭС Эль-Дабаа, Арабская республика Египет. III квартал 2022 года, ГК Росатом №05-0077 | V34: =IFERROR(INDEX([2]Лист1!$E:$E,AI34),"") | W34: =IFERROR(INDEX([2]Лист1!$I:$I,AI34),"") | X34: =IFERROR(INDEX([2]Лист1!$V:$V,AI34),"") | Y34: =IFERROR(INDEX([2]Лист1!$L:$L,AI34),"") | Z34: =IFERROR(INDEX([2]Лист1!$J:$J,AI34),"") | AA34: =IFERROR(INDEX([2]Лист1!$K:$K,AI34),"") | AB34: =IFERROR(INDEX([2]Лист1!$E:$E,AJ34),"") | AC34: =IFERROR(INDEX([2]Лист1!$I:$I,AJ34),"") | AD34: =IFERROR(INDEX([2]Лист1!$V:$V,AJ34),"") | AE34: =IFERROR(INDEX([2]Лист1!$L:$L,AJ34),"") | AF34: =IFERROR(INDEX([2]Лист1!$J:$J,AJ34),"") | AG34: =IFERROR(INDEX([2]Лист1!$K:$K,AJ34),"") | AH34: =MATCH(L34,[2]Лист1!$A:$A,0) -> 6575 | AI34: =MATCH(M34,[2]Лист1!$A:$A,0) -> #N/A | AJ34: =MATCH(N34,[2]Лист1!$A:$A,0) -> #N/A
A35: 3 | B35: ЛСР-03-06-201ТМ | C35: 3 | E35: ТЦ_23.7.01.02_31_3123315768_20.05.2022_02/ КА п.4/ Энергомаш ООО "Белэнергомаш-БЗЭМ" №006-00073 | F35: Трубопроводы низкого давления из нержавеющей стали 4 класса безопасности Ду > 80мм _ 159х6 мм | G35: т | H35: 0.911 | I35: 799960.85 | J35: =H35*I35 -> 728764.33 | K35: =J35/SUM($J$2:$J$1590) -> 0.0057069633 | L35: =IFERROR(INDEX([1]мтр!G:G,MATCH($F35,[1]мтр!$C:$C,0)),"") -> 4861 | M35: =IFERROR(INDEX([1]мтр!H:H,MATCH($F35,[1]мтр!$C:$C,0)),"") -> 0 | N35: =IFERROR(INDEX([1]мтр!I:I,MATCH($F35,[1]мтр!$C:$C,0)),"") -> 0 | O35: =IFERROR(AVERAGE(R35,X35,AD35),"") -> 2050605.2 | P35: =IFERROR(INDEX([2]Лист1!$E:$E,AH35),"") -> Трубопроводы низкого давления из нержавеющей стали зданий UJA, UKD. Объём: 40 315 616 руб. / 6 074,16 кг = 6637 RUB/кг. Транспорт 5800 USD (Договор ЕОС-закупки №629007, №7720/220816 от 07.09.2022, АСЭ_Рускон) /40DV контейнер 25 т, класс груза - 2, загрузка 85%. | Q35: =IFERROR(INDEX([2]Лист1!$I:$I,AH35),"") -> т | R35: =IFERROR(INDEX([2]Лист1!$V:$V,AH35),"") -> 2050605.2 | S35: =IFERROR(INDEX([2]Лист1!$L:$L,AH35),"") -> 44753 | T35: =IFERROR(INDEX([2]Лист1!$J:$J,AH35),"") -> Белэнергомаш-БЗЭМ | U35: =IFERROR(INDEX([2]Лист1!$K:$K,AH35),"") -> Поставка трубопроводов по лоту 19677-248 Куд3;4. НМЦ от 11.07.2022, рассчитанная на основании п.1 раздела 3 главы 3 (приложения №8 к ЕОСЗ). | V35: =IFERROR(INDEX([2]Лист1!$E:$E,AI35),"") | W35: =IFERROR(INDEX([2]Лист1!$I:$I,AI35),"") | X35: =IFERROR(INDEX([2]Лист1!$V:$V,AI35),"") | Y35: =IFERROR(INDEX([2]Лист1!$L:$L,AI35),"") | Z35: =IFERROR(INDEX([2]Лист1!$J:$J,AI35),"") | AA35: =IFERROR(INDEX([2]Лист1!$K:$K,AI35),"") | AB35: =IFERROR(INDEX([2]Лист1!$E:$E,AJ35),"") | AC35: =IFERROR(INDEX([2]Лист1!$I:$I,AJ35),"") | AD35: =IFERROR(INDEX([2]Лист1!$V:$V,AJ35),"") | AE35: =IFERROR(INDEX([2]Лист1!$L:$L,AJ35),"") | AF35: =IFERROR(INDEX([2]Лист1!$J:$J,AJ35),"") | AG35: =IFERROR(INDEX([2]Лист1!$K:$K,AJ35),"") | AH35: =MATCH(L35,[2]Лист1!$A:$A,0) -> 4798 | AI35: =MATCH(M35,[2]Лист1!$A:$A,0) -> #N/A | AJ35: =MATCH(N35,[2]Лист1!$A:$A,0) -> #N/A
A36: 3 | B36: ЛСР-03-06-101С | C36: 3 | E36: 04.1.02.05-0014 | F36: Смеси бетонные тяжелого бетона (БСТ), класс В45 (М600)_Бетон B45 W8 на сульфатостойком цементе | G36: м3 | H36: 213.15 | I36: 3406.74 | J36: =H36*I36 -> 726146.63 | K36: =J36/SUM($J$2:$J$1590) -> 0.005686464 | L36: =IFERROR(INDEX([1]мтр!G:G,MATCH($F36,[1]мтр!$C:$C,0)),"") -> 5710 | M36: =IFERROR(INDEX([1]мтр!H:H,MATCH($F36,[1]мтр!$C:$C,0)),"") -> 0 | N36: =IFERROR(INDEX([1]мтр!I:I,MATCH($F36,[1]мтр!$C:$C,0)),"") -> 0 | O36: =IFERROR(AVERAGE(R36,X36,AD36),"") -> 2207.07 | P36: =IFERROR(INDEX([2]Лист1!$E:$E,AH36),"") -> Бетон тяжелый на сульфатостойком портландцементе, класс В45 П5 W8 SRC XS3, XA3 | Q36: =IFERROR(INDEX([2]Лист1!$I:$I,AH36),"") -> м3 | R36: =IFERROR(INDEX([2]Лист1!$V:$V,AH36),"") -> 2207.07 | S36: =IFERROR(INDEX([2]Лист1!$L:$L,AH36),"") -> 44872 | T36: =IFERROR(INDEX([2]Лист1!$J:$J,AH36),"") -> N/A | U36: =IFERROR(INDEX([2]Лист1!$K:$K,AH36),"") -> Справочник сметных цен на строильные материалы, изделия и конструкции для строительства АЭС Эль-Дабаа, Арабская республика Египет. II квартал 2022 года, ГК Росатом №05-0070 | V36: =IFERROR(INDEX([2]Лист1!$E:$E,AI36),"") | W36: =IFERROR(INDEX([2]Лист1!$I:$I,AI36),"") | X36: =IFERROR(INDEX([2]Лист1!$V:$V,AI36),"") | Y36: =IFERROR(INDEX([2]Лист1!$L:$L,AI36),"") | Z36: =IFERROR(INDEX([2]Лист1!$J:$J,AI36),"") | AA36: =IFERROR(INDEX([2]Лист1!$K:$K,AI36),"") | AB36: =IFERROR(INDEX([2]Лист1!$E:$E,AJ36),"") | AC36: =IFERROR(INDEX([2]Лист1!$I:$I,AJ36),"") | AD36: =IFERROR(INDEX([2]Лист1!$V:$V,AJ36),"") | AE36: =IFERROR(INDEX([2]Лист1!$L:$L,AJ36),"") | AF36: =IFERROR(INDEX([2]Лист1!$J:$J,AJ36),"") | AG36: =IFERROR(INDEX([2]Лист1!$K:$K,AJ36),"") | AH36: =MATCH(L36,[2]Лист1!$A:$A,0) -> 463 | AI36: =MATCH(M36,[2]Лист1!$A:$A,0) -> #N/A | AJ36: =MATCH(N36,[2]Лист1!$A:$A,0) -> #N/A
A37: 1 | B37: ЛСР-03-05-602Э | C37: 3 | E37: 21.1.06.10-0314 | F37: Кабель силовой с медными жилами ПвПнг(A)-HF 5х16-1000_Кабель силовой 1 кВ 5*16мм2 | G37: 1000 м | H37: 5.1 | I37: 137838.06 | J37: =H37*I37 -> 702974.11 | K37: =J37/SUM($J$2:$J$1590) -> 0.0055049997 | L37: =IFERROR(INDEX([1]мтр!G:G,MATCH($F37,[1]мтр!$C:$C,0)),"") -> 7605 | M37: =IFERROR(INDEX([1]мтр!H:H,MATCH($F37,[1]мтр!$C:$C,0)),"") -> 0 | N37: =IFERROR(INDEX([1]мтр!I:I,MATCH($F37,[1]мтр!$C:$C,0)),"") -> 0 | O37: =IFERROR(AVERAGE(R37,X37,AD37),"") -> 493339.27 | P37: =IFERROR(INDEX([2]Лист1!$E:$E,AH37),"") -> Кабель силовой ПвПГнг(А)-HF 5х16мк(N,PE)-1кВ ТУ 16.К71-304-2001 (ГОСТ 31996-2012), транспорт 5% | Q37: =IFERROR(INDEX([2]Лист1!$I:$I,AH37),"") -> 1000 м | R37: =IFERROR(INDEX([2]Лист1!$V:$V,AH37),"") -> 493339.27 | S37: =IFERROR(INDEX([2]Лист1!$L:$L,AH37),"") -> 44958 | T37: =IFERROR(INDEX([2]Лист1!$J:$J,AH37),"") -> Группа компаний "Электрокабель" | U37: =IFERROR(INDEX([2]Лист1!$K:$K,AH37),"") -> Прайс лист от 01.02.2023 группы компаний "Электрокабель" https://elektrokable.ru/price_lists.php | V37: =IFERROR(INDEX([2]Лист1!$E:$E,AI37),"") | W37: =IFERROR(INDEX([2]Лист1!$I:$I,AI37),"") | X37: =IFERROR(INDEX([2]Лист1!$V:$V,AI37),"") | Y37: =IFERROR(INDEX([2]Лист1!$L:$L,AI37),"") | Z37: =IFERROR(INDEX([2]Лист1!$J:$J,AI37),"") | AA37: =IFERROR(INDEX([2]Лист1!$K:$K,AI37),"") | AB37: =IFERROR(INDEX([2]Лист1!$E:$E,AJ37),"") | AC37: =IFERROR(INDEX([2]Лист1!$I:$I,AJ37),"") | AD37: =IFERROR(INDEX([2]Лист1!$V:$V,AJ37),"") | AE37: =IFERROR(INDEX([2]Лист1!$L:$L,AJ37),"") | AF37: =IFERROR(INDEX([2]Лист1!$J:$J,AJ37),"") | AG37: =IFERROR(INDEX([2]Лист1!$K:$K,AJ37),"") | AH37: =MATCH(L37,[2]Лист1!$A:$A,0) -> 6671 | AI37: =MATCH(M37,[2]Лист1!$A:$A,0) -> #N/A | AJ37: =MATCH(N37,[2]Лист1!$A:$A,0) -> #N/A
A38: 1 | B38: ЛСР-03-05-203ТМ | C38: 3 | E38: ТЦ_18.1.06.00_2_50_5503095632_05.07.2022_02 /КА п.27/ ЗАО "Сибгазстройдеталь" №897 | F38: Запорная арматура По типу 2с-27-2Н DN 200; pmax=1.3 MPag; tmax=195 °С / °C; Раб. среда: Пар насыщенный; Способ управления: Ручной привод; Тип присоединения: Под приварку; Кл 4Н, угл.ст | G38: шт. | H38: 4 | I38: 147436.32 | J38: =H38*I38 -> 589745.28 | K38: =J38/SUM($J$2:$J$1590) -> 0.0046183032 | L38: =IFERROR(INDEX([1]мтр!G:G,MATCH($F38,[1]мтр!$C:$C,0)),"") | M38: =IFERROR(INDEX([1]мтр!H:H,MATCH($F38,[1]мтр!$C:$C,0)),"") | N38: =IFERROR(INDEX([1]мтр!I:I,MATCH($F38,[1]мтр!$C:$C,0)),"") | O38: =IFERROR(AVERAGE(R38,X38,AD38),"") | P38: =IFERROR(INDEX([2]Лист1!$E:$E,AH38),"") | Q38: =IFERROR(INDEX([2]Лист1!$I:$I,AH38),"") | R38: =IFERROR(INDEX([2]Лист1!$V:$V,AH38),"") | S38: =IFERROR(INDEX([2]Лист1!$L:$L,AH38),"") | T38: =IFERROR(INDEX([2]Лист1!$J:$J,AH38),"") | U38: =IFERROR(INDEX([2]Лист1!$K:$K,AH38),"") | V38: =IFERROR(INDEX([2]Лист1!$E:$E,AI38),"") | W38: =IFERROR(INDEX([2]Лист1!$I:$I,AI38),"") | X38: =IFERROR(INDEX([2]Лист1!$V:$V,AI38),"") | Y38: =IFERROR(INDEX([2]Лист1!$L:$L,AI38),"") | Z38: =IFERROR(INDEX([2]Лист1!$J:$J,AI38),"") | AA38: =IFERROR(INDEX([2]Лист1!$K:$K,AI38),"") | AB38: =IFERROR(INDEX([2]Лист1!$E:$E,AJ38),"") | AC38: =IFERROR(INDEX([2]Лист1!$I:$I,AJ38),"") | AD38: =IFERROR(INDEX([2]Лист1!$V:$V,AJ38),"") | AE38: =IFERROR(INDEX([2]Лист1!$L:$L,AJ38),"") | AF38: =IFERROR(INDEX([2]Лист1!$J:$J,AJ38),"") | AG38: =IFERROR(INDEX([2]Лист1!$K:$K,AJ38),"") | AH38: =MATCH(L38,[2]Лист1!$A:$A,0) -> #N/A | AI38: =MATCH(M38,[2]Лист1!$A:$A,0) -> #N/A | AJ38: =MATCH(N38,[2]Лист1!$A:$A,0) -> #N/A
A39: 1 | B39: ЛСР-03-05-602Э | C39: 3 | E39: 21.1.06.10-0186 | F39: Кабель силовой с медными жилами ВВГнг(A)-FRLS 4х6ок(N)-1000_Кабель силовой 4х6мм2-1кВ | G39: 1000 м | H39: 10.2 | I39: 56503.43 | J39: =H39*I39 -> 576334.99 | K39: =J39/SUM($J$2:$J$1590) -> 0.004513287 | L39: 7310 | M39: =IFERROR(INDEX([1]мтр!H:H,MATCH($F39,[1]мтр!$C:$C,0)),"") -> 0 | N39: =IFERROR(INDEX([1]мтр!I:I,MATCH($F39,[1]мтр!$C:$C,0)),"") -> 0 | O39: =IFERROR(AVERAGE(R39,X39,AD39),"") -> 137806.99 | P39: =IFERROR(INDEX([2]Лист1!$E:$E,AH39),"") -> Импорт из РФ_ВВГнг(А)-FRLS 4х6ок(N)-1кВ ТУ 16.К19-11-2000 (ГОСТ 31996-2012), Транспорт экспертно 5% | Q39: =IFERROR(INDEX([2]Лист1!$I:$I,AH39),"") -> 1000 м | R39: =IFERROR(INDEX([2]Лист1!$V:$V,AH39),"") -> 137806.99 | S39: =IFERROR(INDEX([2]Лист1!$L:$L,AH39),"") -> 45047 | T39: =IFERROR(INDEX([2]Лист1!$J:$J,AH39),"") -> Группа компаний "Электрокабель" | U39: =IFERROR(INDEX([2]Лист1!$K:$K,AH39),"") -> Прайс лист от 01.05.2023 группы компаний "Электрокабель" https://elektrokable.ru/Prais_kabel/Prais-list_kabel.xls | V39: =IFERROR(INDEX([2]Лист1!$E:$E,AI39),"") | W39: =IFERROR(INDEX([2]Лист1!$I:$I,AI39),"") | X39: =IFERROR(INDEX([2]Лист1!$V:$V,AI39),"") | Y39: =IFERROR(INDEX([2]Лист1!$L:$L,AI39),"") | Z39: =IFERROR(INDEX([2]Лист1!$J:$J,AI39),"") | AA39: =IFERROR(INDEX([2]Лист1!$K:$K,AI39),"") | AB39: =IFERROR(INDEX([2]Лист1!$E:$E,AJ39),"") | AC39: =IFERROR(INDEX([2]Лист1!$I:$I,AJ39),"") | AD39: =IFERROR(INDEX([2]Лист1!$V:$V,AJ39),"") | AE39: =IFERROR(INDEX([2]Лист1!$L:$L,AJ39),"") | AF39: =IFERROR(INDEX([2]Лист1!$J:$J,AJ39),"") | AG39: =IFERROR(INDEX([2]Лист1!$K:$K,AJ39),"") | AH39: =MATCH(L39,[2]Лист1!$A:$A,0) -> 6376 | AI39: =MATCH(M39,[2]Лист1!$A:$A,0) -> #N/A | AJ39: =MATCH(N39,[2]Лист1!$A:$A,0) -> #N/A
A40: 1 | B40: ЛСР-03-05-602Э | C40: 3 | E40: 20.5.02.04-0002 | F40: Коробка ответвительная FK 9255_Коробка ответвительная огнестойкая | G40: ШТ | H40: 190 | I40: 2751.23 | J40: =H40*I40 -> 522733.7 | K40: =J40/SUM($J$2:$J$1590) -> 0.0040935346 | L40: =IFERROR(INDEX([1]мтр!G:G,MATCH($F40,[1]мтр!$C:$C,0)),"") -> 7608 | M40: =IFERROR(INDEX([1]мтр!H:H,MATCH($F40,[1]мтр!$C:$C,0)),"") -> 0 | N40: =IFERROR(INDEX([1]мтр!I:I,MATCH($F40,[1]мтр!$C:$C,0)),"") -> 0 | O40: =IFERROR(AVERAGE(R40,X40,AD40),"") -> 13070.668 | P40: =IFERROR(INDEX([2]Лист1!$E:$E,AH40),"") -> Коробка распределительная ОП 200х200х80мм IP66 с клемм. FK 9255 оранж. HENSEL 6000116, транспорт 5% | Q40: =IFERROR(INDEX([2]Лист1!$I:$I,AH40),"") -> шт | R40: =IFERROR(INDEX([2]Лист1!$V:$V,AH40),"") -> 13070.668 | S40: =IFERROR(INDEX([2]Лист1!$L:$L,AH40),"") -> 45013 | T40: =IFERROR(INDEX([2]Лист1!$J:$J,AH40),"") -> Hensel | U40: =IFERROR(INDEX([2]Лист1!$K:$K,AH40),"") -> https://rs24.ru/product/500635 | V40: =IFERROR(INDEX([2]Лист1!$E:$E,AI40),"") | W40: =IFERROR(INDEX([2]Лист1!$I:$I,AI40),"") | X40: =IFERROR(INDEX([2]Лист1!$V:$V,AI40),"") | Y40: =IFERROR(INDEX([2]Лист1!$L:$L,AI40),"") | Z40: =IFERROR(INDEX([2]Лист1!$J:$J,AI40),"") | AA40: =IFERROR(INDEX([2]Лист1!$K:$K,AI40),"") | AB40: =IFERROR(INDEX([2]Лист1!$E:$E,AJ40),"") | AC40: =IFERROR(INDEX([2]Лист1!$I:$I,AJ40),"") | AD40: =IFERROR(INDEX([2]Лист1!$V:$V,AJ40),"") | AE40: =IFERROR(INDEX([2]Лист1!$L:$L,AJ40),"") | AF40: =IFERROR(INDEX([2]Лист1!$J:$J,AJ40),"") | AG40: =IFERROR(INDEX([2]Лист1!$K:$K,AJ40),"") | AH40: =MATCH(L40,[2]Лист1!$A:$A,0) -> 6674 | AI40: =MATCH(M40,[2]Лист1!$A:$A,0) -> #N/A | AJ40: =MATCH(N40,[2]Лист1!$A:$A,0) -> #N/A
A41: 1 | B41: ЛСР-03-05-206ТМ | C41: 3 | E41: ТЦ_23.7.01.02_31_3123315768_20.05.2022_02/ КА п.75/ Энергомаш ООО "Белэнергомаш-БЗЭМ" №006-00073 | F41: Трубопроводы низкого давления из углеродистой стали, 4 класса безопасности, Ду < 80мм _ DN50, DN40, DN32, DN25, DN20, DN15, DN10 | G41: т | H41: 1.421 | I41: 364063.42 | J41: =H41*I41 -> 517334.12 | K41: =J41/SUM($J$2:$J$1590) -> 0.0040512504 | L41: =IFERROR(INDEX([1]мтр!G:G,MATCH($F41,[1]мтр!$C:$C,0)),"") -> 4859 | M41: =IFERROR(INDEX([1]мтр!H:H,MATCH($F41,[1]мтр!$C:$C,0)),"") -> 0 | N41: =IFERROR(INDEX([1]мтр!I:I,MATCH($F41,[1]мтр!$C:$C,0)),"") -> 0 | O41: =IFERROR(AVERAGE(R41,X41,AD41),"") -> 479788.26 | P41: =IFERROR(INDEX([2]Лист1!$E:$E,AH41),"") -> Трубопроводы низкого давления из углеродистой стали зданий UJA, UKD. Объём: 4526466 руб. / 2939,52 кг = 1540 RUB/кг. Транспорт 5800 USD (Договор ЕОС-закупки №629007, №7720/220816 от 07.09.2022, АСЭ_Рускон) /40DV контейнер 25 т, класс груза - 2, загрузка 85%. | Q41: =IFERROR(INDEX([2]Лист1!$I:$I,AH41),"") -> т | R41: =IFERROR(INDEX([2]Лист1!$V:$V,AH41),"") -> 479788.26 | S41: =IFERROR(INDEX([2]Лист1!$L:$L,AH41),"") -> 44753 | T41: =IFERROR(INDEX([2]Лист1!$J:$J,AH41),"") -> Белэнергомаш-БЗЭМ | U41: =IFERROR(INDEX([2]Лист1!$K:$K,AH41),"") -> Поставка трубопроводов по лоту 19677-248 Куд3;4. НМЦ от 11.07.2022, рассчитанная на основании п.1 раздела 3 главы 3 (приложения №8 к ЕОСЗ). | V41: =IFERROR(INDEX([2]Лист1!$E:$E,AI41),"") | W41: =IFERROR(INDEX([2]Лист1!$I:$I,AI41),"") | X41: =IFERROR(INDEX([2]Лист1!$V:$V,AI41),"") | Y41: =IFERROR(INDEX([2]Лист1!$L:$L,AI41),"") | Z41: =IFERROR(INDEX([2]Лист1!$J:$J,AI41),"") | AA41: =IFERROR(INDEX([2]Лист1!$K:$K,AI41),"") | AB41: =IFERROR(INDEX([2]Лист1!$E:$E,AJ41),"") | AC41: =IFERROR(INDEX([2]Лист1!$I:$I,AJ41),"") | AD41: =IFERROR(INDEX([2]Лист1!$V:$V,AJ41),"") | AE41: =IFERROR(INDEX([2]Лист1!$L:$L,AJ41),"") | AF41: =IFERROR(INDEX([2]Лист1!$J:$J,AJ41),"") | AG41: =IFERROR(INDEX([2]Лист1!$K:$K,AJ41),"") | AH41: =MATCH(L41,[2]Лист1!$A:$A,0) -> 4796 | AI41: =MATCH(M41,[2]Лист1!$A:$A,0) -> #N/A | AJ41: =MATCH(N41,[2]Лист1!$A:$A,0) -> #N/A
A42: 1 | B42: ЛСР-03-05-202ТМ | C42: 3 | E42: ТЦ_07.2.07.11_31_3123315768_20.05.2022_02 / КА п.5 / Энергомаш ООО "Белэнергомаш-БЗЭМ" № 006-00073 | F42: Опоры Lisega type 56_ОПС | G42: кг | H42: 591.6 | I42: 865.48 | J42: =H42*I42 -> 512017.97 | K42: =J42/SUM($J$2:$J$1590) -> 0.0040096196 | L42: =IFERROR(INDEX([1]мтр!G:G,MATCH($F42,[1]мтр!$C:$C,0)),"") -> 4863 | M42: =IFERROR(INDEX([1]мтр!H:H,MATCH($F42,[1]мтр!$C:$C,0)),"") -> 0 | N42: =IFERROR(INDEX([1]мтр!I:I,MATCH($F42,[1]мтр!$C:$C,0)),"") -> 0 | O42: =IFERROR(AVERAGE(R42,X42,AD42),"") -> 1828.8126 | P42: =IFERROR(INDEX([2]Лист1!$E:$E,AH42),"") -> Опорно подвесные системы Lisega. Транспорт 5800 USD (Договор ЕОС-закупки №629007, №7720/220816 от 07.09.2022, АСЭ_Рускон) /40DV контейнер 25 т, класс груза - 1, загрузка 100% | Q42: =IFERROR(INDEX([2]Лист1!$I:$I,AH42),"") -> кг | R42: =IFERROR(INDEX([2]Лист1!$V:$V,AH42),"") -> 1828.8126 | S42: =IFERROR(INDEX([2]Лист1!$L:$L,AH42),"") -> 44720 | T42: =IFERROR(INDEX([2]Лист1!$J:$J,AH42),"") -> Белэнергомаш-БЗЭМ | U42: =IFERROR(INDEX([2]Лист1!$K:$K,AH42),"") -> ТКП №006-00082 от 08.06.2022 в адрес АСЭ | V42: =IFERROR(INDEX([2]Лист1!$E:$E,AI42),"") | W42: =IFERROR(INDEX([2]Лист1!$I:$I,AI42),"") | X42: =IFERROR(INDEX([2]Лист1!$V:$V,AI42),"") | Y42: =IFERROR(INDEX([2]Лист1!$L:$L,AI42),"") | Z42: =IFERROR(INDEX([2]Лист1!$J:$J,AI42),"") | AA42: =IFERROR(INDEX([2]Лист1!$K:$K,AI42),"") | AB42: =IFERROR(INDEX([2]Лист1!$E:$E,AJ42),"") | AC42: =IFERROR(INDEX([2]Лист1!$I:$I,AJ42),"") | AD42: =IFERROR(INDEX([2]Лист1!$V:$V,AJ42),"") | AE42: =IFERROR(INDEX([2]Лист1!$L:$L,AJ42),"") | AF42: =IFERROR(INDEX([2]Лист1!$J:$J,AJ42),"") | AG42: =IFERROR(INDEX([2]Лист1!$K:$K,AJ42),"") | AH42: =MATCH(L42,[2]Лист1!$A:$A,0) -> 4800 | AI42: =MATCH(M42,[2]Лист1!$A:$A,0) -> #N/A | AJ42: =MATCH(N42,[2]Лист1!$A:$A,0) -> #N/A
A43: 1 | B43: ЛСР-03-05-501ОВ | C43: 3 | E43: 10.1.02.02-0134 | F43: Листы алюминиевые марок АД0, А5, плиты алюминиевые марок АД0, АД1, шириной 1200-1500 мм, длиной от 2000 до 5000 мм, толщиной: 0,8 мм | G43: т | H43: 9.181 | I43: 51906.55 | J43: =H43*I43 -> 476554.04 | K43: =J43/SUM($J$2:$J$1590) -> 0.0037319011 | L43: =IFERROR(INDEX([1]мтр!G:G,MATCH($F43,[1]мтр!$C:$C,0)),"") -> 6827 | M43: =IFERROR(INDEX([1]мтр!H:H,MATCH($F43,[1]мтр!$C:$C,0)),"") -> 0 | N43: =IFERROR(INDEX([1]мтр!I:I,MATCH($F43,[1]мтр!$C:$C,0)),"") -> 0 | O43: =IFERROR(AVERAGE(R43,X43,AD43),"") -> 120502.15 | P43: =IFERROR(INDEX([2]Лист1!$E:$E,AH43),"") -> Лист алюминиевый 0.8х1200х3000, марка АД1Н | Q43: =IFERROR(INDEX([2]Лист1!$I:$I,AH43),"") -> т | R43: =IFERROR(INDEX([2]Лист1!$V:$V,AH43),"") -> 120502.15 | S43: =IFERROR(INDEX([2]Лист1!$L:$L,AH43),"") -> 44946 | T43: =IFERROR(INDEX([2]Лист1!$J:$J,AH43),"") -> Металлсервис | U43: =IFERROR(INDEX([2]Лист1!$K:$K,AH43),"") -> https://mc.ru/region/krasnodar/metalloprokat/alyuminievyj_list/r1/0.8/mark/ad1n/filtr/cat | V43: =IFERROR(INDEX([2]Лист1!$E:$E,AI43),"") | W43: =IFERROR(INDEX([2]Лист1!$I:$I,AI43),"") | X43: =IFERROR(INDEX([2]Лист1!$V:$V,AI43),"") | Y43: =IFERROR(INDEX([2]Лист1!$L:$L,AI43),"") | Z43: =IFERROR(INDEX([2]Лист1!$J:$J,AI43),"") | AA43: =IFERROR(INDEX([2]Лист1!$K:$K,AI43),"") | AB43: =IFERROR(INDEX([2]Лист1!$E:$E,AJ43),"") | AC43: =IFERROR(INDEX([2]Лист1!$I:$I,AJ43),"") | AD43: =IFERROR(INDEX([2]Лист1!$V:$V,AJ43),"") | AE43: =IFERROR(INDEX([2]Лист1!$L:$L,AJ43),"") | AF43: =IFERROR(INDEX([2]Лист1!$J:$J,AJ43),"") | AG43: =IFERROR(INDEX([2]Лист1!$K:$K,AJ43),"") | AH43: =MATCH(L43,[2]Лист1!$A:$A,0) -> 5893 | AI43: =MATCH(M43,[2]Лист1!$A:$A,0) -> #N/A | AJ43: =MATCH(N43,[2]Лист1!$A:$A,0) -> #N/A
A44: 1 | B44: ЛСР-03-05-501ОВ | C44: 3 | E44: 10.1.02.02-0134 | F44: Листы алюминиевые марок АД0, А5, плиты алюминиевые марок АД0, АД1, шириной 1200-1500 мм, длиной от 2000 до 5000 мм, толщиной: 0,8 мм | G44: т | H44: 9.181 | I44: 51906.55 | J44: =H44*I44 -> 476554.04 | K44: =J44/SUM($J$2:$J$1590) -> 0.0037319011 | L44: =IFERROR(INDEX([1]мтр!G:G,MATCH($F44,[1]мтр!$C:$C,0)),"") -> 6827 | M44: =IFERROR(INDEX([1]мтр!H:H,MATCH($F44,[1]мтр!$C:$C,0)),"") -> 0 | N44: =IFERROR(INDEX([1]мтр!I:I,MATCH($F44,[1]мтр!$C:$C,0)),"") -> 0 | O44: =IFERROR(AVERAGE(R44,X44,AD44),"") -> 120502.15 | P44: =IFERROR(INDEX([2]Лист1!$E:$E,AH44),"") -> Лист алюминиевый 0.8х1200х3000, марка АД1Н | Q44: =IFERROR(INDEX([2]Лист1!$I:$I,AH44),"") -> т | R44: =IFERROR(INDEX([2]Лист1!$V:$V,AH44),"") -> 120502.15 | S44: =IFERROR(INDEX([2]Лист1!$L:$L,AH44),"") -> 44946 | T44: =IFERROR(INDEX([2]Лист1!$J:$J,AH44),"") -> Металлсервис | U44: =IFERROR(INDEX([2]Лист1!$K:$K,AH44),"") -> https://mc.ru/region/krasnodar/metalloprokat/alyuminievyj_list/r1/0.8/mark/ad1n/filtr/cat | V44: =IFERROR(INDEX([2]Лист1!$E:$E,AI44),"") | W44: =IFERROR(INDEX([2]Лист1!$I:$I,AI44),"") | X44: =IFERROR(INDEX([2]Лист1!$V:$V,AI44),"") | Y44: =IFERROR(INDEX([2]Лист1!$L:$L,AI44),"") | Z44: =IFERROR(INDEX([2]Лист1!$J:$J,AI44),"") | AA44: =IFERROR(INDEX([2]Лист1!$K:$K,AI44),"") | AB44: =IFERROR(INDEX([2]Лист1!$E:$E,AJ44),"") | AC44: =IFERROR(INDEX([2]Лист1!$I:$I,AJ44),"") | AD44: =IFERROR(INDEX([2]Лист1!$V:$V,AJ44),"") | AE44: =IFERROR(INDEX([2]Лист1!$L:$L,AJ44),"") | AF44: =IFERROR(INDEX([2]Лист1!$J:$J,AJ44),"") | AG44: =IFERROR(INDEX([2]Лист1!$K:$K,AJ44),"") | AH44: =MATCH(L44,[2]Лист1!$A:$A,0) -> 5893 | AI44: =MATCH(M44,[2]Лист1!$A:$A,0) -> #N/A | AJ44: =MATCH(N44,[2]Лист1!$A:$A,0) -> #N/A
A45: 3 | B45: ЛСР-03-06-201ТМ | C45: 3 | E45: ТЦ_18.1.06.04_76_7610060282_05.05.2022_02/ п.3/ ООО "Актан" №955 | F45: Затвор дисковый поворотный DN 150; Pmax=0.6MPag; Tmax=35 °С; Раб. среда: Обессоленная вода; Способ управления : Ручной привод; Тип присоединения : Фланцевый, нерж. сталь, класс без-сти 4Н_По типу А.КШ.Р.150.25.02.01 | G45: шт. | H45: 2 | I45: 229485.17 | J45: =H45*I45 -> 458970.34 | K45: =J45/SUM($J$2:$J$1590) -> 0.0035942029 | L45: =IFERROR(INDEX([1]мтр!G:G,MATCH($F45,[1]мтр!$C:$C,0)),"") | M45: =IFERROR(INDEX([1]мтр!H:H,MATCH($F45,[1]мтр!$C:$C,0)),"") | N45: =IFERROR(INDEX([1]мтр!I:I,MATCH($F45,[1]мтр!$C:$C,0)),"") | O45: =IFERROR(AVERAGE(R45,X45,AD45),"") | P45: =IFERROR(INDEX([2]Лист1!$E:$E,AH45),"") | Q45: =IFERROR(INDEX([2]Лист1!$I:$I,AH45),"") | R45: =IFERROR(INDEX([2]Лист1!$V:$V,AH45),"") | S45: =IFERROR(INDEX([2]Лист1!$L:$L,AH45),"") | T45: =IFERROR(INDEX([2]Лист1!$J:$J,AH45),"") | U45: =IFERROR(INDEX([2]Лист1!$K:$K,AH45),"") | V45: =IFERROR(INDEX([2]Лист1!$E:$E,AI45),"") | W45: =IFERROR(INDEX([2]Лист1!$I:$I,AI45),"") | X45: =IFERROR(INDEX([2]Лист1!$V:$V,AI45),"") | Y45: =IFERROR(INDEX([2]Лист1!$L:$L,AI45),"") | Z45: =IFERROR(INDEX([2]Лист1!$J:$J,AI45),"") | AA45: =IFERROR(INDEX([2]Лист1!$K:$K,AI45),"") | AB45: =IFERROR(INDEX([2]Лист1!$E:$E,AJ45),"") | AC45: =IFERROR(INDEX([2]Лист1!$I:$I,AJ45),"") | AD45: =IFERROR(INDEX([2]Лист1!$V:$V,AJ45),"") | AE45: =IFERROR(INDEX([2]Лист1!$L:$L,AJ45),"") | AF45: =IFERROR(INDEX([2]Лист1!$J:$J,AJ45),"") | AG45: =IFERROR(INDEX([2]Лист1!$K:$K,AJ45),"") | AH45: =MATCH(L45,[2]Лист1!$A:$A,0) -> #N/A | AI45: =MATCH(M45,[2]Лист1!$A:$A,0) -> #N/A | AJ45: =MATCH(N45,[2]Лист1!$A:$A,0) -> #N/A
A46: 1 | B46: ЛСР-03-05-203ТМ | C46: 3 | E46: ТЦ_18.1.06.00_50_5503095632_05.07.2022_02 /КА п.52/ ЗАО "Сибгазстройдеталь" №897 | F46: Запорная арматура По типу 1156-125-М DN 125; pmax=1.10 MPag; tmax=80 °С / °C; Раб. среда:Вода химически обессоленная; Способ управления: Ручной привод; Тип присоединения: Под приварку, л.4Н, угл.ст. | G46: шт. | H46: 2 | I46: 226407.66 | J46: =H46*I46 -> 452815.32 | K46: =J46/SUM($J$2:$J$1590) -> 0.0035460029 | L46: 7311 | M46: =IFERROR(INDEX([1]мтр!H:H,MATCH($F46,[1]мтр!$C:$C,0)),"") | N46: =IFERROR(INDEX([1]мтр!I:I,MATCH($F46,[1]мтр!$C:$C,0)),"") | O46: =IFERROR(AVERAGE(R46,X46,AD46),"") -> 0 | P46: =IFERROR(INDEX([2]Лист1!$E:$E,AH46),"") -> 0 | Q46: =IFERROR(INDEX([2]Лист1!$I:$I,AH46),"") -> 0 | R46: =IFERROR(INDEX([2]Лист1!$V:$V,AH46),"") -> 0 | S46: =IFERROR(INDEX([2]Лист1!$L:$L,AH46),"") -> 0 | T46: =IFERROR(INDEX([2]Лист1!$J:$J,AH46),"") -> 0 | U46: =IFERROR(INDEX([2]Лист1!$K:$K,AH46),"") -> 0 | V46: =IFERROR(INDEX([2]Лист1!$E:$E,AI46),"") | W46: =IFERROR(INDEX([2]Лист1!$I:$I,AI46),"") | X46: =IFERROR(INDEX([2]Лист1!$V:$V,AI46),"") | Y46: =IFERROR(INDEX([2]Лист1!$L:$L,AI46),"") | Z46: =IFERROR(INDEX([2]Лист1!$J:$J,AI46),"") | AA46: =IFERROR(INDEX([2]Лист1!$K:$K,AI46),"") | AB46: =IFERROR(INDEX([2]Лист1!$E:$E,AJ46),"") | AC46: =IFERROR(INDEX([2]Лист1!$I:$I,AJ46),"") | AD46: =IFERROR(INDEX([2]Лист1!$V:$V,AJ46),"") | AE46: =IFERROR(INDEX([2]Лист1!$L:$L,AJ46),"") | AF46: =IFERROR(INDEX([2]Лист1!$J:$J,AJ46),"") | AG46: =IFERROR(INDEX([2]Лист1!$K:$K,AJ46),"") | AH46: =MATCH(L46,[2]Лист1!$A:$A,0) -> 6377 | AI46: =MATCH(M46,[2]Лист1!$A:$A,0) -> #N/A | AJ46: =MATCH(N46,[2]Лист1!$A:$A,0) -> #N/A
A47: 1 | B47: ЛСР-03-05-203ТМ | C47: 3 | E47: ТЦ_18.1.06.00_50_5503095632_05.07.2022_02 /КА п.57/ ЗАО "Сибгазстройдеталь" №897 | F47: Запорная арматура По типу 1156-125-М DN 125; pmax=1.10 MPag; tmax=80 °С / °C; Раб. Среда:Вода химически обессоленная; Способ управления: Ручной привод; Тип присоединения: Под приварку Кл.4Н, угл.ст. | G47: шт. | H47: 2 | I47: 226407.66 | J47: =H47*I47 -> 452815.32 | K47: =J47/SUM($J$2:$J$1590) -> 0.0035460029 | L47: 7311 | M47: =IFERROR(INDEX([1]мтр!H:H,MATCH($F47,[1]мтр!$C:$C,0)),"") | N47: =IFERROR(INDEX([1]мтр!I:I,MATCH($F47,[1]мтр!$C:$C,0)),"") | O47: =IFERROR(AVERAGE(R47,X47,AD47),"") -> 0 | P47: =IFERROR(INDEX([2]Лист1!$E:$E,AH47),"") -> 0 | Q47: =IFERROR(INDEX([2]Лист1!$I:$I,AH47),"") -> 0 | R47: =IFERROR(INDEX([2]Лист1!$V:$V,AH47),"") -> 0 | S47: =IFERROR(INDEX([2]Лист1!$L:$L,AH47),"") -> 0 | T47: =IFERROR(INDEX([2]Лист1!$J:$J,AH47),"") -> 0 | U47: =IFERROR(INDEX([2]Лист1!$K:$K,AH47),"") -> 0 | V47: =IFERROR(INDEX([2]Лист1!$E:$E,AI47),"") | W47: =IFERROR(INDEX([2]Лист1!$I:$I,AI47),"") | X47: =IFERROR(INDEX([2]Лист1!$V:$V,AI47),"") | Y47: =IFERROR(INDEX([2]Лист1!$L:$L,AI47),"") | Z47: =IFERROR(INDEX([2]Лист1!$J:$J,AI47),"") | AA47: =IFERROR(INDEX([2]Лист1!$K:$K,AI47),"") | AB47: =IFERROR(INDEX([2]Лист1!$E:$E,AJ47),"") | AC47: =IFERROR(INDEX([2]Лист1!$I:$I,AJ47),"") | AD47: =IFERROR(INDEX([2]Лист1!$V:$V,AJ47),"") | AE47: =IFERROR(INDEX([2]Лист1!$L:$L,AJ47),"") | AF47: =IFERROR(INDEX([2]Лист1!$J:$J,AJ47),"") | AG47: =IFERROR(INDEX([2]Лист1!$K:$K,AJ47),"") | AH47: =MATCH(L47,[2]Лист1!$A:$A,0) -> 6377 | AI47: =MATCH(M47,[2]Лист1!$A:$A,0) -> #N/A | AJ47: =MATCH(N47,[2]Лист1!$A:$A,0) -> #N/A
A48: 1 | B48: ЛСР-03-05-203ТМ | C48: 3 | E48: ТЦ_18.1.06.00_50_5503095632_05.07.2022_02 /КА п.54/ ЗАО "Сибгазстройдеталь" №897 | F48: Запорная арматура По типу 1156-125-М DN 125; pmax=1.94 MPag; tmax=109 °С / °C; Раб. среда:Вода питательная ПРК; Способ управления: Ручной привод; Тип присоединения: Под приварку, Кл. 4Н, угл.ст. | G48: шт. | H48: 2 | I48: 226407.66 | J48: =H48*I48 -> 452815.32 | K48: =J48/SUM($J$2:$J$1590) -> 0.0035460029 | L48: 7313 | M48: =IFERROR(INDEX([1]мтр!H:H,MATCH($F48,[1]мтр!$C:$C,0)),"") | N48: =IFERROR(INDEX([1]мтр!I:I,MATCH($F48,[1]мтр!$C:$C,0)),"") | O48: =IFERROR(AVERAGE(R48,X48,AD48),"") -> 0 | P48: =IFERROR(INDEX([2]Лист1!$E:$E,AH48),"") -> 0 | Q48: =IFERROR(INDEX([2]Лист1!$I:$I,AH48),"") -> 0 | R48: =IFERROR(INDEX([2]Лист1!$V:$V,AH48),"") -> 0 | S48: =IFERROR(INDEX([2]Лист1!$L:$L,AH48),"") -> 0 | T48: =IFERROR(INDEX([2]Лист1!$J:$J,AH48),"") -> 0 | U48: =IFERROR(INDEX([2]Лист1!$K:$K,AH48),"") -> 0 | V48: =IFERROR(INDEX([2]Лист1!$E:$E,AI48),"") | W48: =IFERROR(INDEX([2]Лист1!$I:$I,AI48),"") | X48: =IFERROR(INDEX([2]Лист1!$V:$V,AI48),"") | Y48: =IFERROR(INDEX([2]Лист1!$L:$L,AI48),"") | Z48: =IFERROR(INDEX([2]Лист1!$J:$J,AI48),"") | AA48: =IFERROR(INDEX([2]Лист1!$K:$K,AI48),"") | AB48: =IFERROR(INDEX([2]Лист1!$E:$E,AJ48),"") | AC48: =IFERROR(INDEX([2]Лист1!$I:$I,AJ48),"") | AD48: =IFERROR(INDEX([2]Лист1!$V:$V,AJ48),"") | AE48: =IFERROR(INDEX([2]Лист1!$L:$L,AJ48),"") | AF48: =IFERROR(INDEX([2]Лист1!$J:$J,AJ48),"") | AG48: =IFERROR(INDEX([2]Лист1!$K:$K,AJ48),"") | AH48: =MATCH(L48,[2]Лист1!$A:$A,0) -> 6379 | AI48: =MATCH(M48,[2]Лист1!$A:$A,0) -> #N/A | AJ48: =MATCH(N48,[2]Лист1!$A:$A,0) -> #N/A
A49: 3 | B49: ЛСР-03-06-101С | C49: 3 | E49: 04.1.02.05-0014 | F49: Смеси бетонные тяжелого бетона (БСТ), класс В45 (М600)_Бетон B45 W8 | G49: м3 | H49: 128.52 | I49: 3406.74 | J49: =H49*I49 -> 437834.22 | K49: =J49/SUM($J$2:$J$1590) -> 0.0034286857 | L49: =IFERROR(INDEX([1]мтр!G:G,MATCH($F49,[1]мтр!$C:$C,0)),"") -> 5710 | M49: =IFERROR(INDEX([1]мтр!H:H,MATCH($F49,[1]мтр!$C:$C,0)),"") -> 0 | N49: =IFERROR(INDEX([1]мтр!I:I,MATCH($F49,[1]мтр!$C:$C,0)),"") -> 0 | O49: =IFERROR(AVERAGE(R49,X49,AD49),"") -> 2207.07 | P49: =IFERROR(INDEX([2]Лист1!$E:$E,AH49),"") -> Бетон тяжелый на сульфатостойком портландцементе, класс В45 П5 W8 SRC XS3, XA3 | Q49: =IFERROR(INDEX([2]Лист1!$I:$I,AH49),"") -> м3 | R49: =IFERROR(INDEX([2]Лист1!$V:$V,AH49),"") -> 2207.07 | S49: =IFERROR(INDEX([2]Лист1!$L:$L,AH49),"") -> 44872 | T49: =IFERROR(INDEX([2]Лист1!$J:$J,AH49),"") -> N/A | U49: =IFERROR(INDEX([2]Лист1!$K:$K,AH49),"") -> Справочник сметных цен на строильные материалы, изделия и конструкции для строительства АЭС Эль-Дабаа, Арабская республика Египет. II квартал 2022 года, ГК Росатом №05-0070 | V49: =IFERROR(INDEX([2]Лист1!$E:$E,AI49),"") | W49: =IFERROR(INDEX([2]Лист1!$I:$I,AI49),"") | X49: =IFERROR(INDEX([2]Лист1!$V:$V,AI49),"") | Y49: =IFERROR(INDEX([2]Лист1!$L:$L,AI49),"") | Z49: =IFERROR(INDEX([2]Лист1!$J:$J,AI49),"") | AA49: =IFERROR(INDEX([2]Лист1!$K:$K,AI49),"") | AB49: =IFERROR(INDEX([2]Лист1!$E:$E,AJ49),"") | AC49: =IFERROR(INDEX([2]Лист1!$I:$I,AJ49),"") | AD49: =IFERROR(INDEX([2]Лист1!$V:$V,AJ49),"") | AE49: =IFERROR(INDEX([2]Лист1!$L:$L,AJ49),"") | AF49: =IFERROR(INDEX([2]Лист1!$J:$J,AJ49),"") | AG49: =IFERROR(INDEX([2]Лист1!$K:$K,AJ49),"") | AH49: =MATCH(L49,[2]Лист1!$A:$A,0) -> 463 | AI49: =MATCH(M49,[2]Лист1!$A:$A,0) -> #N/A | AJ49: =MATCH(N49,[2]Лист1!$A:$A,0) -> #N/A
A50: 1 | B50: ЛСР-03-05-203ТМ | C50: 3 | E50: ТЦ_18.1.06.00_50_5503095632_05.07.2022_02 /КА п.56/ ЗАО "Сибгазстройдеталь" №897 | F50: Запорная арматура По типу 1052-65-0 DN 65; pmax=1.94 MPag; tmax=130 °С / °C; Раб. среда:Вода питательная ПРК; Способ управления: Ручной привод; Тип присоединения: Под приварку Кл.4Н, угл.ст. | G50: шт. | H50: 16 | I50: 24393.04 | J50: =H50*I50 -> 390288.64 | K50: =J50/SUM($J$2:$J$1590) -> 0.0030563556 | L50: 7318 | M50: =IFERROR(INDEX([1]мтр!H:H,MATCH($F50,[1]мтр!$C:$C,0)),"") | N50: =IFERROR(INDEX([1]мтр!I:I,MATCH($F50,[1]мтр!$C:$C,0)),"") | O50: =IFERROR(AVERAGE(R50,X50,AD50),"") -> 0 | P50: =IFERROR(INDEX([2]Лист1!$E:$E,AH50),"") -> 0 | Q50: =IFERROR(INDEX([2]Лист1!$I:$I,AH50),"") -> 0 | R50: =IFERROR(INDEX([2]Лист1!$V:$V,AH50),"") -> 0 | S50: =IFERROR(INDEX([2]Лист1!$L:$L,AH50),"") -> 0 | T50: =IFERROR(INDEX([2]Лист1!$J:$J,AH50),"") -> 0 | U50: =IFERROR(INDEX([2]Лист1!$K:$K,AH50),"") -> 0 | V50: =IFERROR(INDEX([2]Лист1!$E:$E,AI50),"") | W50: =IFERROR(INDEX([2]Лист1!$I:$I,AI50),"") | X50: =IFERROR(INDEX([2]Лист1!$V:$V,AI50),"") | Y50: =IFERROR(INDEX([2]Лист1!$L:$L,AI50),"") | Z50: =IFERROR(INDEX([2]Лист1!$J:$J,AI50),"") | AA50: =IFERROR(INDEX([2]Лист1!$K:$K,AI50),"") | AB50: =IFERROR(INDEX([2]Лист1!$E:$E,AJ50),"") | AC50: =IFERROR(INDEX([2]Лист1!$I:$I,AJ50),"") | AD50: =IFERROR(INDEX([2]Лист1!$V:$V,AJ50),"") | AE50: =IFERROR(INDEX([2]Лист1!$L:$L,AJ50),"") | AF50: =IFERROR(INDEX([2]Лист1!$J:$J,AJ50),"") | AG50: =IFERROR(INDEX([2]Лист1!$K:$K,AJ50),"") | AH50: =MATCH(L50,[2]Лист1!$A:$A,0) -> 6384 | AI50: =MATCH(M50,[2]Лист1!$A:$A,0) -> #N/A | AJ50: =MATCH(N50,[2]Лист1!$A:$A,0) -> #N/A
A51: 1 | B51: ЛСР-03-05-701АК | C51: 3 | E51: ТЦ_20.2.03.02_50_7710050305_31.05.2022_02 | F51: Опорная конструкция T MQK-600. Hilti 4; III; QA2 | G51: шт. | H51: 272 | I51: 1422.48 | J51: =H51*I51 -> 386914.56 | K51: =J51/SUM($J$2:$J$1590) -> 0.0030299331 | L51: =IFERROR(INDEX([1]мтр!G:G,MATCH($F51,[1]мтр!$C:$C,0)),"") -> 7609 | M51: =IFERROR(INDEX([1]мтр!H:H,MATCH($F51,[1]мтр!$C:$C,0)),"") -> 0 | N51: =IFERROR(INDEX([1]мтр!I:I,MATCH($F51,[1]мтр!$C:$C,0)),"") -> 0 | O51: =IFERROR(AVERAGE(R51,X51,AD51),"") -> 2697.7432 | P51: =IFERROR(INDEX([2]Лист1!$E:$E,AH51),"") -> Опорная конструкция T MQK-600 в составе:- консольная опора MQK-72/600 #369616, 1 шт;- анкер для тяжелых нагрузок HSL4-G M8 d12x92 5/-/- #2237458, 2 шт. Транспорт экспертно 5% | Q51: =IFERROR(INDEX([2]Лист1!$I:$I,AH51),"") -> шт. | R51: =IFERROR(INDEX([2]Лист1!$V:$V,AH51),"") -> 2697.7432 | S51: =IFERROR(INDEX([2]Лист1!$L:$L,AH51),"") -> 45013 | T51: =IFERROR(INDEX([2]Лист1!$J:$J,AH51),"") -> Hilti Italy | U51: =IFERROR(INDEX([2]Лист1!$K:$K,AH51),"") -> https://www.hilti.it/c/CLS_INSTALLATION_SYS_7134/CLS_SPRINKLER_7134/CLS_SPRINKLER_COMPONENTS_7134/r4345https://www.hilti.it/?CHA_GLOBAL_ANC_SIZE=M8&CHD_ANCHOR_LENGTH=102%20mm&combo_content=51979bb59b0ce01b4fe329858c7e0028&salespackquantity=40%20pezzi&itemCode=371793 | V51: =IFERROR(INDEX([2]Лист1!$E:$E,AI51),"") | W51: =IFERROR(INDEX([2]Лист1!$I:$I,AI51),"") | X51: =IFERROR(INDEX([2]Лист1!$V:$V,AI51),"") | Y51: =IFERROR(INDEX([2]Лист1!$L:$L,AI51),"") | Z51: =IFERROR(INDEX([2]Лист1!$J:$J,AI51),"") | AA51: =IFERROR(INDEX([2]Лист1!$K:$K,AI51),"") | AB51: =IFERROR(INDEX([2]Лист1!$E:$E,AJ51),"") | AC51: =IFERROR(INDEX([2]Лист1!$I:$I,AJ51),"") | AD51: =IFERROR(INDEX([2]Лист1!$V:$V,AJ51),"") | AE51: =IFERROR(INDEX([2]Лист1!$L:$L,AJ51),"") | AF51: =IFERROR(INDEX([2]Лист1!$J:$J,AJ51),"") | AG51: =IFERROR(INDEX([2]Лист1!$K:$K,AJ51),"") | AH51: =MATCH(L51,[2]Лист1!$A:$A,0) -> 6675 | AI51: =MATCH(M51,[2]Лист1!$A:$A,0) -> #N/A | AJ51: =MATCH(N51,[2]Лист1!$A:$A,0) -> #N/A
A52: 1 | B52: ЛСР-03-05-203ТМ | C52: 3 | E52: ТЦ_18.1.06.00_50_5503095632_05.07.2022_02 /КА п.40/ ЗАО "Сибгазстройдеталь" №897 | F52: Запорная арматура По типу 2с-32-2 DN 100; pmax=0.12 MPag; tmax=109 °С / °C; Раб. Среда:Вода питательная ПРК; Способ управления: Ручной привод; Тип присоединения: Под приварку ,Кл. 4Н, угл.ст. | G52: шт. | H52: 5 | I52: 76856.84 | J52: =H52*I52 -> 384284.2 | K52: =J52/SUM($J$2:$J$1590) -> 0.0030093347 | L52: 7320 | M52: =IFERROR(INDEX([1]мтр!H:H,MATCH($F52,[1]мтр!$C:$C,0)),"") | N52: =IFERROR(INDEX([1]мтр!I:I,MATCH($F52,[1]мтр!$C:$C,0)),"") | O52: =IFERROR(AVERAGE(R52,X52,AD52),"") -> 0 | P52: =IFERROR(INDEX([2]Лист1!$E:$E,AH52),"") -> 0 | Q52: =IFERROR(INDEX([2]Лист1!$I:$I,AH52),"") -> 0 | R52: =IFERROR(INDEX([2]Лист1!$V:$V,AH52),"") -> 0 | S52: =IFERROR(INDEX([2]Лист1!$L:$L,AH52),"") -> 0 | T52: =IFERROR(INDEX([2]Лист1!$J:$J,AH52),"") -> 0 | U52: =IFERROR(INDEX([2]Лист1!$K:$K,AH52),"") -> 0 | V52: =IFERROR(INDEX([2]Лист1!$E:$E,AI52),"") | W52: =IFERROR(INDEX([2]Лист1!$I:$I,AI52),"") | X52: =IFERROR(INDEX([2]Лист1!$V:$V,AI52),"") | Y52: =IFERROR(INDEX([2]Лист1!$L:$L,AI52),"") | Z52: =IFERROR(INDEX([2]Лист1!$J:$J,AI52),"") | AA52: =IFERROR(INDEX([2]Лист1!$K:$K,AI52),"") | AB52: =IFERROR(INDEX([2]Лист1!$E:$E,AJ52),"") | AC52: =IFERROR(INDEX([2]Лист1!$I:$I,AJ52),"") | AD52: =IFERROR(INDEX([2]Лист1!$V:$V,AJ52),"") | AE52: =IFERROR(INDEX([2]Лист1!$L:$L,AJ52),"") | AF52: =IFERROR(INDEX([2]Лист1!$J:$J,AJ52),"") | AG52: =IFERROR(INDEX([2]Лист1!$K:$K,AJ52),"") | AH52: =MATCH(L52,[2]Лист1!$A:$A,0) -> 6386 | AI52: =MATCH(M52,[2]Лист1!$A:$A,0) -> #N/A | AJ52: =MATCH(N52,[2]Лист1!$A:$A,0) -> #N/A
A53: 1 | B53: ЛСР-03-05-203ТМ | C53: 3 | E53: ТЦ_18.1.06.00_50_5503095632_05.07.2022_02 /КА п.30/ ЗАО "Сибгазстройдеталь" №897 | F53: Запорная арматура По типу 2с-32-1 DN 80; pmax=0.88 MPag; tmax=178 °С / °C; Раб. среда: Вода продувочная ПРК; Способ управления: Ручной привод; Тип присоединения: Под приварку; Кл 4Н, угл.ст. | G53: шт. | H53: 5 | I53: 74145.24 | J53: =H53*I53 -> 370726.2 | K53: =J53/SUM($J$2:$J$1590) -> 0.0029031619 | L53: 7319 | M53: =IFERROR(INDEX([1]мтр!H:H,MATCH($F53,[1]мтр!$C:$C,0)),"") | N53: =IFERROR(INDEX([1]мтр!I:I,MATCH($F53,[1]мтр!$C:$C,0)),"") | O53: =IFERROR(AVERAGE(R53,X53,AD53),"") -> 0 | P53: =IFERROR(INDEX([2]Лист1!$E:$E,AH53),"") -> 0 | Q53: =IFERROR(INDEX([2]Лист1!$I:$I,AH53),"") -> 0 | R53: =IFERROR(INDEX([2]Лист1!$V:$V,AH53),"") -> 0 | S53: =IFERROR(INDEX([2]Лист1!$L:$L,AH53),"") -> 0 | T53: =IFERROR(INDEX([2]Лист1!$J:$J,AH53),"") -> 0 | U53: =IFERROR(INDEX([2]Лист1!$K:$K,AH53),"") -> 0 | V53: =IFERROR(INDEX([2]Лист1!$E:$E,AI53),"") | W53: =IFERROR(INDEX([2]Лист1!$I:$I,AI53),"") | X53: =IFERROR(INDEX([2]Лист1!$V:$V,AI53),"") | Y53: =IFERROR(INDEX([2]Лист1!$L:$L,AI53),"") | Z53: =IFERROR(INDEX([2]Лист1!$J:$J,AI53),"") | AA53: =IFERROR(INDEX([2]Лист1!$K:$K,AI53),"") | AB53: =IFERROR(INDEX([2]Лист1!$E:$E,AJ53),"") | AC53: =IFERROR(INDEX([2]Лист1!$I:$I,AJ53),"") | AD53: =IFERROR(INDEX([2]Лист1!$V:$V,AJ53),"") | AE53: =IFERROR(INDEX([2]Лист1!$L:$L,AJ53),"") | AF53: =IFERROR(INDEX([2]Лист1!$J:$J,AJ53),"") | AG53: =IFERROR(INDEX([2]Лист1!$K:$K,AJ53),"") | AH53: =MATCH(L53,[2]Лист1!$A:$A,0) -> 6385 | AI53: =MATCH(M53,[2]Лист1!$A:$A,0) -> #N/A | AJ53: =MATCH(N53,[2]Лист1!$A:$A,0) -> #N/A
A54: 1 | B54: ЛСР-03-05-602Э | C54: 3 | E54: 20.3.03.07-0111 | F54: Светильник промышленный GM: C100-42-96-CG-65-L00-T (1 модуль)_Светильник светодиодный накладной IP65, 230 В, 50 Гц, 26-50 Вт_Светильник светодиодный накладной | G54: ШТ | H54: 155 | I54: 2347.02 | J54: =H54*I54 -> 363788.1 | K54: =J54/SUM($J$2:$J$1590) -> 0.0028488295 | L54: 7332 | M54: =IFERROR(INDEX([1]мтр!H:H,MATCH($F54,[1]мтр!$C:$C,0)),"") | N54: =IFERROR(INDEX([1]мтр!I:I,MATCH($F54,[1]мтр!$C:$C,0)),"") | O54: =IFERROR(AVERAGE(R54,X54,AD54),"") -> 0 | P54: =IFERROR(INDEX([2]Лист1!$E:$E,AH54),"") -> 0 | Q54: =IFERROR(INDEX([2]Лист1!$I:$I,AH54),"") -> 0 | R54: =IFERROR(INDEX([2]Лист1!$V:$V,AH54),"") -> 0 | S54: =IFERROR(INDEX([2]Лист1!$L:$L,AH54),"") -> 0 | T54: =IFERROR(INDEX([2]Лист1!$J:$J,AH54),"") -> 0 | U54: =IFERROR(INDEX([2]Лист1!$K:$K,AH54),"") -> 0 | V54: =IFERROR(INDEX([2]Лист1!$E:$E,AI54),"") | W54: =IFERROR(INDEX([2]Лист1!$I:$I,AI54),"") | X54: =IFERROR(INDEX([2]Лист1!$V:$V,AI54),"") | Y54: =IFERROR(INDEX([2]Лист1!$L:$L,AI54),"") | Z54: =IFERROR(INDEX([2]Лист1!$J:$J,AI54),"") | AA54: =IFERROR(INDEX([2]Лист1!$K:$K,AI54),"") | AB54: =IFERROR(INDEX([2]Лист1!$E:$E,AJ54),"") | AC54: =IFERROR(INDEX([2]Лист1!$I:$I,AJ54),"") | AD54: =IFERROR(INDEX([2]Лист1!$V:$V,AJ54),"") | AE54: =IFERROR(INDEX([2]Лист1!$L:$L,AJ54),"") | AF54: =IFERROR(INDEX([2]Лист1!$J:$J,AJ54),"") | AG54: =IFERROR(INDEX([2]Лист1!$K:$K,AJ54),"") | AH54: =MATCH(L54,[2]Лист1!$A:$A,0) -> 6398 | AI54: =MATCH(M54,[2]Лист1!$A:$A,0) -> #N/A | AJ54: =MATCH(N54,[2]Лист1!$A:$A,0) -> #N/A
A55: 1 | B55: ЛСР-03-05-203ТМ | C55: 3 | E55: ТЦ_18.1.04.00_50_5503095632_05.07.2022_02 /КА п.28/ ЗАО "Сибгазстройдеталь" №897 | F55: Обратный клапан По типу 4с-3-4 DN 200; pmax=1.3 MPag; tmax=195 °С / °C; Раб. среда: Пар насыщенный; Способ управления: Направлением потока; Тип присоединения: Под приварку; Кл 4Н, угл.ст. | G55: шт. | H55: 4 | I55: 90599.14 | J55: =H55*I55 -> 362396.56 | K55: =J55/SUM($J$2:$J$1590) -> 0.0028379323 | L55: =IFERROR(INDEX([1]мтр!G:G,MATCH($F55,[1]мтр!$C:$C,0)),"") | M55: =IFERROR(INDEX([1]мтр!H:H,MATCH($F55,[1]мтр!$C:$C,0)),"") | N55: =IFERROR(INDEX([1]мтр!I:I,MATCH($F55,[1]мтр!$C:$C,0)),"") | O55: =IFERROR(AVERAGE(R55,X55,AD55),"") | P55: =IFERROR(INDEX([2]Лист1!$E:$E,AH55),"") | Q55: =IFERROR(INDEX([2]Лист1!$I:$I,AH55),"") | R55: =IFERROR(INDEX([2]Лист1!$V:$V,AH55),"") | S55: =IFERROR(INDEX([2]Лист1!$L:$L,AH55),"") | T55: =IFERROR(INDEX([2]Лист1!$J:$J,AH55),"") | U55: =IFERROR(INDEX([2]Лист1!$K:$K,AH55),"") | V55: =IFERROR(INDEX([2]Лист1!$E:$E,AI55),"") | W55: =IFERROR(INDEX([2]Лист1!$I:$I,AI55),"") | X55: =IFERROR(INDEX([2]Лист1!$V:$V,AI55),"") | Y55: =IFERROR(INDEX([2]Лист1!$L:$L,AI55),"") | Z55: =IFERROR(INDEX([2]Лист1!$J:$J,AI55),"") | AA55: =IFERROR(INDEX([2]Лист1!$K:$K,AI55),"") | AB55: =IFERROR(INDEX([2]Лист1!$E:$E,AJ55),"") | AC55: =IFERROR(INDEX([2]Лист1!$I:$I,AJ55),"") | AD55: =IFERROR(INDEX([2]Лист1!$V:$V,AJ55),"") | AE55: =IFERROR(INDEX([2]Лист1!$L:$L,AJ55),"") | AF55: =IFERROR(INDEX([2]Лист1!$J:$J,AJ55),"") | AG55: =IFERROR(INDEX([2]Лист1!$K:$K,AJ55),"") | AH55: =MATCH(L55,[2]Лист1!$A:$A,0) -> #N/A | AI55: =MATCH(M55,[2]Лист1!$A:$A,0) -> #N/A | AJ55: =MATCH(N55,[2]Лист1!$A:$A,0) -> #N/A
A56: 1 | B56: ЛСР-03-05-206ТМ | C56: 3 | E56: ТЦ_23.7.01.02_31_3123315768_20.05.2022_02/КА п.78// ООО "Белэнергомаш-БЗЭМ" №006-00073 | F56: Трубопроводы низкого давления из нержавеющей стали, 4 класса безопасности, Ду >80мм_DN150, DN125, DN100. | G56: т | H56: 0.402 | I56: 799960.85 | J56: =H56*I56 -> 321584.26 | K56: =J56/SUM($J$2:$J$1590) -> 0.0025183307 | L56: =IFERROR(INDEX([1]мтр!G:G,MATCH($F56,[1]мтр!$C:$C,0)),"") -> 4861 | M56: =IFERROR(INDEX([1]мтр!H:H,MATCH($F56,[1]мтр!$C:$C,0)),"") -> 0 | N56: =IFERROR(INDEX([1]мтр!I:I,MATCH($F56,[1]мтр!$C:$C,0)),"") -> 0 | O56: =IFERROR(AVERAGE(R56,X56,AD56),"") -> 2050605.2 | P56: =IFERROR(INDEX([2]Лист1!$E:$E,AH56),"") -> Трубопроводы низкого давления из нержавеющей стали зданий UJA, UKD. Объём: 40 315 616 руб. / 6 074,16 кг = 6637 RUB/кг. Транспорт 5800 USD (Договор ЕОС-закупки №629007, №7720/220816 от 07.09.2022, АСЭ_Рускон) /40DV контейнер 25 т, класс груза - 2, загрузка 85%. | Q56: =IFERROR(INDEX([2]Лист1!$I:$I,AH56),"") -> т | R56: =IFERROR(INDEX([2]Лист1!$V:$V,AH56),"") -> 2050605.2 | S56: =IFERROR(INDEX([2]Лист1!$L:$L,AH56),"") -> 44753 | T56: =IFERROR(INDEX([2]Лист1!$J:$J,AH56),"") -> Белэнергомаш-БЗЭМ | U56: =IFERROR(INDEX([2]Лист1!$K:$K,AH56),"") -> Поставка трубопроводов по лоту 19677-248 Куд3;4. НМЦ от 11.07.2022, рассчитанная на основании п.1 раздела 3 главы 3 (приложения №8 к ЕОСЗ). | V56: =IFERROR(INDEX([2]Лист1!$E:$E,AI56),"") | W56: =IFERROR(INDEX([2]Лист1!$I:$I,AI56),"") | X56: =IFERROR(INDEX([2]Лист1!$V:$V,AI56),"") | Y56: =IFERROR(INDEX([2]Лист1!$L:$L,AI56),"") | Z56: =IFERROR(INDEX([2]Лист1!$J:$J,AI56),"") | AA56: =IFERROR(INDEX([2]Лист1!$K:$K,AI56),"") | AB56: =IFERROR(INDEX([2]Лист1!$E:$E,AJ56),"") | AC56: =IFERROR(INDEX([2]Лист1!$I:$I,AJ56),"") | AD56: =IFERROR(INDEX([2]Лист1!$V:$V,AJ56),"") | AE56: =IFERROR(INDEX([2]Лист1!$L:$L,AJ56),"") | AF56: =IFERROR(INDEX([2]Лист1!$J:$J,AJ56),"") | AG56: =IFERROR(INDEX([2]Лист1!$K:$K,AJ56),"") | AH56: =MATCH(L56,[2]Лист1!$A:$A,0) -> 4798 | AI56: =MATCH(M56,[2]Лист1!$A:$A,0) -> #N/A | AJ56: =MATCH(N56,[2]Лист1!$A:$A,0) -> #N/A
A57: 1 | B57: ЛСР-03-05-206ТМ | C57: 3 | E57: ТЦ_12.2.04.12_32_3234045370_11.03.2022_02/ КА п.83/ ООО "Брянский завод теплоизоляционных материалов" №444 | F57: Маты базальтовые прошивные энергетические марки 50 в обкладке из стеклоткани Т-23 со всех сторон (МБПЭ 3-50 Т-23). (толщина 100мм)_МПБ-50-СТ6 2000*1000*100 | G57: м3 | H57: 261.576 | I57: 1207.07 | J57: =H57*I57 -> 315740.54 | K57: =J57/SUM($J$2:$J$1590) -> 0.0024725684 | L57: =IFERROR(INDEX([1]мтр!G:G,MATCH($F57,[1]мтр!$C:$C,0)),"") -> 5187 | M57: =IFERROR(INDEX([1]мтр!H:H,MATCH($F57,[1]мтр!$C:$C,0)),"") -> 0 | N57: =IFERROR(INDEX([1]мтр!I:I,MATCH($F57,[1]мтр!$C:$C,0)),"") -> 0 | O57: =IFERROR(AVERAGE(R57,X57,AD57),"") -> 4403.9852 | P57: =IFERROR(INDEX([2]Лист1!$E:$E,AH57),"") -> Мат прошивной МПБ-50/СТ6 1500х500х50мм ТУ 23.99.19-002-02500345-2003. Транспорт экспертно 5% | Q57: =IFERROR(INDEX([2]Лист1!$I:$I,AH57),"") -> м3 | R57: =IFERROR(INDEX([2]Лист1!$V:$V,AH57),"") -> 4403.9852 | S57: =IFERROR(INDEX([2]Лист1!$L:$L,AH57),"") -> 44707 | T57: =IFERROR(INDEX([2]Лист1!$J:$J,AH57),"") -> ООО "Техэнергомаш" | U57: =IFERROR(INDEX([2]Лист1!$K:$K,AH57),"") -> ЕОС "Закупки" 866429 ТКП 0590 от 26.05.2022 | V57: =IFERROR(INDEX([2]Лист1!$E:$E,AI57),"") | W57: =IFERROR(INDEX([2]Лист1!$I:$I,AI57),"") | X57: =IFERROR(INDEX([2]Лист1!$V:$V,AI57),"") | Y57: =IFERROR(INDEX([2]Лист1!$L:$L,AI57),"") | Z57: =IFERROR(INDEX([2]Лист1!$J:$J,AI57),"") | AA57: =IFERROR(INDEX([2]Лист1!$K:$K,AI57),"") | AB57: =IFERROR(INDEX([2]Лист1!$E:$E,AJ57),"") | AC57: =IFERROR(INDEX([2]Лист1!$I:$I,AJ57),"") | AD57: =IFERROR(INDEX([2]Лист1!$V:$V,AJ57),"") | AE57: =IFERROR(INDEX([2]Лист1!$L:$L,AJ57),"") | AF57: =IFERROR(INDEX([2]Лист1!$J:$J,AJ57),"") | AG57: =IFERROR(INDEX([2]Лист1!$K:$K,AJ57),"") | AH57: =MATCH(L57,[2]Лист1!$A:$A,0) -> 4862 | AI57: =MATCH(M57,[2]Лист1!$A:$A,0) -> #N/A | AJ57: =MATCH(N57,[2]Лист1!$A:$A,0) -> #N/A
A58: 1 | B58: ЛСР-03-05-206ТМ | C58: 3 | E58: 10.1.02.02-0101 | F58: Листы алюминиевые, марка АД1Н, толщина 0,5 мм | G58: кг | H58: 5028.84 | I58: 60.23 | J58: =H58*I58 -> 302887.03 | K58: =J58/SUM($J$2:$J$1590) -> 0.0023719124 | L58: =IFERROR(INDEX([1]мтр!G:G,MATCH($F58,[1]мтр!$C:$C,0)),"") -> 5054 | M58: =IFERROR(INDEX([1]мтр!H:H,MATCH($F58,[1]мтр!$C:$C,0)),"") -> 0 | N58: =IFERROR(INDEX([1]мтр!I:I,MATCH($F58,[1]мтр!$C:$C,0)),"") -> 0 | O58: =IFERROR(AVERAGE(R58,X58,AD58),"") -> 78.330769 | P58: =IFERROR(INDEX([2]Лист1!$E:$E,AH58),"") -> Листы алюминиевые, марка АД1 Н, толщина 0,5 ммТранспорт контейнер 40 DC / 25 т:1) автомобильный Москва - Новорос.: 1150 км х 70руб/км;2) таможенное оформление РФ: 34 830 руб;3) портовая обработка и фрахт до Александрии: 273 800 руб;4) портовая обработка и таможенное оформление в Александрии: 1250 EGP;5) автомобильный Александрия - площадка: 6200 EGPИст. 1-3: согл НМЦ РосСЭМ от 17.01.2022, 4-5: инф Филиал.Класс груза - 2, загрузка = 85% НДС РФ, налоги пошлины АРЕ = 0%. | Q58: =IFERROR(INDEX([2]Лист1!$I:$I,AH58),"") -> кг | R58: =IFERROR(INDEX([2]Лист1!$V:$V,AH58),"") -> 78.330769 | S58: =IFERROR(INDEX([2]Лист1!$L:$L,AH58),"") -> 44587 | T58: =IFERROR(INDEX([2]Лист1!$J:$J,AH58),"") -> Металлсервис | U58: =IFERROR(INDEX([2]Лист1!$K:$K,AH58),"") -> https://mc.ru/metalloprokat/alyuminievyj_list/mark/ad1n | V58: =IFERROR(INDEX([2]Лист1!$E:$E,AI58),"") | W58: =IFERROR(INDEX([2]Лист1!$I:$I,AI58),"") | X58: =IFERROR(INDEX([2]Лист1!$V:$V,AI58),"") | Y58: =IFERROR(INDEX([2]Лист1!$L:$L,AI58),"") | Z58: =IFERROR(INDEX([2]Лист1!$J:$J,AI58),"") | AA58: =IFERROR(INDEX([2]Лист1!$K:$K,AI58),"") | AB58: =IFERROR(INDEX([2]Лист1!$E:$E,AJ58),"") | AC58: =IFERROR(INDEX([2]Лист1!$I:$I,AJ58),"") | AD58: =IFERROR(INDEX([2]Лист1!$V:$V,AJ58),"") | AE58: =IFERROR(INDEX([2]Лист1!$L:$L,AJ58),"") | AF58: =IFERROR(INDEX([2]Лист1!$J:$J,AJ58),"") | AG58: =IFERROR(INDEX([2]Лист1!$K:$K,AJ58),"") | AH58: =MATCH(L58,[2]Лист1!$A:$A,0) -> 2947 | AI58: =MATCH(M58,[2]Лист1!$A:$A,0) -> #N/A | AJ58: =MATCH(N58,[2]Лист1!$A:$A,0) -> #N/A
A59: 1 | B59: ЛСР-03-05-203ТМ | C59: 3 | E59: ТЦ_18.1.05.00_50_5503095632_05.07.2022_02 /КА п.38/ ЗАО "Сибгазстройдеталь" №897 | F59: Арматура предохранительная По типу КПП 096-03 pmax=2.5 MPag; tmax=203 °С / °C; Раб. среда:Вода питательная ПРК; Способ управления: Привод пружинный; Тип присоединения: Фланцевый DN вход = 65; DN выход : 65 Кл. 4Н, угл.ст. | G59: шт. | H59: 4 | I59: 72159.06 | J59: =H59*I59 -> 288636.24 | K59: =J59/SUM($J$2:$J$1590) -> 0.0022603143 | L59: =IFERROR(INDEX([1]мтр!G:G,MATCH($F59,[1]мтр!$C:$C,0)),"") | M59: =IFERROR(INDEX([1]мтр!H:H,MATCH($F59,[1]мтр!$C:$C,0)),"") | N59: =IFERROR(INDEX([1]мтр!I:I,MATCH($F59,[1]мтр!$C:$C,0)),"") | O59: =IFERROR(AVERAGE(R59,X59,AD59),"") | P59: =IFERROR(INDEX([2]Лист1!$E:$E,AH59),"") | Q59: =IFERROR(INDEX([2]Лист1!$I:$I,AH59),"") | R59: =IFERROR(INDEX([2]Лист1!$V:$V,AH59),"") | S59: =IFERROR(INDEX([2]Лист1!$L:$L,AH59),"") | T59: =IFERROR(INDEX([2]Лист1!$J:$J,AH59),"") | U59: =IFERROR(INDEX([2]Лист1!$K:$K,AH59),"") | V59: =IFERROR(INDEX([2]Лист1!$E:$E,AI59),"") | W59: =IFERROR(INDEX([2]Лист1!$I:$I,AI59),"") | X59: =IFERROR(INDEX([2]Лист1!$V:$V,AI59),"") | Y59: =IFERROR(INDEX([2]Лист1!$L:$L,AI59),"") | Z59: =IFERROR(INDEX([2]Лист1!$J:$J,AI59),"") | AA59: =IFERROR(INDEX([2]Лист1!$K:$K,AI59),"") | AB59: =IFERROR(INDEX([2]Лист1!$E:$E,AJ59),"") | AC59: =IFERROR(INDEX([2]Лист1!$I:$I,AJ59),"") | AD59: =IFERROR(INDEX([2]Лист1!$V:$V,AJ59),"") | AE59: =IFERROR(INDEX([2]Лист1!$L:$L,AJ59),"") | AF59: =IFERROR(INDEX([2]Лист1!$J:$J,AJ59),"") | AG59: =IFERROR(INDEX([2]Лист1!$K:$K,AJ59),"") | AH59: =MATCH(L59,[2]Лист1!$A:$A,0) -> #N/A | AI59: =MATCH(M59,[2]Лист1!$A:$A,0) -> #N/A | AJ59: =MATCH(N59,[2]Лист1!$A:$A,0) -> #N/A
A60: 1 | B60: ЛСР-03-05-602Э | C60: 3 | E60: 21.1.08.03-0042 | F60: Кабель контрольный КВВГнг(A)-FRLS 5х2,5 | G60: 1000 м | H60: 13.26 | I60: 21050.68 | J60: =H60*I60 -> 279132.02 | K60: =J60/SUM($J$2:$J$1590) -> 0.0021858866 | L60: 7307 | M60: =IFERROR(INDEX([1]мтр!H:H,MATCH($F60,[1]мтр!$C:$C,0)),"") -> 0 | N60: =IFERROR(INDEX([1]мтр!I:I,MATCH($F60,[1]мтр!$C:$C,0)),"") -> 0 | O60: =IFERROR(AVERAGE(R60,X60,AD60),"") -> 78800.752 | P60: =IFERROR(INDEX([2]Лист1!$E:$E,AH60),"") -> Импорт из РФ_КВВГнг(А)-FRLS 5х2,5 660В ТУ 16.К19-11-2000 (ГОСТ 26411-85), Транспорт экспертно 5% | Q60: =IFERROR(INDEX([2]Лист1!$I:$I,AH60),"") -> 1000 м | R60: =IFERROR(INDEX([2]Лист1!$V:$V,AH60),"") -> 78800.752 | S60: =IFERROR(INDEX([2]Лист1!$L:$L,AH60),"") -> 45047 | T60: =IFERROR(INDEX([2]Лист1!$J:$J,AH60),"") -> Группа компаний "Электрокабель" | U60: =IFERROR(INDEX([2]Лист1!$K:$K,AH60),"") -> Прайс лист от 01.05.2023 группы компаний "Электрокабель" https://elektrokable.ru/Prais_kabel/Prais-list_kabel.xls | V60: =IFERROR(INDEX([2]Лист1!$E:$E,AI60),"") | W60: =IFERROR(INDEX([2]Лист1!$I:$I,AI60),"") | X60: =IFERROR(INDEX([2]Лист1!$V:$V,AI60),"") | Y60: =IFERROR(INDEX([2]Лист1!$L:$L,AI60),"") | Z60: =IFERROR(INDEX([2]Лист1!$J:$J,AI60),"") | AA60: =IFERROR(INDEX([2]Лист1!$K:$K,AI60),"") | AB60: =IFERROR(INDEX([2]Лист1!$E:$E,AJ60),"") | AC60: =IFERROR(INDEX([2]Лист1!$I:$I,AJ60),"") | AD60: =IFERROR(INDEX([2]Лист1!$V:$V,AJ60),"") | AE60: =IFERROR(INDEX([2]Лист1!$L:$L,AJ60),"") | AF60: =IFERROR(INDEX([2]Лист1!$J:$J,AJ60),"") | AG60: =IFERROR(INDEX([2]Лист1!$K:$K,AJ60),"") | AH60: =MATCH(L60,[2]Лист1!$A:$A,0) -> 6373 | AI60: =MATCH(M60,[2]Лист1!$A:$A,0) -> #N/A | AJ60: =MATCH(N60,[2]Лист1!$A:$A,0) -> #N/A
A61: 1 | B61: ЛСР-03-05-102С | C61: 3 | E61: 04.3.02.02-0102 | F61: Состав двухкомпонентный полиуретановый для устройства монолитных покрытий пола_Полиуретановый наливной пол | G61: кг | H61: 5550.688 | I61: 50.19 | J61: =H61*I61 -> 278589.03 | K61: =J61/SUM($J$2:$J$1590) -> 0.0021816344 | L61: 5037 | M61: =IFERROR(INDEX([1]мтр!H:H,MATCH($F61,[1]мтр!$C:$C,0)),"") -> 0 | N61: =IFERROR(INDEX([1]мтр!I:I,MATCH($F61,[1]мтр!$C:$C,0)),"") -> 0 | O61: =IFERROR(AVERAGE(R61,X61,AD61),"") -> 255 | P61: =IFERROR(INDEX([2]Лист1!$E:$E,AH61),"") -> Sikafloor-264. Наливное эпоксидное покрытие, упаковка по 15 кг | Q61: =IFERROR(INDEX([2]Лист1!$I:$I,AH61),"") -> кг | R61: =IFERROR(INDEX([2]Лист1!$V:$V,AH61),"") -> 255 | S61: =IFERROR(INDEX([2]Лист1!$L:$L,AH61),"") -> 44588 | T61: =IFERROR(INDEX([2]Лист1!$J:$J,AH61),"") -> Sika Egypt For Construction Chemicals | U61: =IFERROR(INDEX([2]Лист1!$K:$K,AH61),"") -> https://www.sikaegshop.com/index.php?route=product/product&product_id=145 | V61: =IFERROR(INDEX([2]Лист1!$E:$E,AI61),"") | W61: =IFERROR(INDEX([2]Лист1!$I:$I,AI61),"") | X61: =IFERROR(INDEX([2]Лист1!$V:$V,AI61),"") | Y61: =IFERROR(INDEX([2]Лист1!$L:$L,AI61),"") | Z61: =IFERROR(INDEX([2]Лист1!$J:$J,AI61),"") | AA61: =IFERROR(INDEX([2]Лист1!$K:$K,AI61),"") | AB61: =IFERROR(INDEX([2]Лист1!$E:$E,AJ61),"") | AC61: =IFERROR(INDEX([2]Лист1!$I:$I,AJ61),"") | AD61: =IFERROR(INDEX([2]Лист1!$V:$V,AJ61),"") | AE61: =IFERROR(INDEX([2]Лист1!$L:$L,AJ61),"") | AF61: =IFERROR(INDEX([2]Лист1!$J:$J,AJ61),"") | AG61: =IFERROR(INDEX([2]Лист1!$K:$K,AJ61),"") | AH61: =MATCH(L61,[2]Лист1!$A:$A,0) -> 1270 | AI61: =MATCH(M61,[2]Лист1!$A:$A,0) -> #N/A | AJ61: =MATCH(N61,[2]Лист1!$A:$A,0) -> #N/A
A62: 1 | B62: ЛСР-03-05-202ТМ | C62: 3 | E62: ТЦ_18.1.06.04_76_7610060282_31.05.22_02 / КА п.18 / ООО "Актан" № 1194 | F62: Клапан запорный ручной (по типу А.КШ.Р.020.25.02.01), DN 20; Pmax= 0.6 Мpag; tmax= 35°C; Раб. среда: Обессоленная вода; Способ управления: Ручной привод; Тип присоединения: Фланцевый, Класс безопасности 4Н; материал - нж; С комплектом ответных фланцев под приварку с прокладками и крепежом_А.КШ.Р.020.25.02.01 | G62: шт. | H62: 12 | I62: 22325.83 | J62: =H62*I62 -> 267909.96 | K62: =J62/SUM($J$2:$J$1590) -> 0.0020980065 | L62: =IFERROR(INDEX([1]мтр!G:G,MATCH($F62,[1]мтр!$C:$C,0)),"") | M62: =IFERROR(INDEX([1]мтр!H:H,MATCH($F62,[1]мтр!$C:$C,0)),"") | N62: =IFERROR(INDEX([1]мтр!I:I,MATCH($F62,[1]мтр!$C:$C,0)),"") | O62: =IFERROR(AVERAGE(R62,X62,AD62),"") | P62: =IFERROR(INDEX([2]Лист1!$E:$E,AH62),"") | Q62: =IFERROR(INDEX([2]Лист1!$I:$I,AH62),"") | R62: =IFERROR(INDEX([2]Лист1!$V:$V,AH62),"") | S62: =IFERROR(INDEX([2]Лист1!$L:$L,AH62),"") | T62: =IFERROR(INDEX([2]Лист1!$J:$J,AH62),"") | U62: =IFERROR(INDEX([2]Лист1!$K:$K,AH62),"") | V62: =IFERROR(INDEX([2]Лист1!$E:$E,AI62),"") | W62: =IFERROR(INDEX([2]Лист1!$I:$I,AI62),"") | X62: =IFERROR(INDEX([2]Лист1!$V:$V,AI62),"") | Y62: =IFERROR(INDEX([2]Лист1!$L:$L,AI62),"") | Z62: =IFERROR(INDEX([2]Лист1!$J:$J,AI62),"") | AA62: =IFERROR(INDEX([2]Лист1!$K:$K,AI62),"") | AB62: =IFERROR(INDEX([2]Лист1!$E:$E,AJ62),"") | AC62: =IFERROR(INDEX([2]Лист1!$I:$I,AJ62),"") | AD62: =IFERROR(INDEX([2]Лист1!$V:$V,AJ62),"") | AE62: =IFERROR(INDEX([2]Лист1!$L:$L,AJ62),"") | AF62: =IFERROR(INDEX([2]Лист1!$J:$J,AJ62),"") | AG62: =IFERROR(INDEX([2]Лист1!$K:$K,AJ62),"") | AH62: =MATCH(L62,[2]Лист1!$A:$A,0) -> #N/A | AI62: =MATCH(M62,[2]Лист1!$A:$A,0) -> #N/A | AJ62: =MATCH(N62,[2]Лист1!$A:$A,0) -> #N/A
A63: 1 | B63: ЛСР-03-05-206ТМ | C63: 3 | E63: ТЦ_23.7.01.02_31_3123315768_20.05.2022_02/ КА п.76/ ООО "Белэнергомаш-БЗЭМ" №006-00073 | F63: Трубопроводы низкого давления из углеродистой стали, 4 класса безопасности, Ду > 80мм_DN150, DN125, DN100, DN80 | G63: т | H63: 1.242 | I63: 211499.32 | J63: =H63*I63 -> 262682.16 | K63: =J63/SUM($J$2:$J$1590) -> 0.0020570675 | L63: =IFERROR(INDEX([1]мтр!G:G,MATCH($F63,[1]мтр!$C:$C,0)),"") -> 4859 | M63: =IFERROR(INDEX([1]мтр!H:H,MATCH($F63,[1]мтр!$C:$C,0)),"") -> 0 | N63: =IFERROR(INDEX([1]мтр!I:I,MATCH($F63,[1]мтр!$C:$C,0)),"") -> 0 | O63: =IFERROR(AVERAGE(R63,X63,AD63),"") -> 479788.26 | P63: =IFERROR(INDEX([2]Лист1!$E:$E,AH63),"") -> Трубопроводы низкого давления из углеродистой стали зданий UJA, UKD. Объём: 4526466 руб. / 2939,52 кг = 1540 RUB/кг. Транспорт 5800 USD (Договор ЕОС-закупки №629007, №7720/220816 от 07.09.2022, АСЭ_Рускон) /40DV контейнер 25 т, класс груза - 2, загрузка 85%. | Q63: =IFERROR(INDEX([2]Лист1!$I:$I,AH63),"") -> т | R63: =IFERROR(INDEX([2]Лист1!$V:$V,AH63),"") -> 479788.26 | S63: =IFERROR(INDEX([2]Лист1!$L:$L,AH63),"") -> 44753 | T63: =IFERROR(INDEX([2]Лист1!$J:$J,AH63),"") -> Белэнергомаш-БЗЭМ | U63: =IFERROR(INDEX([2]Лист1!$K:$K,AH63),"") -> Поставка трубопроводов по лоту 19677-248 Куд3;4. НМЦ от 11.07.2022, рассчитанная на основании п.1 раздела 3 главы 3 (приложения №8 к ЕОСЗ). | V63: =IFERROR(INDEX([2]Лист1!$E:$E,AI63),"") | W63: =IFERROR(INDEX([2]Лист1!$I:$I,AI63),"") | X63: =IFERROR(INDEX([2]Лист1!$V:$V,AI63),"") | Y63: =IFERROR(INDEX([2]Лист1!$L:$L,AI63),"") | Z63: =IFERROR(INDEX([2]Лист1!$J:$J,AI63),"") | AA63: =IFERROR(INDEX([2]Лист1!$K:$K,AI63),"") | AB63: =IFERROR(INDEX([2]Лист1!$E:$E,AJ63),"") | AC63: =IFERROR(INDEX([2]Лист1!$I:$I,AJ63),"") | AD63: =IFERROR(INDEX([2]Лист1!$V:$V,AJ63),"") | AE63: =IFERROR(INDEX([2]Лист1!$L:$L,AJ63),"") | AF63: =IFERROR(INDEX([2]Лист1!$J:$J,AJ63),"") | AG63: =IFERROR(INDEX([2]Лист1!$K:$K,AJ63),"") | AH63: =MATCH(L63,[2]Лист1!$A:$A,0) -> 4796 | AI63: =MATCH(M63,[2]Лист1!$A:$A,0) -> #N/A | AJ63: =MATCH(N63,[2]Лист1!$A:$A,0) -> #N/A
A64: 1 | B64: ЛСР-03-05-501ОВ | C64: 3 | E64: 19.3.01.04-1008 | F64: Заслонка регулирующая для прямоугольных каналов, ширина 500 мм, высота 300 мм_Клапан ручной регулирующий (прим) | G64: ШТ | H64: 360 | I64: 725.36 | J64: =H64*I64 -> 261129.6 | K64: =J64/SUM($J$2:$J$1590) -> 0.0020449094 | L64: =IFERROR(INDEX([1]мтр!G:G,MATCH($F64,[1]мтр!$C:$C,0)),"") | M64: =IFERROR(INDEX([1]мтр!H:H,MATCH($F64,[1]мтр!$C:$C,0)),"") | N64: =IFERROR(INDEX([1]мтр!I:I,MATCH($F64,[1]мтр!$C:$C,0)),"") | O64: =IFERROR(AVERAGE(R64,X64,AD64),"") | P64: =IFERROR(INDEX([2]Лист1!$E:$E,AH64),"") | Q64: =IFERROR(INDEX([2]Лист1!$I:$I,AH64),"") | R64: =IFERROR(INDEX([2]Лист1!$V:$V,AH64),"") | S64: =IFERROR(INDEX([2]Лист1!$L:$L,AH64),"") | T64: =IFERROR(INDEX([2]Лист1!$J:$J,AH64),"") | U64: =IFERROR(INDEX([2]Лист1!$K:$K,AH64),"") | V64: =IFERROR(INDEX([2]Лист1!$E:$E,AI64),"") | W64: =IFERROR(INDEX([2]Лист1!$I:$I,AI64),"") | X64: =IFERROR(INDEX([2]Лист1!$V:$V,AI64),"") | Y64: =IFERROR(INDEX([2]Лист1!$L:$L,AI64),"") | Z64: =IFERROR(INDEX([2]Лист1!$J:$J,AI64),"") | AA64: =IFERROR(INDEX([2]Лист1!$K:$K,AI64),"") | AB64: =IFERROR(INDEX([2]Лист1!$E:$E,AJ64),"") | AC64: =IFERROR(INDEX([2]Лист1!$I:$I,AJ64),"") | AD64: =IFERROR(INDEX([2]Лист1!$V:$V,AJ64),"") | AE64: =IFERROR(INDEX([2]Лист1!$L:$L,AJ64),"") | AF64: =IFERROR(INDEX([2]Лист1!$J:$J,AJ64),"") | AG64: =IFERROR(INDEX([2]Лист1!$K:$K,AJ64),"") | AH64: =MATCH(L64,[2]Лист1!$A:$A,0) -> #N/A | AI64: =MATCH(M64,[2]Лист1!$A:$A,0) -> #N/A | AJ64: =MATCH(N64,[2]Лист1!$A:$A,0) -> #N/A
A65: 1 | B65: ЛСР-03-05-201ТМ | C65: 3 | E65: ТЦ_18.1.06.05_53_5321034434_31.05.2022_02 /КА п. 10/ ПАО "Контур" №26-1285 | F65: Регулирующая арматура НГ27101-010-М-03 DN 6; pmax=1.3 MPag; tmax=195 °С; Раб. среда:Пар насыщенный; Способ управления : Ручной привод; Тип присоединения: Под приварку, нерж, класс 4Н, масса 6,9кг | G65: ШТ | H65: 8 | I65: 32099.21 | J65: =H65*I65 -> 256793.68 | K65: =J65/SUM($J$2:$J$1590) -> 0.0020109548 | L65: =IFERROR(INDEX([1]мтр!G:G,MATCH($F65,[1]мтр!$C:$C,0)),"") | M65: =IFERROR(INDEX([1]мтр!H:H,MATCH($F65,[1]мтр!$C:$C,0)),"") | N65: =IFERROR(INDEX([1]мтр!I:I,MATCH($F65,[1]мтр!$C:$C,0)),"") | O65: =IFERROR(AVERAGE(R65,X65,AD65),"") | P65: =IFERROR(INDEX([2]Лист1!$E:$E,AH65),"") | Q65: =IFERROR(INDEX([2]Лист1!$I:$I,AH65),"") | R65: =IFERROR(INDEX([2]Лист1!$V:$V,AH65),"") | S65: =IFERROR(INDEX([2]Лист1!$L:$L,AH65),"") | T65: =IFERROR(INDEX([2]Лист1!$J:$J,AH65),"") | U65: =IFERROR(INDEX([2]Лист1!$K:$K,AH65),"") | V65: =IFERROR(INDEX([2]Лист1!$E:$E,AI65),"") | W65: =IFERROR(INDEX([2]Лист1!$I:$I,AI65),"") | X65: =IFERROR(INDEX([2]Лист1!$V:$V,AI65),"") | Y65: =IFERROR(INDEX([2]Лист1!$L:$L,AI65),"") | Z65: =IFERROR(INDEX([2]Лист1!$J:$J,AI65),"") | AA65: =IFERROR(INDEX([2]Лист1!$K:$K,AI65),"") | AB65: =IFERROR(INDEX([2]Лист1!$E:$E,AJ65),"") | AC65: =IFERROR(INDEX([2]Лист1!$I:$I,AJ65),"") | AD65: =IFERROR(INDEX([2]Лист1!$V:$V,AJ65),"") | AE65: =IFERROR(INDEX([2]Лист1!$L:$L,AJ65),"") | AF65: =IFERROR(INDEX([2]Лист1!$J:$J,AJ65),"") | AG65: =IFERROR(INDEX([2]Лист1!$K:$K,AJ65),"") | AH65: =MATCH(L65,[2]Лист1!$A:$A,0) -> #N/A | AI65: =MATCH(M65,[2]Лист1!$A:$A,0) -> #N/A | AJ65: =MATCH(N65,[2]Лист1!$A:$A,0) -> #N/A
A66: 1 | B66: ЛСР-03-05-701АК | C66: 3 | E66: ТЦ_25.3.18.01_77_7716218811_26.05.2022_01 | F66: Взрывобезопасный корпус с крышкой на винтах KE 9306.000 Rittal ШВГ: 300х300х120 мм; Монтажная панель для KL 275х285х2 мм, оцинкованная сталь – 1 шт; IP66; Кабельный ввод M20х1.5, латунь – 10 шт; DIN-рейка 35х7.5 для ширины 300 мм – 10 шт. 4; III; QNC | G66: шт. | H66: 1 | I66: 250536.12 | J66: =H66*I66 -> 250536.12 | K66: =J66/SUM($J$2:$J$1590) -> 0.0019619517 | L66: =IFERROR(INDEX([1]мтр!G:G,MATCH($F66,[1]мтр!$C:$C,0)),"") | M66: =IFERROR(INDEX([1]мтр!H:H,MATCH($F66,[1]мтр!$C:$C,0)),"") | N66: =IFERROR(INDEX([1]мтр!I:I,MATCH($F66,[1]мтр!$C:$C,0)),"") | O66: =IFERROR(AVERAGE(R66,X66,AD66),"") | P66: =IFERROR(INDEX([2]Лист1!$E:$E,AH66),"") | Q66: =IFERROR(INDEX([2]Лист1!$I:$I,AH66),"") | R66: =IFERROR(INDEX([2]Лист1!$V:$V,AH66),"") | S66: =IFERROR(INDEX([2]Лист1!$L:$L,AH66),"") | T66: =IFERROR(INDEX([2]Лист1!$J:$J,AH66),"") | U66: =IFERROR(INDEX([2]Лист1!$K:$K,AH66),"") | V66: =IFERROR(INDEX([2]Лист1!$E:$E,AI66),"") | W66: =IFERROR(INDEX([2]Лист1!$I:$I,AI66),"") | X66: =IFERROR(INDEX([2]Лист1!$V:$V,AI66),"") | Y66: =IFERROR(INDEX([2]Лист1!$L:$L,AI66),"") | Z66: =IFERROR(INDEX([2]Лист1!$J:$J,AI66),"") | AA66: =IFERROR(INDEX([2]Лист1!$K:$K,AI66),"") | AB66: =IFERROR(INDEX([2]Лист1!$E:$E,AJ66),"") | AC66: =IFERROR(INDEX([2]Лист1!$I:$I,AJ66),"") | AD66: =IFERROR(INDEX([2]Лист1!$V:$V,AJ66),"") | AE66: =IFERROR(INDEX([2]Лист1!$L:$L,AJ66),"") | AF66: =IFERROR(INDEX([2]Лист1!$J:$J,AJ66),"") | AG66: =IFERROR(INDEX([2]Лист1!$K:$K,AJ66),"") | AH66: =MATCH(L66,[2]Лист1!$A:$A,0) -> #N/A | AI66: =MATCH(M66,[2]Лист1!$A:$A,0) -> #N/A | AJ66: =MATCH(N66,[2]Лист1!$A:$A,0) -> #N/A
A67: 1 | B67: ЛСР-03-05-206ТМ | C67: 3 | E67: ТЦ_23.7.01.02_31_3123315768_20.05.2022_02/ КА п.75/ ООО "Белэнергомаш-БЗЭМ" №006-00073 | F67: Трубопроводы низкого давления из углеродистой стали, 4 класса безопасности, Ду < 80мм _DN65, DN50, DN40, DN25, DN15, DN10, | G67: т | H67: 0.679 | I67: 364063.42 | J67: =H67*I67 -> 247199.06 | K67: =J67/SUM($J$2:$J$1590) -> 0.0019358192 | L67: =IFERROR(INDEX([1]мтр!G:G,MATCH($F67,[1]мтр!$C:$C,0)),"") -> 4859 | M67: =IFERROR(INDEX([1]мтр!H:H,MATCH($F67,[1]мтр!$C:$C,0)),"") -> 0 | N67: =IFERROR(INDEX([1]мтр!I:I,MATCH($F67,[1]мтр!$C:$C,0)),"") -> 0 | O67: =IFERROR(AVERAGE(R67,X67,AD67),"") -> 479788.26 | P67: =IFERROR(INDEX([2]Лист1!$E:$E,AH67),"") -> Трубопроводы низкого давления из углеродистой стали зданий UJA, UKD. Объём: 4526466 руб. / 2939,52 кг = 1540 RUB/кг. Транспорт 5800 USD (Договор ЕОС-закупки №629007, №7720/220816 от 07.09.2022, АСЭ_Рускон) /40DV контейнер 25 т, класс груза - 2, загрузка 85%. | Q67: =IFERROR(INDEX([2]Лист1!$I:$I,AH67),"") -> т | R67: =IFERROR(INDEX([2]Лист1!$V:$V,AH67),"") -> 479788.26 | S67: =IFERROR(INDEX([2]Лист1!$L:$L,AH67),"") -> 44753 | T67: =IFERROR(INDEX([2]Лист1!$J:$J,AH67),"") -> Белэнергомаш-БЗЭМ | U67: =IFERROR(INDEX([2]Лист1!$K:$K,AH67),"") -> Поставка трубопроводов по лоту 19677-248 Куд3;4. НМЦ от 11.07.2022, рассчитанная на основании п.1 раздела 3 главы 3 (приложения №8 к ЕОСЗ). | V67: =IFERROR(INDEX([2]Лист1!$E:$E,AI67),"") | W67: =IFERROR(INDEX([2]Лист1!$I:$I,AI67),"") | X67: =IFERROR(INDEX([2]Лист1!$V:$V,AI67),"") | Y67: =IFERROR(INDEX([2]Лист1!$L:$L,AI67),"") | Z67: =IFERROR(INDEX([2]Лист1!$J:$J,AI67),"") | AA67: =IFERROR(INDEX([2]Лист1!$K:$K,AI67),"") | AB67: =IFERROR(INDEX([2]Лист1!$E:$E,AJ67),"") | AC67: =IFERROR(INDEX([2]Лист1!$I:$I,AJ67),"") | AD67: =IFERROR(INDEX([2]Лист1!$V:$V,AJ67),"") | AE67: =IFERROR(INDEX([2]Лист1!$L:$L,AJ67),"") | AF67: =IFERROR(INDEX([2]Лист1!$J:$J,AJ67),"") | AG67: =IFERROR(INDEX([2]Лист1!$K:$K,AJ67),"") | AH67: =MATCH(L67,[2]Лист1!$A:$A,0) -> 4796 | AI67: =MATCH(M67,[2]Лист1!$A:$A,0) -> #N/A | AJ67: =MATCH(N67,[2]Лист1!$A:$A,0) -> #N/A
A68: 1 | B68: ЛСР-03-05-501ОВ | C68: 3 | E68: 08.3.05.05-0058 | F68: Сталь листовая оцинкованная, толщина 1,0 мм_Для воздуховодов Д560мм | G68: т | H68: 22.5 | I68: 10500 | J68: =H68*I68 -> 236250 | K68: =J68/SUM($J$2:$J$1590) -> 0.0018500769 | L68: =IFERROR(INDEX([1]мтр!G:G,MATCH($F68,[1]мтр!$C:$C,0)),"") -> 5420 | M68: =IFERROR(INDEX([1]мтр!H:H,MATCH($F68,[1]мтр!$C:$C,0)),"") -> 5421 | N68: =IFERROR(INDEX([1]мтр!I:I,MATCH($F68,[1]мтр!$C:$C,0)),"") -> 0 | O68: =IFERROR(AVERAGE(R68,X68,AD68),"") -> 29646.055 | P68: =IFERROR(INDEX([2]Лист1!$E:$E,AH68),"") -> Сталь листовая оцинкованная толщиной листа 1,0 мм (Лист оцинкованный 1х1250х2500 Zn140 М пас ст 220) Транспорт экспертно 5% | Q68: =IFERROR(INDEX([2]Лист1!$I:$I,AH68),"") -> т | R68: =IFERROR(INDEX([2]Лист1!$V:$V,AH68),"") -> 26699.168 | S68: =IFERROR(INDEX([2]Лист1!$L:$L,AH68),"") -> 44886 | T68: =IFERROR(INDEX([2]Лист1!$J:$J,AH68),"") -> Металлсервис | U68: =IFERROR(INDEX([2]Лист1!$K:$K,AH68),"") -> https://mc.ru/metalloprokat/list_ocinkovannyy_1x1250x2500_zn140_m_pas_st_220_razmer_1 | V68: =IFERROR(INDEX([2]Лист1!$E:$E,AI68),"") -> Сталь листовая оцинкованная толщиной листа 1,0 мм (ОЦ 02 1 1250 2500 52246 100 ПС ≤3,6) Транспорт экспертно 5% | W68: =IFERROR(INDEX([2]Лист1!$I:$I,AI68),"") -> т | X68: =IFERROR(INDEX([2]Лист1!$V:$V,AI68),"") -> 32592.941 | Y68: =IFERROR(INDEX([2]Лист1!$L:$L,AI68),"") -> 44886 | Z68: =IFERROR(INDEX([2]Лист1!$J:$J,AI68),"") -> НЛМК | AA68: =IFERROR(INDEX([2]Лист1!$K:$K,AI68),"") -> https://nlmk.shop/catalog/galvanized-steel/list-ocinkovannyj/list-oc-1/?q=%3Arelevance | AB68: =IFERROR(INDEX([2]Лист1!$E:$E,AJ68),"") | AC68: =IFERROR(INDEX([2]Лист1!$I:$I,AJ68),"") | AD68: =IFERROR(INDEX([2]Лист1!$V:$V,AJ68),"") | AE68: =IFERROR(INDEX([2]Лист1!$L:$L,AJ68),"") | AF68: =IFERROR(INDEX([2]Лист1!$J:$J,AJ68),"") | AG68: =IFERROR(INDEX([2]Лист1!$K:$K,AJ68),"") | AH68: =MATCH(L68,[2]Лист1!$A:$A,0) -> 4932 | AI68: =MATCH(M68,[2]Лист1!$A:$A,0) -> 4933 | AJ68: =MATCH(N68,[2]Лист1!$A:$A,0) -> #N/A
A69: 1 | B69: ЛСР-03-05-204ВП | C69: 3 | E69: ТЦ_23.7.01.02_31_3123315768_20.05.2022_02/ КА п.12/ООО "Белэнергомаш-БЗЭМ" №006-00073 | F69: Трубопроводы из нержавеющей стали низкого давления 4 класса безопасности Ду<80 | G69: т | H69: 0.295 | I69: 799960.85 | J69: =H69*I69 -> 235988.45 | K69: =J69/SUM($J$2:$J$1590) -> 0.0018480287 | L69: =IFERROR(INDEX([1]мтр!G:G,MATCH($F69,[1]мтр!$C:$C,0)),"") -> 4861 | M69: =IFERROR(INDEX([1]мтр!H:H,MATCH($F69,[1]мтр!$C:$C,0)),"") -> 0 | N69: =IFERROR(INDEX([1]мтр!I:I,MATCH($F69,[1]мтр!$C:$C,0)),"") -> 0 | O69: =IFERROR(AVERAGE(R69,X69,AD69),"") -> 2050605.2 | P69: =IFERROR(INDEX([2]Лист1!$E:$E,AH69),"") -> Трубопроводы низкого давления из нержавеющей стали зданий UJA, UKD. Объём: 40 315 616 руб. / 6 074,16 кг = 6637 RUB/кг. Транспорт 5800 USD (Договор ЕОС-закупки №629007, №7720/220816 от 07.09.2022, АСЭ_Рускон) /40DV контейнер 25 т, класс груза - 2, загрузка 85%. | Q69: =IFERROR(INDEX([2]Лист1!$I:$I,AH69),"") -> т | R69: =IFERROR(INDEX([2]Лист1!$V:$V,AH69),"") -> 2050605.2 | S69: =IFERROR(INDEX([2]Лист1!$L:$L,AH69),"") -> 44753 | T69: =IFERROR(INDEX([2]Лист1!$J:$J,AH69),"") -> Белэнергомаш-БЗЭМ | U69: =IFERROR(INDEX([2]Лист1!$K:$K,AH69),"") -> Поставка трубопроводов по лоту 19677-248 Куд3;4. НМЦ от 11.07.2022, рассчитанная на основании п.1 раздела 3 главы 3 (приложения №8 к ЕОСЗ). | V69: =IFERROR(INDEX([2]Лист1!$E:$E,AI69),"") | W69: =IFERROR(INDEX([2]Лист1!$I:$I,AI69),"") | X69: =IFERROR(INDEX([2]Лист1!$V:$V,AI69),"") | Y69: =IFERROR(INDEX([2]Лист1!$L:$L,AI69),"") | Z69: =IFERROR(INDEX([2]Лист1!$J:$J,AI69),"") | AA69: =IFERROR(INDEX([2]Лист1!$K:$K,AI69),"") | AB69: =IFERROR(INDEX([2]Лист1!$E:$E,AJ69),"") | AC69: =IFERROR(INDEX([2]Лист1!$I:$I,AJ69),"") | AD69: =IFERROR(INDEX([2]Лист1!$V:$V,AJ69),"") | AE69: =IFERROR(INDEX([2]Лист1!$L:$L,AJ69),"") | AF69: =IFERROR(INDEX([2]Лист1!$J:$J,AJ69),"") | AG69: =IFERROR(INDEX([2]Лист1!$K:$K,AJ69),"") | AH69: =MATCH(L69,[2]Лист1!$A:$A,0) -> 4798 | AI69: =MATCH(M69,[2]Лист1!$A:$A,0) -> #N/A | AJ69: =MATCH(N69,[2]Лист1!$A:$A,0) -> #N/A
A70: 1 | B70: ЛСР-03-05-203ТМ | C70: 3 | E70: ТЦ_18.1.06.00_50_5503095632_05.07.2022_02 /КА п.45/ ЗАО "Сибгазстройдеталь" №897 | F70: Запорная арматура По типу 1156-125-М DN 125; pmax=1.10 MPag; tmax=40 °С / °C; Раб. среда:Вода химически обессоленная; Способ управления: Ручной привод; Тип присоединения: Под приварку Кл. 4Н, угл.ст. | G70: шт. | H70: 1 | I70: 226407.66 | J70: =H70*I70 -> 226407.66 | K70: =J70/SUM($J$2:$J$1590) -> 0.0017730014 | L70: 7311 | M70: =IFERROR(INDEX([1]мтр!H:H,MATCH($F70,[1]мтр!$C:$C,0)),"") | N70: =IFERROR(INDEX([1]мтр!I:I,MATCH($F70,[1]мтр!$C:$C,0)),"") | O70: =IFERROR(AVERAGE(R70,X70,AD70),"") -> 0 | P70: =IFERROR(INDEX([2]Лист1!$E:$E,AH70),"") -> 0 | Q70: =IFERROR(INDEX([2]Лист1!$I:$I,AH70),"") -> 0 | R70: =IFERROR(INDEX([2]Лист1!$V:$V,AH70),"") -> 0 | S70: =IFERROR(INDEX([2]Лист1!$L:$L,AH70),"") -> 0 | T70: =IFERROR(INDEX([2]Лист1!$J:$J,AH70),"") -> 0 | U70: =IFERROR(INDEX([2]Лист1!$K:$K,AH70),"") -> 0 | V70: =IFERROR(INDEX([2]Лист1!$E:$E,AI70),"") | W70: =IFERROR(INDEX([2]Лист1!$I:$I,AI70),"") | X70: =IFERROR(INDEX([2]Лист1!$V:$V,AI70),"") | Y70: =IFERROR(INDEX([2]Лист1!$L:$L,AI70),"") | Z70: =IFERROR(INDEX([2]Лист1!$J:$J,AI70),"") | AA70: =IFERROR(INDEX([2]Лист1!$K:$K,AI70),"") | AB70: =IFERROR(INDEX([2]Лист1!$E:$E,AJ70),"") | AC70: =IFERROR(INDEX([2]Лист1!$I:$I,AJ70),"") | AD70: =IFERROR(INDEX([2]Лист1!$V:$V,AJ70),"") | AE70: =IFERROR(INDEX([2]Лист1!$L:$L,AJ70),"") | AF70: =IFERROR(INDEX([2]Лист1!$J:$J,AJ70),"") | AG70: =IFERROR(INDEX([2]Лист1!$K:$K,AJ70),"") | AH70: =MATCH(L70,[2]Лист1!$A:$A,0) -> 6377 | AI70: =MATCH(M70,[2]Лист1!$A:$A,0) -> #N/A | AJ70: =MATCH(N70,[2]Лист1!$A:$A,0) -> #N/A
A71: 1 | B71: ЛСР-03-05-203ТМ | C71: 3 | E71: ТЦ_18.1.06.00_50_5503095632_05.07.2022_02/ КА п.73/ ЗАО "Сибгазстройдеталь" №897 | F71: Запорная арматура По типу 1156-125-М DN 125; pmax=0.7 MPag; tmax=25 °С / °C; Раб. среда:Вода химически обессоленная; Способ управления: Ручной привод; Тип присоединения: Под приварку, Кл 4 Н, угл.ст. | G71: шт. | H71: 1 | I71: 226407.66 | J71: =H71*I71 -> 226407.66 | K71: =J71/SUM($J$2:$J$1590) -> 0.0017730014 | L71: 7312 | M71: =IFERROR(INDEX([1]мтр!H:H,MATCH($F71,[1]мтр!$C:$C,0)),"") | N71: =IFERROR(INDEX([1]мтр!I:I,MATCH($F71,[1]мтр!$C:$C,0)),"") | O71: =IFERROR(AVERAGE(R71,X71,AD71),"") -> 0 | P71: =IFERROR(INDEX([2]Лист1!$E:$E,AH71),"") -> 0 | Q71: =IFERROR(INDEX([2]Лист1!$I:$I,AH71),"") -> 0 | R71: =IFERROR(INDEX([2]Лист1!$V:$V,AH71),"") -> 0 | S71: =IFERROR(INDEX([2]Лист1!$L:$L,AH71),"") -> 0 | T71: =IFERROR(INDEX([2]Лист1!$J:$J,AH71),"") -> 0 | U71: =IFERROR(INDEX([2]Лист1!$K:$K,AH71),"") -> 0 | V71: =IFERROR(INDEX([2]Лист1!$E:$E,AI71),"") | W71: =IFERROR(INDEX([2]Лист1!$I:$I,AI71),"") | X71: =IFERROR(INDEX([2]Лист1!$V:$V,AI71),"") | Y71: =IFERROR(INDEX([2]Лист1!$L:$L,AI71),"") | Z71: =IFERROR(INDEX([2]Лист1!$J:$J,AI71),"") | AA71: =IFERROR(INDEX([2]Лист1!$K:$K,AI71),"") | AB71: =IFERROR(INDEX([2]Лист1!$E:$E,AJ71),"") | AC71: =IFERROR(INDEX([2]Лист1!$I:$I,AJ71),"") | AD71: =IFERROR(INDEX([2]Лист1!$V:$V,AJ71),"") | AE71: =IFERROR(INDEX([2]Лист1!$L:$L,AJ71),"") | AF71: =IFERROR(INDEX([2]Лист1!$J:$J,AJ71),"") | AG71: =IFERROR(INDEX([2]Лист1!$K:$K,AJ71),"") | AH71: =MATCH(L71,[2]Лист1!$A:$A,0) -> 6378 | AI71: =MATCH(M71,[2]Лист1!$A:$A,0) -> #N/A | AJ71: =MATCH(N71,[2]Лист1!$A:$A,0) -> #N/A
A72: 1 | B72: ЛСР-03-05-203ТМ | C72: 3 | E72: ТЦ_18.1.06.00_50_5503095632_05.07.2022_02 /КА п.55/ ЗАО "Сибгазстройдеталь" №897 | F72: Запорная арматура По типу 1156-125-М DN 125; pmax=1.94 MPag; tmax=130 °С / °C; Раб. среда:Вода питательная ПРК; Способ управления: Ручной привод; Тип присоединения: Под приварку, Кл.4Н, угл.ст. | G72: шт. | H72: 1 | I72: 226407.66 | J72: =H72*I72 -> 226407.66 | K72: =J72/SUM($J$2:$J$1590) -> 0.0017730014 | L72: 7313 | M72: =IFERROR(INDEX([1]мтр!H:H,MATCH($F72,[1]мтр!$C:$C,0)),"") | N72: =IFERROR(INDEX([1]мтр!I:I,MATCH($F72,[1]мтр!$C:$C,0)),"") | O72: =IFERROR(AVERAGE(R72,X72,AD72),"") -> 0 | P72: =IFERROR(INDEX([2]Лист1!$E:$E,AH72),"") -> 0 | Q72: =IFERROR(INDEX([2]Лист1!$I:$I,AH72),"") -> 0 | R72: =IFERROR(INDEX([2]Лист1!$V:$V,AH72),"") -> 0 | S72: =IFERROR(INDEX([2]Лист1!$L:$L,AH72),"") -> 0 | T72: =IFERROR(INDEX([2]Лист1!$J:$J,AH72),"") -> 0 | U72: =IFERROR(INDEX([2]Лист1!$K:$K,AH72),"") -> 0 | V72: =IFERROR(INDEX([2]Лист1!$E:$E,AI72),"") | W72: =IFERROR(INDEX([2]Лист1!$I:$I,AI72),"") | X72: =IFERROR(INDEX([2]Лист1!$V:$V,AI72),"") | Y72: =IFERROR(INDEX([2]Лист1!$L:$L,AI72),"") | Z72: =IFERROR(INDEX([2]Лист1!$J:$J,AI72),"") | AA72: =IFERROR(INDEX([2]Лист1!$K:$K,AI72),"") | AB72: =IFERROR(INDEX([2]Лист1!$E:$E,AJ72),"") | AC72: =IFERROR(INDEX([2]Лист1!$I:$I,AJ72),"") | AD72: =IFERROR(INDEX([2]Лист1!$V:$V,AJ72),"") | AE72: =IFERROR(INDEX([2]Лист1!$L:$L,AJ72),"") | AF72: =IFERROR(INDEX([2]Лист1!$J:$J,AJ72),"") | AG72: =IFERROR(INDEX([2]Лист1!$K:$K,AJ72),"") | AH72: =MATCH(L72,[2]Лист1!$A:$A,0) -> 6379 | AI72: =MATCH(M72,[2]Лист1!$A:$A,0) -> #N/A | AJ72: =MATCH(N72,[2]Лист1!$A:$A,0) -> #N/A
A73: 1 | B73: ЛСР-03-05-303ПТ | C73: 3 | E73: ТЦ_18.1.03.02_64_6454042041_28.03.2022_02 / КА п. 1 / ЗАО "Саратовэнергомашкомплект" №ИП-22/901 от 28.03.2022г. | F73: Затвор дисковый поворотный межфланцевый с ответными фланцами под приварку в стык, прокладками, крепежом и датчиком положения DN 100; tmax=35 °С; Раб. среда:Вода на противопожарные нужды; Способ управления : Ручной привод; Тип присоединения: Фланцевый; Pnom=1.0 MPag; Tnom=15 °С; материал корпуса: углеродистая сталь | G73: ШТ | H73: 11 | I73: 20427.26 | J73: =H73*I73 -> 224699.86 | K73: =J73/SUM($J$2:$J$1590) -> 0.0017596276 | L73: =IFERROR(INDEX([1]мтр!G:G,MATCH($F73,[1]мтр!$C:$C,0)),"") | M73: =IFERROR(INDEX([1]мтр!H:H,MATCH($F73,[1]мтр!$C:$C,0)),"") | N73: =IFERROR(INDEX([1]мтр!I:I,MATCH($F73,[1]мтр!$C:$C,0)),"") | O73: =IFERROR(AVERAGE(R73,X73,AD73),"") | P73: =IFERROR(INDEX([2]Лист1!$E:$E,AH73),"") | Q73: =IFERROR(INDEX([2]Лист1!$I:$I,AH73),"") | R73: =IFERROR(INDEX([2]Лист1!$V:$V,AH73),"") | S73: =IFERROR(INDEX([2]Лист1!$L:$L,AH73),"") | T73: =IFERROR(INDEX([2]Лист1!$J:$J,AH73),"") | U73: =IFERROR(INDEX([2]Лист1!$K:$K,AH73),"") | V73: =IFERROR(INDEX([2]Лист1!$E:$E,AI73),"") | W73: =IFERROR(INDEX([2]Лист1!$I:$I,AI73),"") | X73: =IFERROR(INDEX([2]Лист1!$V:$V,AI73),"") | Y73: =IFERROR(INDEX([2]Лист1!$L:$L,AI73),"") | Z73: =IFERROR(INDEX([2]Лист1!$J:$J,AI73),"") | AA73: =IFERROR(INDEX([2]Лист1!$K:$K,AI73),"") | AB73: =IFERROR(INDEX([2]Лист1!$E:$E,AJ73),"") | AC73: =IFERROR(INDEX([2]Лист1!$I:$I,AJ73),"") | AD73: =IFERROR(INDEX([2]Лист1!$V:$V,AJ73),"") | AE73: =IFERROR(INDEX([2]Лист1!$L:$L,AJ73),"") | AF73: =IFERROR(INDEX([2]Лист1!$J:$J,AJ73),"") | AG73: =IFERROR(INDEX([2]Лист1!$K:$K,AJ73),"") | AH73: =MATCH(L73,[2]Лист1!$A:$A,0) -> #N/A | AI73: =MATCH(M73,[2]Лист1!$A:$A,0) -> #N/A | AJ73: =MATCH(N73,[2]Лист1!$A:$A,0) -> #N/A
A74: 1 | B74: ЛСР-03-05-102С | C74: 3 | E74: 08.1.02.23-0001 | F74: Покрытия зданий с повышенными архитектурными требованиями сайдинг стальной с полимерным покрытием_Кассетные стальные стеновые панели 600х1200х30 мм | G74: м2 | H74: 1647.988 | I74: 132.94 | J74: =H74*I74 -> 219083.52 | K74: =J74/SUM($J$2:$J$1590) -> 0.001715646 | L74: =IFERROR(INDEX([1]мтр!G:G,MATCH($F74,[1]мтр!$C:$C,0)),"") | M74: =IFERROR(INDEX([1]мтр!H:H,MATCH($F74,[1]мтр!$C:$C,0)),"") | N74: =IFERROR(INDEX([1]мтр!I:I,MATCH($F74,[1]мтр!$C:$C,0)),"") | O74: =IFERROR(AVERAGE(R74,X74,AD74),"") | P74: =IFERROR(INDEX([2]Лист1!$E:$E,AH74),"") | Q74: =IFERROR(INDEX([2]Лист1!$I:$I,AH74),"") | R74: =IFERROR(INDEX([2]Лист1!$V:$V,AH74),"") | S74: =IFERROR(INDEX([2]Лист1!$L:$L,AH74),"") | T74: =IFERROR(INDEX([2]Лист1!$J:$J,AH74),"") | U74: =IFERROR(INDEX([2]Лист1!$K:$K,AH74),"") | V74: =IFERROR(INDEX([2]Лист1!$E:$E,AI74),"") | W74: =IFERROR(INDEX([2]Лист1!$I:$I,AI74),"") | X74: =IFERROR(INDEX([2]Лист1!$V:$V,AI74),"") | Y74: =IFERROR(INDEX([2]Лист1!$L:$L,AI74),"") | Z74: =IFERROR(INDEX([2]Лист1!$J:$J,AI74),"") | AA74: =IFERROR(INDEX([2]Лист1!$K:$K,AI74),"") | AB74: =IFERROR(INDEX([2]Лист1!$E:$E,AJ74),"") | AC74: =IFERROR(INDEX([2]Лист1!$I:$I,AJ74),"") | AD74: =IFERROR(INDEX([2]Лист1!$V:$V,AJ74),"") | AE74: =IFERROR(INDEX([2]Лист1!$L:$L,AJ74),"") | AF74: =IFERROR(INDEX([2]Лист1!$J:$J,AJ74),"") | AG74: =IFERROR(INDEX([2]Лист1!$K:$K,AJ74),"") | AH74: =MATCH(L74,[2]Лист1!$A:$A,0) -> #N/A | AI74: =MATCH(M74,[2]Лист1!$A:$A,0) -> #N/A | AJ74: =MATCH(N74,[2]Лист1!$A:$A,0) -> #N/A
A75: 3 | B75: ЛСР-03-06-101С | C75: 3 | E75: 12.1.02.10-0131 | F75: ТПО-мембрана гидроизоляционная, марка Sikaplan "WT 1200-20C" ("Sarnafil TG68-20")_ТПО-мембрана гидроизоляционная на основе термопластичного полиолефина типа Sikaplan WT | G75: м2 | H75: 380.16 | I75: 548.11 | J75: =H75*I75 -> 208369.5 | K75: =J75/SUM($J$2:$J$1590) -> 0.0016317443 | L75: =IFERROR(INDEX([1]мтр!G:G,MATCH($F75,[1]мтр!$C:$C,0)),"") -> 4683 | M75: =IFERROR(INDEX([1]мтр!H:H,MATCH($F75,[1]мтр!$C:$C,0)),"") -> 0 | N75: =IFERROR(INDEX([1]мтр!I:I,MATCH($F75,[1]мтр!$C:$C,0)),"") -> 0 | O75: =IFERROR(AVERAGE(R75,X75,AD75),"") -> 600 | P75: =IFERROR(INDEX([2]Лист1!$E:$E,AH75),"") -> ТПО-мембрана гидроизоляционная, марка Sikaplan WT 1200-20C | Q75: =IFERROR(INDEX([2]Лист1!$I:$I,AH75),"") -> м2 | R75: =IFERROR(INDEX([2]Лист1!$V:$V,AH75),"") -> 600 | S75: =IFERROR(INDEX([2]Лист1!$L:$L,AH75),"") -> 44608 | T75: =IFERROR(INDEX([2]Лист1!$J:$J,AH75),"") -> Sika Egypt For Construction Chemicals | U75: =IFERROR(INDEX([2]Лист1!$K:$K,AH75),"") -> Предложение SikaEgypt от 16.02.2022 | V75: =IFERROR(INDEX([2]Лист1!$E:$E,AI75),"") | W75: =IFERROR(INDEX([2]Лист1!$I:$I,AI75),"") | X75: =IFERROR(INDEX([2]Лист1!$V:$V,AI75),"") | Y75: =IFERROR(INDEX([2]Лист1!$L:$L,AI75),"") | Z75: =IFERROR(INDEX([2]Лист1!$J:$J,AI75),"") | AA75: =IFERROR(INDEX([2]Лист1!$K:$K,AI75),"") | AB75: =IFERROR(INDEX([2]Лист1!$E:$E,AJ75),"") | AC75: =IFERROR(INDEX([2]Лист1!$I:$I,AJ75),"") | AD75: =IFERROR(INDEX([2]Лист1!$V:$V,AJ75),"") | AE75: =IFERROR(INDEX([2]Лист1!$L:$L,AJ75),"") | AF75: =IFERROR(INDEX([2]Лист1!$J:$J,AJ75),"") | AG75: =IFERROR(INDEX([2]Лист1!$K:$K,AJ75),"") | AH75: =MATCH(L75,[2]Лист1!$A:$A,0) -> 3792 | AI75: =MATCH(M75,[2]Лист1!$A:$A,0) -> #N/A | AJ75: =MATCH(N75,[2]Лист1!$A:$A,0) -> #N/A
A76: 1 | B76: ЛСР-03-05-202ТМ | C76: 3 | E76: ТЦ_18.1.06.04_76_7610060282_05.05.22_02 / КА п. 10 / ООО "Актан" № 955 | F76: Клапан запорный (по типу А.КШ.Р.125.25.02.01), DN 125; Pmax=0.6MPag; Tmax=35 °С; Раб. среда: Обессоленная вода; Способ управления: Ручной привод; Тип присоединения: Фланцевый; Класс безопасности 4Н; материал - нж; с комплектом ответных фланцев под приварку с прокладками и крепежом_Кран шаровой А.КШ.Р.125.25.02.01 | G76: шт. | H76: 1 | I76: 207437.98 | J76: =H76*I76 -> 207437.98 | K76: =J76/SUM($J$2:$J$1590) -> 0.0016244496 | L76: =IFERROR(INDEX([1]мтр!G:G,MATCH($F76,[1]мтр!$C:$C,0)),"") | M76: =IFERROR(INDEX([1]мтр!H:H,MATCH($F76,[1]мтр!$C:$C,0)),"") | N76: =IFERROR(INDEX([1]мтр!I:I,MATCH($F76,[1]мтр!$C:$C,0)),"") | O76: =IFERROR(AVERAGE(R76,X76,AD76),"") | P76: =IFERROR(INDEX([2]Лист1!$E:$E,AH76),"") | Q76: =IFERROR(INDEX([2]Лист1!$I:$I,AH76),"") | R76: =IFERROR(INDEX([2]Лист1!$V:$V,AH76),"") | S76: =IFERROR(INDEX([2]Лист1!$L:$L,AH76),"") | T76: =IFERROR(INDEX([2]Лист1!$J:$J,AH76),"") | U76: =IFERROR(INDEX([2]Лист1!$K:$K,AH76),"") | V76: =IFERROR(INDEX([2]Лист1!$E:$E,AI76),"") | W76: =IFERROR(INDEX([2]Лист1!$I:$I,AI76),"") | X76: =IFERROR(INDEX([2]Лист1!$V:$V,AI76),"") | Y76: =IFERROR(INDEX([2]Лист1!$L:$L,AI76),"") | Z76: =IFERROR(INDEX([2]Лист1!$J:$J,AI76),"") | AA76: =IFERROR(INDEX([2]Лист1!$K:$K,AI76),"") | AB76: =IFERROR(INDEX([2]Лист1!$E:$E,AJ76),"") | AC76: =IFERROR(INDEX([2]Лист1!$I:$I,AJ76),"") | AD76: =IFERROR(INDEX([2]Лист1!$V:$V,AJ76),"") | AE76: =IFERROR(INDEX([2]Лист1!$L:$L,AJ76),"") | AF76: =IFERROR(INDEX([2]Лист1!$J:$J,AJ76),"") | AG76: =IFERROR(INDEX([2]Лист1!$K:$K,AJ76),"") | AH76: =MATCH(L76,[2]Лист1!$A:$A,0) -> #N/A | AI76: =MATCH(M76,[2]Лист1!$A:$A,0) -> #N/A | AJ76: =MATCH(N76,[2]Лист1!$A:$A,0) -> #N/A
A77: 1 | B77: ЛСР-03-05-206ТМ | C77: 3 | E77: 19.1.01.04-0062 | F77: Воздуховоды из тонколистовой коррозионно-стойкой стали толщиной: 2,0 мм, периметром более 1000 мм__Короб S= 540х1490 ((540х2+1490*2)/1000х100)= 406 м2 | G77: м2 | H77: 406 | I77: 505.4 | J77: =H77*I77 -> 205192.4 | K77: =J77/SUM($J$2:$J$1590) -> 0.0016068644 | L77: =IFERROR(INDEX([1]мтр!G:G,MATCH($F77,[1]мтр!$C:$C,0)),"") | M77: =IFERROR(INDEX([1]мтр!H:H,MATCH($F77,[1]мтр!$C:$C,0)),"") | N77: =IFERROR(INDEX([1]мтр!I:I,MATCH($F77,[1]мтр!$C:$C,0)),"") | O77: =IFERROR(AVERAGE(R77,X77,AD77),"") | P77: =IFERROR(INDEX([2]Лист1!$E:$E,AH77),"") | Q77: =IFERROR(INDEX([2]Лист1!$I:$I,AH77),"") | R77: =IFERROR(INDEX([2]Лист1!$V:$V,AH77),"") | S77: =IFERROR(INDEX([2]Лист1!$L:$L,AH77),"") | T77: =IFERROR(INDEX([2]Лист1!$J:$J,AH77),"") | U77: =IFERROR(INDEX([2]Лист1!$K:$K,AH77),"") | V77: =IFERROR(INDEX([2]Лист1!$E:$E,AI77),"") | W77: =IFERROR(INDEX([2]Лист1!$I:$I,AI77),"") | X77: =IFERROR(INDEX([2]Лист1!$V:$V,AI77),"") | Y77: =IFERROR(INDEX([2]Лист1!$L:$L,AI77),"") | Z77: =IFERROR(INDEX([2]Лист1!$J:$J,AI77),"") | AA77: =IFERROR(INDEX([2]Лист1!$K:$K,AI77),"") | AB77: =IFERROR(INDEX([2]Лист1!$E:$E,AJ77),"") | AC77: =IFERROR(INDEX([2]Лист1!$I:$I,AJ77),"") | AD77: =IFERROR(INDEX([2]Лист1!$V:$V,AJ77),"") | AE77: =IFERROR(INDEX([2]Лист1!$L:$L,AJ77),"") | AF77: =IFERROR(INDEX([2]Лист1!$J:$J,AJ77),"") | AG77: =IFERROR(INDEX([2]Лист1!$K:$K,AJ77),"") | AH77: =MATCH(L77,[2]Лист1!$A:$A,0) -> #N/A | AI77: =MATCH(M77,[2]Лист1!$A:$A,0) -> #N/A | AJ77: =MATCH(N77,[2]Лист1!$A:$A,0) -> #N/A
A78: 1 | B78: ЛСР-03-05-102С | C78: 3 | E78: 07.2.06.06-0011 | F78: Конструкции навесной фасадной системы с воздушным зазором_Направляющие системы вентилируемого фасада толщиной 60 мм | G78: м2 | H78: 771.2 | I78: 261.21 | J78: =H78*I78 -> 201445.15 | K78: =J78/SUM($J$2:$J$1590) -> 0.0015775197 | L78: =IFERROR(INDEX([1]мтр!G:G,MATCH($F78,[1]мтр!$C:$C,0)),"") -> 3731 | M78: =IFERROR(INDEX([1]мтр!H:H,MATCH($F78,[1]мтр!$C:$C,0)),"") -> 0 | N78: =IFERROR(INDEX([1]мтр!I:I,MATCH($F78,[1]мтр!$C:$C,0)),"") -> 0 | O78: =IFERROR(AVERAGE(R78,X78,AD78),"") -> 490.53113 | P78: =IFERROR(INDEX([2]Лист1!$E:$E,AH78),"") -> Каркас Hilti для навесной фасадной системы 1800x600mm Liberta. Транспорт экспертно 5% | Q78: =IFERROR(INDEX([2]Лист1!$I:$I,AH78),"") -> м2 | R78: =IFERROR(INDEX([2]Лист1!$V:$V,AH78),"") -> 490.53113 | S78: =IFERROR(INDEX([2]Лист1!$L:$L,AH78),"") -> 44162 | T78: =IFERROR(INDEX([2]Лист1!$J:$J,AH78),"") -> Hilti | U78: =IFERROR(INDEX([2]Лист1!$K:$K,AH78),"") -> Письмо дилера фасадных систем Ruukka для Пакша | V78: =IFERROR(INDEX([2]Лист1!$E:$E,AI78),"") | W78: =IFERROR(INDEX([2]Лист1!$I:$I,AI78),"") | X78: =IFERROR(INDEX([2]Лист1!$V:$V,AI78),"") | Y78: =IFERROR(INDEX([2]Лист1!$L:$L,AI78),"") | Z78: =IFERROR(INDEX([2]Лист1!$J:$J,AI78),"") | AA78: =IFERROR(INDEX([2]Лист1!$K:$K,AI78),"") | AB78: =IFERROR(INDEX([2]Лист1!$E:$E,AJ78),"") | AC78: =IFERROR(INDEX([2]Лист1!$I:$I,AJ78),"") | AD78: =IFERROR(INDEX([2]Лист1!$V:$V,AJ78),"") | AE78: =IFERROR(INDEX([2]Лист1!$L:$L,AJ78),"") | AF78: =IFERROR(INDEX([2]Лист1!$J:$J,AJ78),"") | AG78: =IFERROR(INDEX([2]Лист1!$K:$K,AJ78),"") | AH78: =MATCH(L78,[2]Лист1!$A:$A,0) -> 2623 | AI78: =MATCH(M78,[2]Лист1!$A:$A,0) -> #N/A | AJ78: =MATCH(N78,[2]Лист1!$A:$A,0) -> #N/A
A79: 4 | B79: ЛСР-03-09-201ТМ | C79: 3 | E79: ТЦ_23.7.01.02_31_3123315768_20.05.2022_02/ КА п.1/ ООО "Белэнергомаш-БЗЭМ" №006-00073 | F79: Трубопроводы низкого давления из углеродистой стали, 4 класса безопасности, Ду < 80мм _ DN65, DN50, DN20, DN15 | G79: т | H79: 0.541 | I79: 364063.42 | J79: =H79*I79 -> 196958.31 | K79: =J79/SUM($J$2:$J$1590) -> 0.0015423832 | L79: =IFERROR(INDEX([1]мтр!G:G,MATCH($F79,[1]мтр!$C:$C,0)),"") -> 4859 | M79: =IFERROR(INDEX([1]мтр!H:H,MATCH($F79,[1]мтр!$C:$C,0)),"") -> 0 | N79: =IFERROR(INDEX([1]мтр!I:I,MATCH($F79,[1]мтр!$C:$C,0)),"") -> 0 | O79: =IFERROR(AVERAGE(R79,X79,AD79),"") -> 479788.26 | P79: =IFERROR(INDEX([2]Лист1!$E:$E,AH79),"") -> Трубопроводы низкого давления из углеродистой стали зданий UJA, UKD. Объём: 4526466 руб. / 2939,52 кг = 1540 RUB/кг. Транспорт 5800 USD (Договор ЕОС-закупки №629007, №7720/220816 от 07.09.2022, АСЭ_Рускон) /40DV контейнер 25 т, класс груза - 2, загрузка 85%. | Q79: =IFERROR(INDEX([2]Лист1!$I:$I,AH79),"") -> т | R79: =IFERROR(INDEX([2]Лист1!$V:$V,AH79),"") -> 479788.26 | S79: =IFERROR(INDEX([2]Лист1!$L:$L,AH79),"") -> 44753 | T79: =IFERROR(INDEX([2]Лист1!$J:$J,AH79),"") -> Белэнергомаш-БЗЭМ | U79: =IFERROR(INDEX([2]Лист1!$K:$K,AH79),"") -> Поставка трубопроводов по лоту 19677-248 Куд3;4. НМЦ от 11.07.2022, рассчитанная на основании п.1 раздела 3 главы 3 (приложения №8 к ЕОСЗ). | V79: =IFERROR(INDEX([2]Лист1!$E:$E,AI79),"") | W79: =IFERROR(INDEX([2]Лист1!$I:$I,AI79),"") | X79: =IFERROR(INDEX([2]Лист1!$V:$V,AI79),"") | Y79: =IFERROR(INDEX([2]Лист1!$L:$L,AI79),"") | Z79: =IFERROR(INDEX([2]Лист1!$J:$J,AI79),"") | AA79: =IFERROR(INDEX([2]Лист1!$K:$K,AI79),"") | AB79: =IFERROR(INDEX([2]Лист1!$E:$E,AJ79),"") | AC79: =IFERROR(INDEX([2]Лист1!$I:$I,AJ79),"") | AD79: =IFERROR(INDEX([2]Лист1!$V:$V,AJ79),"") | AE79: =IFERROR(INDEX([2]Лист1!$L:$L,AJ79),"") | AF79: =IFERROR(INDEX([2]Лист1!$J:$J,AJ79),"") | AG79: =IFERROR(INDEX([2]Лист1!$K:$K,AJ79),"") | AH79: =MATCH(L79,[2]Лист1!$A:$A,0) -> 4796 | AI79: =MATCH(M79,[2]Лист1!$A:$A,0) -> #N/A | AJ79: =MATCH(N79,[2]Лист1!$A:$A,0) -> #N/A
A80: 1 | B80: ЛСР-03-05-701АК | C80: 3 | E80: ТЦ_20.5.02.02_77_7702341124_01.06.2022_02 | F80: Коробка клеммная Klippon STB-48-SS-S. Weidmuller 48 клемм 4/N; III; QNC | G80: шт. | H80: 16 | I80: 12197.39 | J80: =H80*I80 -> 195158.24 | K80: =J80/SUM($J$2:$J$1590) -> 0.0015282868 | L80: =IFERROR(INDEX([1]мтр!G:G,MATCH($F80,[1]мтр!$C:$C,0)),"") -> 5049 | M80: =IFERROR(INDEX([1]мтр!H:H,MATCH($F80,[1]мтр!$C:$C,0)),"") -> 0 | N80: =IFERROR(INDEX([1]мтр!I:I,MATCH($F80,[1]мтр!$C:$C,0)),"") -> 0 | O80: =IFERROR(AVERAGE(R80,X80,AD80),"") -> 48137.667 | P80: =IFERROR(INDEX([2]Лист1!$E:$E,AH80),"") -> Коробка Klippon STB-48-SS-S . Транспорт экcпертно 5% | Q80: =IFERROR(INDEX([2]Лист1!$I:$I,AH80),"") -> шт. | R80: =IFERROR(INDEX([2]Лист1!$V:$V,AH80),"") -> 48137.667 | S80: =IFERROR(INDEX([2]Лист1!$L:$L,AH80),"") -> 44441 | T80: =IFERROR(INDEX([2]Лист1!$J:$J,AH80),"") -> Weidmuller | U80: =IFERROR(INDEX([2]Лист1!$K:$K,AH80),"") -> Письмо от А. Стрельцова, рук. "Атомное направление" | V80: =IFERROR(INDEX([2]Лист1!$E:$E,AI80),"") | W80: =IFERROR(INDEX([2]Лист1!$I:$I,AI80),"") | X80: =IFERROR(INDEX([2]Лист1!$V:$V,AI80),"") | Y80: =IFERROR(INDEX([2]Лист1!$L:$L,AI80),"") | Z80: =IFERROR(INDEX([2]Лист1!$J:$J,AI80),"") | AA80: =IFERROR(INDEX([2]Лист1!$K:$K,AI80),"") | AB80: =IFERROR(INDEX([2]Лист1!$E:$E,AJ80),"") | AC80: =IFERROR(INDEX([2]Лист1!$I:$I,AJ80),"") | AD80: =IFERROR(INDEX([2]Лист1!$V:$V,AJ80),"") | AE80: =IFERROR(INDEX([2]Лист1!$L:$L,AJ80),"") | AF80: =IFERROR(INDEX([2]Лист1!$J:$J,AJ80),"") | AG80: =IFERROR(INDEX([2]Лист1!$K:$K,AJ80),"") | AH80: =MATCH(L80,[2]Лист1!$A:$A,0) -> 2840 | AI80: =MATCH(M80,[2]Лист1!$A:$A,0) -> #N/A | AJ80: =MATCH(N80,[2]Лист1!$A:$A,0) -> #N/A
A81: 1 | B81: ЛСР-03-05-203ТМ | C81: 3 | E81: ТЦ_18.1.06.00_50_5503095632_05.07.2022_02 /КА п.49/ ЗАО "Сибгазстройдеталь" №897 | F81: Запорная арматура По типу 1054-40-0 DN 40; pmax=1.94 MPag; tmax=109 °С / °C; Раб. Среда:Вода питательная ПРК; Способ управления: Ручной привод; Тип присоединения: Под приварку, Кл.4Н, угл.ст. | G81: шт. | H81: 8 | I81: 23300.53 | J81: =H81*I81 -> 186404.24 | K81: =J81/SUM($J$2:$J$1590) -> 0.0014597341 | L81: 7321 | M81: =IFERROR(INDEX([1]мтр!H:H,MATCH($F81,[1]мтр!$C:$C,0)),"") | N81: =IFERROR(INDEX([1]мтр!I:I,MATCH($F81,[1]мтр!$C:$C,0)),"") | O81: =IFERROR(AVERAGE(R81,X81,AD81),"") -> 0 | P81: =IFERROR(INDEX([2]Лист1!$E:$E,AH81),"") -> 0 | Q81: =IFERROR(INDEX([2]Лист1!$I:$I,AH81),"") -> 0 | R81: =IFERROR(INDEX([2]Лист1!$V:$V,AH81),"") -> 0 | S81: =IFERROR(INDEX([2]Лист1!$L:$L,AH81),"") -> 0 | T81: =IFERROR(INDEX([2]Лист1!$J:$J,AH81),"") -> 0 | U81: =IFERROR(INDEX([2]Лист1!$K:$K,AH81),"") -> 0 | V81: =IFERROR(INDEX([2]Лист1!$E:$E,AI81),"") | W81: =IFERROR(INDEX([2]Лист1!$I:$I,AI81),"") | X81: =IFERROR(INDEX([2]Лист1!$V:$V,AI81),"") | Y81: =IFERROR(INDEX([2]Лист1!$L:$L,AI81),"") | Z81: =IFERROR(INDEX([2]Лист1!$J:$J,AI81),"") | AA81: =IFERROR(INDEX([2]Лист1!$K:$K,AI81),"") | AB81: =IFERROR(INDEX([2]Лист1!$E:$E,AJ81),"") | AC81: =IFERROR(INDEX([2]Лист1!$I:$I,AJ81),"") | AD81: =IFERROR(INDEX([2]Лист1!$V:$V,AJ81),"") | AE81: =IFERROR(INDEX([2]Лист1!$L:$L,AJ81),"") | AF81: =IFERROR(INDEX([2]Лист1!$J:$J,AJ81),"") | AG81: =IFERROR(INDEX([2]Лист1!$K:$K,AJ81),"") | AH81: =MATCH(L81,[2]Лист1!$A:$A,0) -> 6387 | AI81: =MATCH(M81,[2]Лист1!$A:$A,0) -> #N/A | AJ81: =MATCH(N81,[2]Лист1!$A:$A,0) -> #N/A
A82: 1 | B82: ЛСР-03-05-701АК | C82: 3 | E82: ТЦ_20.5.02.02_77_7702341124_01.06.2022_02 | F82: Коробка клеммная Klippon STB-48-SS-S. Weidmuller 48 клемм 4; III; QA2 | G82: шт. | H82: 15 | I82: 12197.39 | J82: =H82*I82 -> 182960.85 | K82: =J82/SUM($J$2:$J$1590) -> 0.0014327689 | L82: =IFERROR(INDEX([1]мтр!G:G,MATCH($F82,[1]мтр!$C:$C,0)),"") -> 5049 | M82: =IFERROR(INDEX([1]мтр!H:H,MATCH($F82,[1]мтр!$C:$C,0)),"") -> 0 | N82: =IFERROR(INDEX([1]мтр!I:I,MATCH($F82,[1]мтр!$C:$C,0)),"") -> 0 | O82: =IFERROR(AVERAGE(R82,X82,AD82),"") -> 48137.667 | P82: =IFERROR(INDEX([2]Лист1!$E:$E,AH82),"") -> Коробка Klippon STB-48-SS-S . Транспорт экcпертно 5% | Q82: =IFERROR(INDEX([2]Лист1!$I:$I,AH82),"") -> шт. | R82: =IFERROR(INDEX([2]Лист1!$V:$V,AH82),"") -> 48137.667 | S82: =IFERROR(INDEX([2]Лист1!$L:$L,AH82),"") -> 44441 | T82: =IFERROR(INDEX([2]Лист1!$J:$J,AH82),"") -> Weidmuller | U82: =IFERROR(INDEX([2]Лист1!$K:$K,AH82),"") -> Письмо от А. Стрельцова, рук. "Атомное направление" | V82: =IFERROR(INDEX([2]Лист1!$E:$E,AI82),"") | W82: =IFERROR(INDEX([2]Лист1!$I:$I,AI82),"") | X82: =IFERROR(INDEX([2]Лист1!$V:$V,AI82),"") | Y82: =IFERROR(INDEX([2]Лист1!$L:$L,AI82),"") | Z82: =IFERROR(INDEX([2]Лист1!$J:$J,AI82),"") | AA82: =IFERROR(INDEX([2]Лист1!$K:$K,AI82),"") | AB82: =IFERROR(INDEX([2]Лист1!$E:$E,AJ82),"") | AC82: =IFERROR(INDEX([2]Лист1!$I:$I,AJ82),"") | AD82: =IFERROR(INDEX([2]Лист1!$V:$V,AJ82),"") | AE82: =IFERROR(INDEX([2]Лист1!$L:$L,AJ82),"") | AF82: =IFERROR(INDEX([2]Лист1!$J:$J,AJ82),"") | AG82: =IFERROR(INDEX([2]Лист1!$K:$K,AJ82),"") | AH82: =MATCH(L82,[2]Лист1!$A:$A,0) -> 2840 | AI82: =MATCH(M82,[2]Лист1!$A:$A,0) -> #N/A | AJ82: =MATCH(N82,[2]Лист1!$A:$A,0) -> #N/A
A83: 1 | B83: ЛСР-03-05-602Э | C83: 3 | E83: 10.3.02.03-0011 | F83: Припои оловянно-свинцовые бессурьмянистые, марка ПОС30 | G83: т | H83: 2.66192 | I83: 68050 | J83: =H83*I83 -> 181143.66 | K83: =J83/SUM($J$2:$J$1590) -> 0.0014185384 | L83: =IFERROR(INDEX([1]мтр!G:G,MATCH($F83,[1]мтр!$C:$C,0)),"") -> 6982 | M83: =IFERROR(INDEX([1]мтр!H:H,MATCH($F83,[1]мтр!$C:$C,0)),"") -> 0 | N83: =IFERROR(INDEX([1]мтр!I:I,MATCH($F83,[1]мтр!$C:$C,0)),"") -> 0 | O83: =IFERROR(AVERAGE(R83,X83,AD83),"") -> 186714.48 | P83: =IFERROR(INDEX([2]Лист1!$E:$E,AH83),"") -> Припои оловянно-свинцовые бессурьмянистые марки ПОС30 | Q83: =IFERROR(INDEX([2]Лист1!$I:$I,AH83),"") -> т | R83: =IFERROR(INDEX([2]Лист1!$V:$V,AH83),"") -> 186714.48 | S83: =IFERROR(INDEX([2]Лист1!$L:$L,AH83),"") -> 44602 | T83: =IFERROR(INDEX([2]Лист1!$J:$J,AH83),"") -> N/A | U83: =IFERROR(INDEX([2]Лист1!$K:$K,AH83),"") -> ТКП ОЭС от 10.02.2022 для лота 6416 | V83: =IFERROR(INDEX([2]Лист1!$E:$E,AI83),"") | W83: =IFERROR(INDEX([2]Лист1!$I:$I,AI83),"") | X83: =IFERROR(INDEX([2]Лист1!$V:$V,AI83),"") | Y83: =IFERROR(INDEX([2]Лист1!$L:$L,AI83),"") | Z83: =IFERROR(INDEX([2]Лист1!$J:$J,AI83),"") | AA83: =IFERROR(INDEX([2]Лист1!$K:$K,AI83),"") | AB83: =IFERROR(INDEX([2]Лист1!$E:$E,AJ83),"") | AC83: =IFERROR(INDEX([2]Лист1!$I:$I,AJ83),"") | AD83: =IFERROR(INDEX([2]Лист1!$V:$V,AJ83),"") | AE83: =IFERROR(INDEX([2]Лист1!$L:$L,AJ83),"") | AF83: =IFERROR(INDEX([2]Лист1!$J:$J,AJ83),"") | AG83: =IFERROR(INDEX([2]Лист1!$K:$K,AJ83),"") | AH83: =MATCH(L83,[2]Лист1!$A:$A,0) -> 6048 | AI83: =MATCH(M83,[2]Лист1!$A:$A,0) -> #N/A | AJ83: =MATCH(N83,[2]Лист1!$A:$A,0) -> #N/A
A84: 1 | B84: ЛСР-03-05-703ПС | C84: 3 | E84: ТЦ_20.2.03.04_50_7717029550_02.06.2022_01 | F84: Проходка кабельная универсальная EI90. Диаметр 32 мм, огнестойкость не менее 90 мин. 4; III; QNC | G84: ШТ | H84: 200 | I84: 880.51 | J84: =H84*I84 -> 176102 | K84: =J84/SUM($J$2:$J$1590) -> 0.0013790571 | L84: =IFERROR(INDEX([1]мтр!G:G,MATCH($F84,[1]мтр!$C:$C,0)),"") | M84: =IFERROR(INDEX([1]мтр!H:H,MATCH($F84,[1]мтр!$C:$C,0)),"") | N84: =IFERROR(INDEX([1]мтр!I:I,MATCH($F84,[1]мтр!$C:$C,0)),"") | O84: =IFERROR(AVERAGE(R84,X84,AD84),"") | P84: =IFERROR(INDEX([2]Лист1!$E:$E,AH84),"") | Q84: =IFERROR(INDEX([2]Лист1!$I:$I,AH84),"") | R84: =IFERROR(INDEX([2]Лист1!$V:$V,AH84),"") | S84: =IFERROR(INDEX([2]Лист1!$L:$L,AH84),"") | T84: =IFERROR(INDEX([2]Лист1!$J:$J,AH84),"") | U84: =IFERROR(INDEX([2]Лист1!$K:$K,AH84),"") | V84: =IFERROR(INDEX([2]Лист1!$E:$E,AI84),"") | W84: =IFERROR(INDEX([2]Лист1!$I:$I,AI84),"") | X84: =IFERROR(INDEX([2]Лист1!$V:$V,AI84),"") | Y84: =IFERROR(INDEX([2]Лист1!$L:$L,AI84),"") | Z84: =IFERROR(INDEX([2]Лист1!$J:$J,AI84),"") | AA84: =IFERROR(INDEX([2]Лист1!$K:$K,AI84),"") | AB84: =IFERROR(INDEX([2]Лист1!$E:$E,AJ84),"") | AC84: =IFERROR(INDEX([2]Лист1!$I:$I,AJ84),"") | AD84: =IFERROR(INDEX([2]Лист1!$V:$V,AJ84),"") | AE84: =IFERROR(INDEX([2]Лист1!$L:$L,AJ84),"") | AF84: =IFERROR(INDEX([2]Лист1!$J:$J,AJ84),"") | AG84: =IFERROR(INDEX([2]Лист1!$K:$K,AJ84),"") | AH84: =MATCH(L84,[2]Лист1!$A:$A,0) -> #N/A | AI84: =MATCH(M84,[2]Лист1!$A:$A,0) -> #N/A | AJ84: =MATCH(N84,[2]Лист1!$A:$A,0) -> #N/A
A85: 4 | B85: ЛСР-03-09-201ТМ | C85: 3 | E85: ТЦ_23.7.01.02_31_3123315768_20.05.2022_02/ КА п.2/ ООО "Белэнергомаш-БЗЭМ" №006-00073 | F85: Трубопроводы низкого давления из углеродистой стали, 4 класса безопасности, Ду > 80мм_DN150, DN125, DN100, DN80 | G85: т | H85: 0.819 | I85: 211499.32 | J85: =H85*I85 -> 173217.94 | K85: =J85/SUM($J$2:$J$1590) -> 0.001356472 | L85: =IFERROR(INDEX([1]мтр!G:G,MATCH($F85,[1]мтр!$C:$C,0)),"") -> 4859 | M85: =IFERROR(INDEX([1]мтр!H:H,MATCH($F85,[1]мтр!$C:$C,0)),"") -> 0 | N85: =IFERROR(INDEX([1]мтр!I:I,MATCH($F85,[1]мтр!$C:$C,0)),"") -> 0 | O85: =IFERROR(AVERAGE(R85,X85,AD85),"") -> 479788.26 | P85: =IFERROR(INDEX([2]Лист1!$E:$E,AH85),"") -> Трубопроводы низкого давления из углеродистой стали зданий UJA, UKD. Объём: 4526466 руб. / 2939,52 кг = 1540 RUB/кг. Транспорт 5800 USD (Договор ЕОС-закупки №629007, №7720/220816 от 07.09.2022, АСЭ_Рускон) /40DV контейнер 25 т, класс груза - 2, загрузка 85%. | Q85: =IFERROR(INDEX([2]Лист1!$I:$I,AH85),"") -> т | R85: =IFERROR(INDEX([2]Лист1!$V:$V,AH85),"") -> 479788.26 | S85: =IFERROR(INDEX([2]Лист1!$L:$L,AH85),"") -> 44753 | T85: =IFERROR(INDEX([2]Лист1!$J:$J,AH85),"") -> Белэнергомаш-БЗЭМ | U85: =IFERROR(INDEX([2]Лист1!$K:$K,AH85),"") -> Поставка трубопроводов по лоту 19677-248 Куд3;4. НМЦ от 11.07.2022, рассчитанная на основании п.1 раздела 3 главы 3 (приложения №8 к ЕОСЗ). | V85: =IFERROR(INDEX([2]Лист1!$E:$E,AI85),"") | W85: =IFERROR(INDEX([2]Лист1!$I:$I,AI85),"") | X85: =IFERROR(INDEX([2]Лист1!$V:$V,AI85),"") | Y85: =IFERROR(INDEX([2]Лист1!$L:$L,AI85),"") | Z85: =IFERROR(INDEX([2]Лист1!$J:$J,AI85),"") | AA85: =IFERROR(INDEX([2]Лист1!$K:$K,AI85),"") | AB85: =IFERROR(INDEX([2]Лист1!$E:$E,AJ85),"") | AC85: =IFERROR(INDEX([2]Лист1!$I:$I,AJ85),"") | AD85: =IFERROR(INDEX([2]Лист1!$V:$V,AJ85),"") | AE85: =IFERROR(INDEX([2]Лист1!$L:$L,AJ85),"") | AF85: =IFERROR(INDEX([2]Лист1!$J:$J,AJ85),"") | AG85: =IFERROR(INDEX([2]Лист1!$K:$K,AJ85),"") | AH85: =MATCH(L85,[2]Лист1!$A:$A,0) -> 4796 | AI85: =MATCH(M85,[2]Лист1!$A:$A,0) -> #N/A | AJ85: =MATCH(N85,[2]Лист1!$A:$A,0) -> #N/A
A86: 1 | B86: ЛСР-03-05-203ТМ | C86: 3 | E86: ТЦ_18.1.05.00_50_5503095632_05.07.2022_02 /КА п.31/ ЗАО "Сибгазстройдеталь" №897 | F86: Арматура предохранительная По типу 16с-7нж pmax=0.88 MPag; tmax=178 °С / °C; Раб. среда: Пар насыщенный; Способ управления: Привод пружинный ; Тип присоединения : Фланцевый DN вход = 80; DN выход: 125 Кл 4Н, угл.ст._Клапан предохранительный 17с6нж Ду80 Ру16 СППК4Р | G86: шт. | H86: 2 | I86: 85459.02 | J86: =H86*I86 -> 170918.04 | K86: =J86/SUM($J$2:$J$1590) -> 0.0013384615 | L86: =IFERROR(INDEX([1]мтр!G:G,MATCH($F86,[1]мтр!$C:$C,0)),"") | M86: =IFERROR(INDEX([1]мтр!H:H,MATCH($F86,[1]мтр!$C:$C,0)),"") | N86: =IFERROR(INDEX([1]мтр!I:I,MATCH($F86,[1]мтр!$C:$C,0)),"") | O86: =IFERROR(AVERAGE(R86,X86,AD86),"") | P86: =IFERROR(INDEX([2]Лист1!$E:$E,AH86),"") | Q86: =IFERROR(INDEX([2]Лист1!$I:$I,AH86),"") | R86: =IFERROR(INDEX([2]Лист1!$V:$V,AH86),"") | S86: =IFERROR(INDEX([2]Лист1!$L:$L,AH86),"") | T86: =IFERROR(INDEX([2]Лист1!$J:$J,AH86),"") | U86: =IFERROR(INDEX([2]Лист1!$K:$K,AH86),"") | V86: =IFERROR(INDEX([2]Лист1!$E:$E,AI86),"") | W86: =IFERROR(INDEX([2]Лист1!$I:$I,AI86),"") | X86: =IFERROR(INDEX([2]Лист1!$V:$V,AI86),"") | Y86: =IFERROR(INDEX([2]Лист1!$L:$L,AI86),"") | Z86: =IFERROR(INDEX([2]Лист1!$J:$J,AI86),"") | AA86: =IFERROR(INDEX([2]Лист1!$K:$K,AI86),"") | AB86: =IFERROR(INDEX([2]Лист1!$E:$E,AJ86),"") | AC86: =IFERROR(INDEX([2]Лист1!$I:$I,AJ86),"") | AD86: =IFERROR(INDEX([2]Лист1!$V:$V,AJ86),"") | AE86: =IFERROR(INDEX([2]Лист1!$L:$L,AJ86),"") | AF86: =IFERROR(INDEX([2]Лист1!$J:$J,AJ86),"") | AG86: =IFERROR(INDEX([2]Лист1!$K:$K,AJ86),"") | AH86: =MATCH(L86,[2]Лист1!$A:$A,0) -> #N/A | AI86: =MATCH(M86,[2]Лист1!$A:$A,0) -> #N/A | AJ86: =MATCH(N86,[2]Лист1!$A:$A,0) -> #N/A
A87: 1 | B87: ЛСР-03-05-701АК | C87: 3 | E87: ТЦ_18.9.02.02_78_7806152178_30.05.2022_01 | F87: Клапан сильфонный запорный; DN 10; P<2.2 MPa; Присоединительные размеры: 14х2; 4;-; III; QNC; | G87: шт. | H87: 20 | I87: 7991.88 | J87: =H87*I87 -> 159837.6 | K87: =J87/SUM($J$2:$J$1590) -> 0.0012516904 | L87: 7329 | M87: =IFERROR(INDEX([1]мтр!H:H,MATCH($F87,[1]мтр!$C:$C,0)),"") | N87: =IFERROR(INDEX([1]мтр!I:I,MATCH($F87,[1]мтр!$C:$C,0)),"") | O87: =IFERROR(AVERAGE(R87,X87,AD87),"") -> 0 | P87: =IFERROR(INDEX([2]Лист1!$E:$E,AH87),"") -> 0 | Q87: =IFERROR(INDEX([2]Лист1!$I:$I,AH87),"") -> 0 | R87: =IFERROR(INDEX([2]Лист1!$V:$V,AH87),"") -> 0 | S87: =IFERROR(INDEX([2]Лист1!$L:$L,AH87),"") -> 0 | T87: =IFERROR(INDEX([2]Лист1!$J:$J,AH87),"") -> 0 | U87: =IFERROR(INDEX([2]Лист1!$K:$K,AH87),"") -> 0 | V87: =IFERROR(INDEX([2]Лист1!$E:$E,AI87),"") | W87: =IFERROR(INDEX([2]Лист1!$I:$I,AI87),"") | X87: =IFERROR(INDEX([2]Лист1!$V:$V,AI87),"") | Y87: =IFERROR(INDEX([2]Лист1!$L:$L,AI87),"") | Z87: =IFERROR(INDEX([2]Лист1!$J:$J,AI87),"") | AA87: =IFERROR(INDEX([2]Лист1!$K:$K,AI87),"") | AB87: =IFERROR(INDEX([2]Лист1!$E:$E,AJ87),"") | AC87: =IFERROR(INDEX([2]Лист1!$I:$I,AJ87),"") | AD87: =IFERROR(INDEX([2]Лист1!$V:$V,AJ87),"") | AE87: =IFERROR(INDEX([2]Лист1!$L:$L,AJ87),"") | AF87: =IFERROR(INDEX([2]Лист1!$J:$J,AJ87),"") | AG87: =IFERROR(INDEX([2]Лист1!$K:$K,AJ87),"") | AH87: =MATCH(L87,[2]Лист1!$A:$A,0) -> 6395 | AI87: =MATCH(M87,[2]Лист1!$A:$A,0) -> #N/A | AJ87: =MATCH(N87,[2]Лист1!$A:$A,0) -> #N/A
A88: 1 | B88: ЛСР-03-05-701АК | C88: 3 | E88: ТЦ_18.9.02.02_78_7806152178_30.05.2022_01 | F88: Клапан сильфонный запорный; DN 10; P<2.2 MPa; Присоединительные размеры: 14х2; 4;-; III; QNC; | G88: шт. | H88: 20 | I88: 7991.88 | J88: =H88*I88 -> 159837.6 | K88: =J88/SUM($J$2:$J$1590) -> 0.0012516904 | L88: 7329 | M88: =IFERROR(INDEX([1]мтр!H:H,MATCH($F88,[1]мтр!$C:$C,0)),"") | N88: =IFERROR(INDEX([1]мтр!I:I,MATCH($F88,[1]мтр!$C:$C,0)),"") | O88: =IFERROR(AVERAGE(R88,X88,AD88),"") -> 0 | P88: =IFERROR(INDEX([2]Лист1!$E:$E,AH88),"") -> 0 | Q88: =IFERROR(INDEX([2]Лист1!$I:$I,AH88),"") -> 0 | R88: =IFERROR(INDEX([2]Лист1!$V:$V,AH88),"") -> 0 | S88: =IFERROR(INDEX([2]Лист1!$L:$L,AH88),"") -> 0 | T88: =IFERROR(INDEX([2]Лист1!$J:$J,AH88),"") -> 0 | U88: =IFERROR(INDEX([2]Лист1!$K:$K,AH88),"") -> 0 | V88: =IFERROR(INDEX([2]Лист1!$E:$E,AI88),"") | W88: =IFERROR(INDEX([2]Лист1!$I:$I,AI88),"") | X88: =IFERROR(INDEX([2]Лист1!$V:$V,AI88),"") | Y88: =IFERROR(INDEX([2]Лист1!$L:$L,AI88),"") | Z88: =IFERROR(INDEX([2]Лист1!$J:$J,AI88),"") | AA88: =IFERROR(INDEX([2]Лист1!$K:$K,AI88),"") | AB88: =IFERROR(INDEX([2]Лист1!$E:$E,AJ88),"") | AC88: =IFERROR(INDEX([2]Лист1!$I:$I,AJ88),"") | AD88: =IFERROR(INDEX([2]Лист1!$V:$V,AJ88),"") | AE88: =IFERROR(INDEX([2]Лист1!$L:$L,AJ88),"") | AF88: =IFERROR(INDEX([2]Лист1!$J:$J,AJ88),"") | AG88: =IFERROR(INDEX([2]Лист1!$K:$K,AJ88),"") | AH88: =MATCH(L88,[2]Лист1!$A:$A,0) -> 6395 | AI88: =MATCH(M88,[2]Лист1!$A:$A,0) -> #N/A | AJ88: =MATCH(N88,[2]Лист1!$A:$A,0) -> #N/A
A89: 1 | B89: ЛСР-03-05-203ТМ | C89: 3 | E89: ТЦ_18.1.06.00_50_5503095632_05.07.2022_02 /КА п.42/ ЗАО "Сибгазстройдеталь" №897 | F89: Запорная арматура По типу 2с-25-1Н DN 150; pmax=0.12 MPag; tmax=109 °С / °C; Раб. Среда: Вода питательная ПРК; Способ управления: Ручной привод; Тип присоединения: Под приварку, Кл. 4Н, угл.ст. | G89: шт. | H89: 1 | I89: 151166.68 | J89: =H89*I89 -> 151166.68 | K89: =J89/SUM($J$2:$J$1590) -> 0.0011837883 | L89: 7315 | M89: =IFERROR(INDEX([1]мтр!H:H,MATCH($F89,[1]мтр!$C:$C,0)),"") | N89: =IFERROR(INDEX([1]мтр!I:I,MATCH($F89,[1]мтр!$C:$C,0)),"") | O89: =IFERROR(AVERAGE(R89,X89,AD89),"") -> 0 | P89: =IFERROR(INDEX([2]Лист1!$E:$E,AH89),"") -> 0 | Q89: =IFERROR(INDEX([2]Лист1!$I:$I,AH89),"") -> 0 | R89: =IFERROR(INDEX([2]Лист1!$V:$V,AH89),"") -> 0 | S89: =IFERROR(INDEX([2]Лист1!$L:$L,AH89),"") -> 0 | T89: =IFERROR(INDEX([2]Лист1!$J:$J,AH89),"") -> 0 | U89: =IFERROR(INDEX([2]Лист1!$K:$K,AH89),"") -> 0 | V89: =IFERROR(INDEX([2]Лист1!$E:$E,AI89),"") | W89: =IFERROR(INDEX([2]Лист1!$I:$I,AI89),"") | X89: =IFERROR(INDEX([2]Лист1!$V:$V,AI89),"") | Y89: =IFERROR(INDEX([2]Лист1!$L:$L,AI89),"") | Z89: =IFERROR(INDEX([2]Лист1!$J:$J,AI89),"") | AA89: =IFERROR(INDEX([2]Лист1!$K:$K,AI89),"") | AB89: =IFERROR(INDEX([2]Лист1!$E:$E,AJ89),"") | AC89: =IFERROR(INDEX([2]Лист1!$I:$I,AJ89),"") | AD89: =IFERROR(INDEX([2]Лист1!$V:$V,AJ89),"") | AE89: =IFERROR(INDEX([2]Лист1!$L:$L,AJ89),"") | AF89: =IFERROR(INDEX([2]Лист1!$J:$J,AJ89),"") | AG89: =IFERROR(INDEX([2]Лист1!$K:$K,AJ89),"") | AH89: =MATCH(L89,[2]Лист1!$A:$A,0) -> 6381 | AI89: =MATCH(M89,[2]Лист1!$A:$A,0) -> #N/A | AJ89: =MATCH(N89,[2]Лист1!$A:$A,0) -> #N/A
A90: 1 | B90: ЛСР-03-05-203ТМ | C90: 3 | E90: ТЦ_18.1.06.00_50_5503095632_05.07.2022_02 /КА п.47/ ЗАО "Сибгазстройдеталь" №897 | F90: Запорная арматура По типу 2с-25-1Н DN 150; pmax=0.88 MPag; tmax=178 °С / °C; Раб. среда:Пар насыщенный; Способ управления: Ручной привод; Тип присоединения: Под приварку Кл.4Н, угл.ст. | G90: шт. | H90: 1 | I90: 151166.68 | J90: =H90*I90 -> 151166.68 | K90: =J90/SUM($J$2:$J$1590) -> 0.0011837883 | L90: 7316 | M90: =IFERROR(INDEX([1]мтр!H:H,MATCH($F90,[1]мтр!$C:$C,0)),"") | N90: =IFERROR(INDEX([1]мтр!I:I,MATCH($F90,[1]мтр!$C:$C,0)),"") | O90: =IFERROR(AVERAGE(R90,X90,AD90),"") -> 0 | P90: =IFERROR(INDEX([2]Лист1!$E:$E,AH90),"") -> 0 | Q90: =IFERROR(INDEX([2]Лист1!$I:$I,AH90),"") -> 0 | R90: =IFERROR(INDEX([2]Лист1!$V:$V,AH90),"") -> 0 | S90: =IFERROR(INDEX([2]Лист1!$L:$L,AH90),"") -> 0 | T90: =IFERROR(INDEX([2]Лист1!$J:$J,AH90),"") -> 0 | U90: =IFERROR(INDEX([2]Лист1!$K:$K,AH90),"") -> 0 | V90: =IFERROR(INDEX([2]Лист1!$E:$E,AI90),"") | W90: =IFERROR(INDEX([2]Лист1!$I:$I,AI90),"") | X90: =IFERROR(INDEX([2]Лист1!$V:$V,AI90),"") | Y90: =IFERROR(INDEX([2]Лист1!$L:$L,AI90),"") | Z90: =IFERROR(INDEX([2]Лист1!$J:$J,AI90),"") | AA90: =IFERROR(INDEX([2]Лист1!$K:$K,AI90),"") | AB90: =IFERROR(INDEX([2]Лист1!$E:$E,AJ90),"") | AC90: =IFERROR(INDEX([2]Лист1!$I:$I,AJ90),"") | AD90: =IFERROR(INDEX([2]Лист1!$V:$V,AJ90),"") | AE90: =IFERROR(INDEX([2]Лист1!$L:$L,AJ90),"") | AF90: =IFERROR(INDEX([2]Лист1!$J:$J,AJ90),"") | AG90: =IFERROR(INDEX([2]Лист1!$K:$K,AJ90),"") | AH90: =MATCH(L90,[2]Лист1!$A:$A,0) -> 6382 | AI90: =MATCH(M90,[2]Лист1!$A:$A,0) -> #N/A | AJ90: =MATCH(N90,[2]Лист1!$A:$A,0) -> #N/A
A91: 1 | B91: ЛСР-03-05-203ТМ | C91: 3 | E91: ТЦ_18.1.06.00_50_5503095632_05.07.2022_02 /КА п.44/ ЗАО "Сибгазстройдеталь" №897 | F91: Запорная арматура По типу 2с-25-1Н DN 150; pmax=1.10 MPag; tmax=80 °С / °C; Раб. среда:Вода химически обессоленная; Способ управления: Ручной привод; Тип присоединения: Под приварку, Кл. 4Н, угл.ст. | G91: шт. | H91: 1 | I91: 151166.68 | J91: =H91*I91 -> 151166.68 | K91: =J91/SUM($J$2:$J$1590) -> 0.0011837883 | L91: 7317 | M91: =IFERROR(INDEX([1]мтр!H:H,MATCH($F91,[1]мтр!$C:$C,0)),"") | N91: =IFERROR(INDEX([1]мтр!I:I,MATCH($F91,[1]мтр!$C:$C,0)),"") | O91: =IFERROR(AVERAGE(R91,X91,AD91),"") -> 0 | P91: =IFERROR(INDEX([2]Лист1!$E:$E,AH91),"") -> 0 | Q91: =IFERROR(INDEX([2]Лист1!$I:$I,AH91),"") -> 0 | R91: =IFERROR(INDEX([2]Лист1!$V:$V,AH91),"") -> 0 | S91: =IFERROR(INDEX([2]Лист1!$L:$L,AH91),"") -> 0 | T91: =IFERROR(INDEX([2]Лист1!$J:$J,AH91),"") -> 0 | U91: =IFERROR(INDEX([2]Лист1!$K:$K,AH91),"") -> 0 | V91: =IFERROR(INDEX([2]Лист1!$E:$E,AI91),"") | W91: =IFERROR(INDEX([2]Лист1!$I:$I,AI91),"") | X91: =IFERROR(INDEX([2]Лист1!$V:$V,AI91),"") | Y91: =IFERROR(INDEX([2]Лист1!$L:$L,AI91),"") | Z91: =IFERROR(INDEX([2]Лист1!$J:$J,AI91),"") | AA91: =IFERROR(INDEX([2]Лист1!$K:$K,AI91),"") | AB91: =IFERROR(INDEX([2]Лист1!$E:$E,AJ91),"") | AC91: =IFERROR(INDEX([2]Лист1!$I:$I,AJ91),"") | AD91: =IFERROR(INDEX([2]Лист1!$V:$V,AJ91),"") | AE91: =IFERROR(INDEX([2]Лист1!$L:$L,AJ91),"") | AF91: =IFERROR(INDEX([2]Лист1!$J:$J,AJ91),"") | AG91: =IFERROR(INDEX([2]Лист1!$K:$K,AJ91),"") | AH91: =MATCH(L91,[2]Лист1!$A:$A,0) -> 6383 | AI91: =MATCH(M91,[2]Лист1!$A:$A,0) -> #N/A | AJ91: =MATCH(N91,[2]Лист1!$A:$A,0) -> #N/A
A92: 1 | B92: ЛСР-03-05-202ТМ | C92: 3 | E92: ТЦ_23.7.01.02_31_3123315768_20.05.2022_02 / КА п.1 / Энергомаш ООО "Белэнергомаш-БЗЭМ" № 006-00073 | F92: Трубопроводы низкого давления, 4Н класса безопасности, материал - нж, Дн 57х3, 32х3, 18х2,5_Трубопроводы из н/ж. стали низкого давления: трубопроводы Ду < 80мм | G92: т | H92: 0.181 | I92: 799960.85 | J92: =H92*I92 -> 144792.91 | K92: =J92/SUM($J$2:$J$1590) -> 0.0011338753 | L92: =IFERROR(INDEX([1]мтр!G:G,MATCH($F92,[1]мтр!$C:$C,0)),"") -> 4861 | M92: =IFERROR(INDEX([1]мтр!H:H,MATCH($F92,[1]мтр!$C:$C,0)),"") -> 0 | N92: =IFERROR(INDEX([1]мтр!I:I,MATCH($F92,[1]мтр!$C:$C,0)),"") -> 0 | O92: =IFERROR(AVERAGE(R92,X92,AD92),"") -> 2050605.2 | P92: =IFERROR(INDEX([2]Лист1!$E:$E,AH92),"") -> Трубопроводы низкого давления из нержавеющей стали зданий UJA, UKD. Объём: 40 315 616 руб. / 6 074,16 кг = 6637 RUB/кг. Транспорт 5800 USD (Договор ЕОС-закупки №629007, №7720/220816 от 07.09.2022, АСЭ_Рускон) /40DV контейнер 25 т, класс груза - 2, загрузка 85%. | Q92: =IFERROR(INDEX([2]Лист1!$I:$I,AH92),"") -> т | R92: =IFERROR(INDEX([2]Лист1!$V:$V,AH92),"") -> 2050605.2 | S92: =IFERROR(INDEX([2]Лист1!$L:$L,AH92),"") -> 44753 | T92: =IFERROR(INDEX([2]Лист1!$J:$J,AH92),"") -> Белэнергомаш-БЗЭМ | U92: =IFERROR(INDEX([2]Лист1!$K:$K,AH92),"") -> Поставка трубопроводов по лоту 19677-248 Куд3;4. НМЦ от 11.07.2022, рассчитанная на основании п.1 раздела 3 главы 3 (приложения №8 к ЕОСЗ). | V92: =IFERROR(INDEX([2]Лист1!$E:$E,AI92),"") | W92: =IFERROR(INDEX([2]Лист1!$I:$I,AI92),"") | X92: =IFERROR(INDEX([2]Лист1!$V:$V,AI92),"") | Y92: =IFERROR(INDEX([2]Лист1!$L:$L,AI92),"") | Z92: =IFERROR(INDEX([2]Лист1!$J:$J,AI92),"") | AA92: =IFERROR(INDEX([2]Лист1!$K:$K,AI92),"") | AB92: =IFERROR(INDEX([2]Лист1!$E:$E,AJ92),"") | AC92: =IFERROR(INDEX([2]Лист1!$I:$I,AJ92),"") | AD92: =IFERROR(INDEX([2]Лист1!$V:$V,AJ92),"") | AE92: =IFERROR(INDEX([2]Лист1!$L:$L,AJ92),"") | AF92: =IFERROR(INDEX([2]Лист1!$J:$J,AJ92),"") | AG92: =IFERROR(INDEX([2]Лист1!$K:$K,AJ92),"") | AH92: =MATCH(L92,[2]Лист1!$A:$A,0) -> 4798 | AI92: =MATCH(M92,[2]Лист1!$A:$A,0) -> #N/A | AJ92: =MATCH(N92,[2]Лист1!$A:$A,0) -> #N/A
A93: 1 | B93: ЛСР-03-05-703ПС | C93: 3 | E93: ТЦ_21.1.08.01_77_7702680818_06.06.2022_01 | F93: Кабель для систем безопасности и передачи данных. Кабель симметричный, огнестойкий, с изолированными кремнийорганической резиной однопроволочными жилами, скрученными в пару, совместно с полиамидной пленкой в общем экране из ламинированной алюминиевой фольги и оболочкой из полимерной композиции, не содержащей галогенов. 4; III; QNC | G93: км | H93: 4.59 | I93: 30661.75 | J93: =H93*I93 -> 140737.43 | K93: =J93/SUM($J$2:$J$1590) -> 0.0011021167 | L93: =IFERROR(INDEX([1]мтр!G:G,MATCH($F93,[1]мтр!$C:$C,0)),"") | M93: =IFERROR(INDEX([1]мтр!H:H,MATCH($F93,[1]мтр!$C:$C,0)),"") | N93: =IFERROR(INDEX([1]мтр!I:I,MATCH($F93,[1]мтр!$C:$C,0)),"") | O93: =IFERROR(AVERAGE(R93,X93,AD93),"") | P93: =IFERROR(INDEX([2]Лист1!$E:$E,AH93),"") | Q93: =IFERROR(INDEX([2]Лист1!$I:$I,AH93),"") | R93: =IFERROR(INDEX([2]Лист1!$V:$V,AH93),"") | S93: =IFERROR(INDEX([2]Лист1!$L:$L,AH93),"") | T93: =IFERROR(INDEX([2]Лист1!$J:$J,AH93),"") | U93: =IFERROR(INDEX([2]Лист1!$K:$K,AH93),"") | V93: =IFERROR(INDEX([2]Лист1!$E:$E,AI93),"") | W93: =IFERROR(INDEX([2]Лист1!$I:$I,AI93),"") | X93: =IFERROR(INDEX([2]Лист1!$V:$V,AI93),"") | Y93: =IFERROR(INDEX([2]Лист1!$L:$L,AI93),"") | Z93: =IFERROR(INDEX([2]Лист1!$J:$J,AI93),"") | AA93: =IFERROR(INDEX([2]Лист1!$K:$K,AI93),"") | AB93: =IFERROR(INDEX([2]Лист1!$E:$E,AJ93),"") | AC93: =IFERROR(INDEX([2]Лист1!$I:$I,AJ93),"") | AD93: =IFERROR(INDEX([2]Лист1!$V:$V,AJ93),"") | AE93: =IFERROR(INDEX([2]Лист1!$L:$L,AJ93),"") | AF93: =IFERROR(INDEX([2]Лист1!$J:$J,AJ93),"") | AG93: =IFERROR(INDEX([2]Лист1!$K:$K,AJ93),"") | AH93: =MATCH(L93,[2]Лист1!$A:$A,0) -> #N/A | AI93: =MATCH(M93,[2]Лист1!$A:$A,0) -> #N/A | AJ93: =MATCH(N93,[2]Лист1!$A:$A,0) -> #N/A
A94: 1 | B94: ЛСР-03-05-203ТМ | C94: 3 | E94: ТЦ_18.1.06.00_50_5503095632_05.07.2022_02/ КА п.74/ ЗАО "Сибгазстройдеталь" №897 | F94: Арматура регулирующая По типу НГ27101-100 DN 100; pmax=0.5 MPa; tmax=40 °С / °C; Раб. среда: Топливо дизельное; Способ управления: Регулятор "До себя"; Тип присоединения: Под приварку Кл 4 Н, угл.ст._АКС27101-106, Клапан запорно-регулирующий сильфонный ручной, разноосные патрубки под приварку, DN100б Pp1,6МПа, ст20, 4Н | G94: шт. | H94: 1 | I94: 138523.83 | J94: =H94*I94 -> 138523.83 | K94: =J94/SUM($J$2:$J$1590) -> 0.001084782 | L94: =IFERROR(INDEX([1]мтр!G:G,MATCH($F94,[1]мтр!$C:$C,0)),"") | M94: =IFERROR(INDEX([1]мтр!H:H,MATCH($F94,[1]мтр!$C:$C,0)),"") | N94: =IFERROR(INDEX([1]мтр!I:I,MATCH($F94,[1]мтр!$C:$C,0)),"") | O94: =IFERROR(AVERAGE(R94,X94,AD94),"") | P94: =IFERROR(INDEX([2]Лист1!$E:$E,AH94),"") | Q94: =IFERROR(INDEX([2]Лист1!$I:$I,AH94),"") | R94: =IFERROR(INDEX([2]Лист1!$V:$V,AH94),"") | S94: =IFERROR(INDEX([2]Лист1!$L:$L,AH94),"") | T94: =IFERROR(INDEX([2]Лист1!$J:$J,AH94),"") | U94: =IFERROR(INDEX([2]Лист1!$K:$K,AH94),"") | V94: =IFERROR(INDEX([2]Лист1!$E:$E,AI94),"") | W94: =IFERROR(INDEX([2]Лист1!$I:$I,AI94),"") | X94: =IFERROR(INDEX([2]Лист1!$V:$V,AI94),"") | Y94: =IFERROR(INDEX([2]Лист1!$L:$L,AI94),"") | Z94: =IFERROR(INDEX([2]Лист1!$J:$J,AI94),"") | AA94: =IFERROR(INDEX([2]Лист1!$K:$K,AI94),"") | AB94: =IFERROR(INDEX([2]Лист1!$E:$E,AJ94),"") | AC94: =IFERROR(INDEX([2]Лист1!$I:$I,AJ94),"") | AD94: =IFERROR(INDEX([2]Лист1!$V:$V,AJ94),"") | AE94: =IFERROR(INDEX([2]Лист1!$L:$L,AJ94),"") | AF94: =IFERROR(INDEX([2]Лист1!$J:$J,AJ94),"") | AG94: =IFERROR(INDEX([2]Лист1!$K:$K,AJ94),"") | AH94: =MATCH(L94,[2]Лист1!$A:$A,0) -> #N/A | AI94: =MATCH(M94,[2]Лист1!$A:$A,0) -> #N/A | AJ94: =MATCH(N94,[2]Лист1!$A:$A,0) -> #N/A
A95: 1 | B95: ЛСР-03-05-206ТМ | C95: 3 | E95: ТЦ_12.2.04.12_32_3234045370_11.03.2022_02/ КА п.84/ ООО "Брянский завод теплоизоляционных материалов" №444 | F95: Маты базальтовые прошивные энергетические марки 50 в обкладке из стеклоткани Т-23 со всех сторон (МБПЭ 3-50 Т-23). (толщина 60 мм) _МПБ-50-СТ6 2000*1000*60 | G95: м3 | H95: 108.5 | I95: 1255.99 | J95: =H95*I95 -> 136274.92 | K95: =J95/SUM($J$2:$J$1590) -> 0.0010671707 | L95: =IFERROR(INDEX([1]мтр!G:G,MATCH($F95,[1]мтр!$C:$C,0)),"") -> 5187 | M95: =IFERROR(INDEX([1]мтр!H:H,MATCH($F95,[1]мтр!$C:$C,0)),"") -> 0 | N95: =IFERROR(INDEX([1]мтр!I:I,MATCH($F95,[1]мтр!$C:$C,0)),"") -> 0 | O95: =IFERROR(AVERAGE(R95,X95,AD95),"") -> 4403.9852 | P95: =IFERROR(INDEX([2]Лист1!$E:$E,AH95),"") -> Мат прошивной МПБ-50/СТ6 1500х500х50мм ТУ 23.99.19-002-02500345-2003. Транспорт экспертно 5% | Q95: =IFERROR(INDEX([2]Лист1!$I:$I,AH95),"") -> м3 | R95: =IFERROR(INDEX([2]Лист1!$V:$V,AH95),"") -> 4403.9852 | S95: =IFERROR(INDEX([2]Лист1!$L:$L,AH95),"") -> 44707 | T95: =IFERROR(INDEX([2]Лист1!$J:$J,AH95),"") -> ООО "Техэнергомаш" | U95: =IFERROR(INDEX([2]Лист1!$K:$K,AH95),"") -> ЕОС "Закупки" 866429 ТКП 0590 от 26.05.2022 | V95: =IFERROR(INDEX([2]Лист1!$E:$E,AI95),"") | W95: =IFERROR(INDEX([2]Лист1!$I:$I,AI95),"") | X95: =IFERROR(INDEX([2]Лист1!$V:$V,AI95),"") | Y95: =IFERROR(INDEX([2]Лист1!$L:$L,AI95),"") | Z95: =IFERROR(INDEX([2]Лист1!$J:$J,AI95),"") | AA95: =IFERROR(INDEX([2]Лист1!$K:$K,AI95),"") | AB95: =IFERROR(INDEX([2]Лист1!$E:$E,AJ95),"") | AC95: =IFERROR(INDEX([2]Лист1!$I:$I,AJ95),"") | AD95: =IFERROR(INDEX([2]Лист1!$V:$V,AJ95),"") | AE95: =IFERROR(INDEX([2]Лист1!$L:$L,AJ95),"") | AF95: =IFERROR(INDEX([2]Лист1!$J:$J,AJ95),"") | AG95: =IFERROR(INDEX([2]Лист1!$K:$K,AJ95),"") | AH95: =MATCH(L95,[2]Лист1!$A:$A,0) -> 4862 | AI95: =MATCH(M95,[2]Лист1!$A:$A,0) -> #N/A | AJ95: =MATCH(N95,[2]Лист1!$A:$A,0) -> #N/A
A96: 3 | B96: ЛСР-03-06-101С | C96: 3 | E96: 08.4.03.03-0008 | F96: Сталь арматурная рифленая свариваемая, класс A500С, диаметр 20 мм_Арматура А500С | G96: т | H96: 23.63 | I96: 5763.12 | J96: =H96*I96 -> 136182.53 | K96: =J96/SUM($J$2:$J$1590) -> 0.0010664472 | L96: =IFERROR(INDEX([1]мтр!G:G,MATCH($F96,[1]мтр!$C:$C,0)),"") -> 7509 | M96: =IFERROR(INDEX([1]мтр!H:H,MATCH($F96,[1]мтр!$C:$C,0)),"") -> 0 | N96: =IFERROR(INDEX([1]мтр!I:I,MATCH($F96,[1]мтр!$C:$C,0)),"") -> 0 | O96: =IFERROR(AVERAGE(R96,X96,AD96),"") -> 16541.58 | P96: =IFERROR(INDEX([2]Лист1!$E:$E,AH96),"") -> Арматура стальная периодического профиля, класс B500DWR, диаметр 6 - 40 мм | Q96: =IFERROR(INDEX([2]Лист1!$I:$I,AH96),"") -> т | R96: =IFERROR(INDEX([2]Лист1!$V:$V,AH96),"") -> 16541.58 | S96: =IFERROR(INDEX([2]Лист1!$L:$L,AH96),"") -> 44984 | T96: =IFERROR(INDEX([2]Лист1!$J:$J,AH96),"") -> N/A | U96: =IFERROR(INDEX([2]Лист1!$K:$K,AH96),"") -> Справочник сметных цен на строильные материалы, изделия и конструкции для строительства АЭС Эль-Дабаа, Арабская республика Египет. III квартал 2022 года, ГК Росатом №05-0077 | V96: =IFERROR(INDEX([2]Лист1!$E:$E,AI96),"") | W96: =IFERROR(INDEX([2]Лист1!$I:$I,AI96),"") | X96: =IFERROR(INDEX([2]Лист1!$V:$V,AI96),"") | Y96: =IFERROR(INDEX([2]Лист1!$L:$L,AI96),"") | Z96: =IFERROR(INDEX([2]Лист1!$J:$J,AI96),"") | AA96: =IFERROR(INDEX([2]Лист1!$K:$K,AI96),"") | AB96: =IFERROR(INDEX([2]Лист1!$E:$E,AJ96),"") | AC96: =IFERROR(INDEX([2]Лист1!$I:$I,AJ96),"") | AD96: =IFERROR(INDEX([2]Лист1!$V:$V,AJ96),"") | AE96: =IFERROR(INDEX([2]Лист1!$L:$L,AJ96),"") | AF96: =IFERROR(INDEX([2]Лист1!$J:$J,AJ96),"") | AG96: =IFERROR(INDEX([2]Лист1!$K:$K,AJ96),"") | AH96: =MATCH(L96,[2]Лист1!$A:$A,0) -> 6575 | AI96: =MATCH(M96,[2]Лист1!$A:$A,0) -> #N/A | AJ96: =MATCH(N96,[2]Лист1!$A:$A,0) -> #N/A
A97: 1 | B97: ЛСР-03-05-102С | C97: 3 | E97: 05.2.04.04-0005 | F97: Плиты бетонные и цементно-песчаные для тротуаров, полов и облицовки, марка 300, толщина 40 мм | G97: м2 | H97: 1393.4 | I97: 95.77 | J97: =H97*I97 -> 133445.92 | K97: =J97/SUM($J$2:$J$1590) -> 0.0010450168 | L97: =IFERROR(INDEX([1]мтр!G:G,MATCH($F97,[1]мтр!$C:$C,0)),"") -> 5318 | M97: =IFERROR(INDEX([1]мтр!H:H,MATCH($F97,[1]мтр!$C:$C,0)),"") -> 0 | N97: =IFERROR(INDEX([1]мтр!I:I,MATCH($F97,[1]мтр!$C:$C,0)),"") -> 0 | O97: =IFERROR(AVERAGE(R97,X97,AD97),"") -> 330.21726 | P97: =IFERROR(INDEX([2]Лист1!$E:$E,AH97),"") -> Плитка EUROLINE Berlin, 400х400х38 мм, серая. | Q97: =IFERROR(INDEX([2]Лист1!$I:$I,AH97),"") -> м2 | R97: =IFERROR(INDEX([2]Лист1!$V:$V,AH97),"") -> 330.21726 | S97: =IFERROR(INDEX([2]Лист1!$L:$L,AH97),"") -> 44378 | T97: =IFERROR(INDEX([2]Лист1!$J:$J,AH97),"") -> LEIER | U97: =IFERROR(INDEX([2]Лист1!$K:$K,AH97),"") -> Прайс лист ÁRLISTA DÍSZBURKOLATOK от 01.07.2021 | V97: =IFERROR(INDEX([2]Лист1!$E:$E,AI97),"") | W97: =IFERROR(INDEX([2]Лист1!$I:$I,AI97),"") | X97: =IFERROR(INDEX([2]Лист1!$V:$V,AI97),"") | Y97: =IFERROR(INDEX([2]Лист1!$L:$L,AI97),"") | Z97: =IFERROR(INDEX([2]Лист1!$J:$J,AI97),"") | AA97: =IFERROR(INDEX([2]Лист1!$K:$K,AI97),"") | AB97: =IFERROR(INDEX([2]Лист1!$E:$E,AJ97),"") | AC97: =IFERROR(INDEX([2]Лист1!$I:$I,AJ97),"") | AD97: =IFERROR(INDEX([2]Лист1!$V:$V,AJ97),"") | AE97: =IFERROR(INDEX([2]Лист1!$L:$L,AJ97),"") | AF97: =IFERROR(INDEX([2]Лист1!$J:$J,AJ97),"") | AG97: =IFERROR(INDEX([2]Лист1!$K:$K,AJ97),"") | AH97: =MATCH(L97,[2]Лист1!$A:$A,0) -> 3258 | AI97: =MATCH(M97,[2]Лист1!$A:$A,0) -> #N/A | AJ97: =MATCH(N97,[2]Лист1!$A:$A,0) -> #N/A
A98: 1 | B98: ЛСР-03-05-102С | C98: 3 | E98: 04.3.01.09-0018 | F98: Раствор готовый кладочный, цементный, М300_Раствор цементно-песчаный М300 | G98: м3 | H98: 186.5694 | I98: 711.5 | J98: =H98*I98 -> 132744.13 | K98: =J98/SUM($J$2:$J$1590) -> 0.0010395211 | L98: =IFERROR(INDEX([1]мтр!G:G,MATCH($F98,[1]мтр!$C:$C,0)),"") -> 3738 | M98: =IFERROR(INDEX([1]мтр!H:H,MATCH($F98,[1]мтр!$C:$C,0)),"") -> 0 | N98: =IFERROR(INDEX([1]мтр!I:I,MATCH($F98,[1]мтр!$C:$C,0)),"") -> 0 | O98: =IFERROR(AVERAGE(R98,X98,AD98),"") -> 817.52736 | P98: =IFERROR(INDEX([2]Лист1!$E:$E,AH98),"") -> Раствор готовый кладочный цементный марки 200, оценка по карте АЭС Руппур М200Пк3 РосСЭМ | Q98: =IFERROR(INDEX([2]Лист1!$I:$I,AH98),"") -> м3 | R98: =IFERROR(INDEX([2]Лист1!$V:$V,AH98),"") -> 817.52736 | S98: =IFERROR(INDEX([2]Лист1!$L:$L,AH98),"") -> 44370 | T98: =IFERROR(INDEX([2]Лист1!$J:$J,AH98),"") -> N/A | U98: =IFERROR(INDEX([2]Лист1!$K:$K,AH98),"") -> оценка по карте АЭС Руппур М200Пк3 РосСЭМ | V98: =IFERROR(INDEX([2]Лист1!$E:$E,AI98),"") | W98: =IFERROR(INDEX([2]Лист1!$I:$I,AI98),"") | X98: =IFERROR(INDEX([2]Лист1!$V:$V,AI98),"") | Y98: =IFERROR(INDEX([2]Лист1!$L:$L,AI98),"") | Z98: =IFERROR(INDEX([2]Лист1!$J:$J,AI98),"") | AA98: =IFERROR(INDEX([2]Лист1!$K:$K,AI98),"") | AB98: =IFERROR(INDEX([2]Лист1!$E:$E,AJ98),"") | AC98: =IFERROR(INDEX([2]Лист1!$I:$I,AJ98),"") | AD98: =IFERROR(INDEX([2]Лист1!$V:$V,AJ98),"") | AE98: =IFERROR(INDEX([2]Лист1!$L:$L,AJ98),"") | AF98: =IFERROR(INDEX([2]Лист1!$J:$J,AJ98),"") | AG98: =IFERROR(INDEX([2]Лист1!$K:$K,AJ98),"") | AH98: =MATCH(L98,[2]Лист1!$A:$A,0) -> 3497 | AI98: =MATCH(M98,[2]Лист1!$A:$A,0) -> #N/A | AJ98: =MATCH(N98,[2]Лист1!$A:$A,0) -> #N/A
A99: 1 | B99: ЛСР-03-05-206ТМ | C99: 3 | E99: 19.1.01.04-0062 | F99: Воздуховоды из тонколистовой коррозионно-стойкой стали толщиной: 2,0 мм, периметром более 1000 мм_Короб 440х1190; S= ((440х2+1190*2)/1000х80)= 260,8м2 | G99: м2 | H99: 260.8 | I99: 505.4 | J99: =H99*I99 -> 131808.32 | K99: =J99/SUM($J$2:$J$1590) -> 0.0010321927 | L99: =IFERROR(INDEX([1]мтр!G:G,MATCH($F99,[1]мтр!$C:$C,0)),"") | M99: =IFERROR(INDEX([1]мтр!H:H,MATCH($F99,[1]мтр!$C:$C,0)),"") | N99: =IFERROR(INDEX([1]мтр!I:I,MATCH($F99,[1]мтр!$C:$C,0)),"") | O99: =IFERROR(AVERAGE(R99,X99,AD99),"") | P99: =IFERROR(INDEX([2]Лист1!$E:$E,AH99),"") | Q99: =IFERROR(INDEX([2]Лист1!$I:$I,AH99),"") | R99: =IFERROR(INDEX([2]Лист1!$V:$V,AH99),"") | S99: =IFERROR(INDEX([2]Лист1!$L:$L,AH99),"") | T99: =IFERROR(INDEX([2]Лист1!$J:$J,AH99),"") | U99: =IFERROR(INDEX([2]Лист1!$K:$K,AH99),"") | V99: =IFERROR(INDEX([2]Лист1!$E:$E,AI99),"") | W99: =IFERROR(INDEX([2]Лист1!$I:$I,AI99),"") | X99: =IFERROR(INDEX([2]Лист1!$V:$V,AI99),"") | Y99: =IFERROR(INDEX([2]Лист1!$L:$L,AI99),"") | Z99: =IFERROR(INDEX([2]Лист1!$J:$J,AI99),"") | AA99: =IFERROR(INDEX([2]Лист1!$K:$K,AI99),"") | AB99: =IFERROR(INDEX([2]Лист1!$E:$E,AJ99),"") | AC99: =IFERROR(INDEX([2]Лист1!$I:$I,AJ99),"") | AD99: =IFERROR(INDEX([2]Лист1!$V:$V,AJ99),"") | AE99: =IFERROR(INDEX([2]Лист1!$L:$L,AJ99),"") | AF99: =IFERROR(INDEX([2]Лист1!$J:$J,AJ99),"") | AG99: =IFERROR(INDEX([2]Лист1!$K:$K,AJ99),"") | AH99: =MATCH(L99,[2]Лист1!$A:$A,0) -> #N/A | AI99: =MATCH(M99,[2]Лист1!$A:$A,0) -> #N/A | AJ99: =MATCH(N99,[2]Лист1!$A:$A,0) -> #N/A
A100: 1 | B100: ЛСР-03-05-102С | C100: 3 | E100: 01.7.15.07-0086 | F100: Дюбель-гвоздь размером 10x240 мм_(расход 9 шт/м2) | G100: ШТ | H100: 24380 | I100: 5.27 | J100: =H100*I100 -> 128482.6 | K100: =J100/SUM($J$2:$J$1590) -> 0.001006149 | L100: =IFERROR(INDEX([1]мтр!G:G,MATCH($F100,[1]мтр!$C:$C,0)),"") | M100: =IFERROR(INDEX([1]мтр!H:H,MATCH($F100,[1]мтр!$C:$C,0)),"") | N100: =IFERROR(INDEX([1]мтр!I:I,MATCH($F100,[1]мтр!$C:$C,0)),"") | O100: =IFERROR(AVERAGE(R100,X100,AD100),"") | P100: =IFERROR(INDEX([2]Лист1!$E:$E,AH100),"") | Q100: =IFERROR(INDEX([2]Лист1!$I:$I,AH100),"") | R100: =IFERROR(INDEX([2]Лист1!$V:$V,AH100),"") | S100: =IFERROR(INDEX([2]Лист1!$L:$L,AH100),"") | T100: =IFERROR(INDEX([2]Лист1!$J:$J,AH100),"") | U100: =IFERROR(INDEX([2]Лист1!$K:$K,AH100),"") | V100: =IFERROR(INDEX([2]Лист1!$E:$E,AI100),"") | W100: =IFERROR(INDEX([2]Лист1!$I:$I,AI100),"") | X100: =IFERROR(INDEX([2]Лист1!$V:$V,AI100),"") | Y100: =IFERROR(INDEX([2]Лист1!$L:$L,AI100),"") | Z100: =IFERROR(INDEX([2]Лист1!$J:$J,AI100),"") | AA100: =IFERROR(INDEX([2]Лист1!$K:$K,AI100),"") | AB100: =IFERROR(INDEX([2]Лист1!$E:$E,AJ100),"") | AC100: =IFERROR(INDEX([2]Лист1!$I:$I,AJ100),"") | AD100: =IFERROR(INDEX([2]Лист1!$V:$V,AJ100),"") | AE100: =IFERROR(INDEX([2]Лист1!$L:$L,AJ100),"") | AF100: =IFERROR(INDEX([2]Лист1!$J:$J,AJ100),"") | AG100: =IFERROR(INDEX([2]Лист1!$K:$K,AJ100),"") | AH100: =MATCH(L100,[2]Лист1!$A:$A,0) -> #N/A | AI100: =MATCH(M100,[2]Лист1!$A:$A,0) -> #N/A | AJ100: =MATCH(N100,[2]Лист1!$A:$A,0) -> #N/A
...
